Workbook
Name BatCostIDR: Assumptions!$E$28
Name BatCostUSD: Assumptions!$E$13
Name BatDegradation: Assumptions!$E$24
Name BatteriesRow: Assumptions!$B$46:$F$46
Name CapexInfl: Assumptions!$E$12
Name CarbonMonetization: Assumptions!$E$35
Name CarbonPriceID: Assumptions!$E$15
Name CarbonPriceUSD: Assumptions!$E$16
Name Churn: Assumptions!$E$27
Name CourierGrowth: Assumptions!$E$23
Name CouriersPerHub: Assumptions!$B$44:$F$44
Name DieselPrice: Assumptions!$E$14
Name EVGrowth: Assumptions!$E$22
Name FX: Assumptions!$E$11
Name HomesPerMG: Assumptions!$B$45:$F$45
Name HubCapex: Assumptions!$E$31
Name HubsRow: Assumptions!$B$42:$F$42
Name HubsY1: Assumptions!$E$36
Name HubUtilization: Assumptions!$E$25
Name Inflation: Assumptions!$E$9
Name MicroCapex: Assumptions!$E$32
Name MicrogridsRow: Assumptions!$B$43:$F$43
Name MicrogridsY1: Assumptions!$E$37
Name MicrogridUptime: Assumptions!$E$26
Name MicroPrice: Assumptions!$E$30
Name OEMARPU: Assumptions!$E$34
Name OEMcustomers: Assumptions!$B$47:$F$47
Name PassportARPU: Assumptions!$E$33
Name Scenario: Assumptions!$B$4
Name ScenIdx: Assumptions!$B$5
Name SwapPrice: Assumptions!$E$29
Name TaxRate: Assumptions!$E$17
Name WACC: Assumptions!$E$10

Sheet Contents
A1: VOLTLOOP — CONTENTS
A2: Click any sheet to open. Grouped by section.
A4: NAVIGATION & CONTROL
A5: Contents
A6: Reading Guide
A7: Model Checks
A8: FD_Decision_Log
A10: FINANCE MODEL
A11: Funding_Plan
A12: BreakEven_Bridge
A13: Valuation
A14: Sensitivity_Y5_Breakeven
... A100: Tropical_Test_Protocol

Sheet Funding_Plan
A1: VOLTLOOP — FUNDING PLAN (close the cash gap, blended financing)
A2: All values IDR. Blue = [Assumption] input (founder-adjustable). New funding sized so ending cash ≥ buffer every year. Drives Cash Flow rows 16-17.
C3: Y1 | D3: Y2 | E3: Y3 | F3: Y4 | G3: Y5 | H3: 5-Yr Total
A4: EXISTING FUNDING (original model)
A5: Existing equity raises [Original] | C5: 3500000000 | D5: 6000000000 | E5: 20000000000 | F5: 30000000000 | G5: 0 | H5: =SUM(C5:G5) -> 59500000000
A6: Existing debt raises [Original] | C6: 0 | D6: 2000000000 | E6: 5000000000 | F6: 8000000000 | G6: 10000000000 | H6: =SUM(C6:G6) -> 25000000000
A7: Existing total funding | C7: =C5+C6 -> 3500000000 | D7: =D5+D6 -> 8000000000 | E7: =E5+E6 -> 25000000000 | F7: =F5+F6 -> 38000000000 | G7: =G5+G6 -> 10000000000 | H7: =SUM(C7:G7) -> 84500000000
A8: Ending cash — original plan [reference snapshot] | C8: -250331294 | D8: -1436375808 | E8: 110502065 | F8: 8019105963 | G8: -10116411077 | H8: =MIN(C8:G8) -> -10116411077
A9: - Min ending cash (original) | C9: =MIN(C8:G8) -> -10116411077
A11: NEW FUNDING REQUIRED (audit fix — blended)
A12: Target minimum cash buffer [Assumption] | C12: 3000000000 | D12: - floor applied to every year's ending cash
A13: New equity raise [Assumption] | C13: 3500000000 | D13: 1500000000 | E13: 0 | F13: 0 | G13: 6000000000 | H13: =SUM(C13:G13) -> 11000000000
A14: New debt facility [Assumption] | C14: 0 | D14: 0 | E14: 0 | F14: 0 | G14: 2500000000 | H14: =SUM(C14:G14) -> 2500000000
A15: New asset financing (battery-backed) [Assumption] | C15: 0 | D15: 0 | E15: 0 | F15: 0 | G15: 2000000000 | H15: =SUM(C15:G15) -> 2000000000
A16: Total new funding | C16: =SUM(C13:C15) -> 3500000000 | D16: =SUM(D13:D15) -> 1500000000 | E16: =SUM(E13:E15) -> 0 | F16: =SUM(F13:F15) -> 0 | G16: =SUM(G13:G15) -> 10500000000 | H16: =SUM(C16:G16) -> 15500000000
A17: Cumulative new funding | C17: =C16 -> 3500000000 | D17: =C17+D16 -> 5000000000 | E17: =D17+E16 -> 5000000000 | F17: =E17+F16 -> 5000000000 | G17: =F17+G16 -> 15500000000 | H17: =SUM(C17:G17) -> 34000000000
A19: PRO-FORMA FUNDING (feeds Cash Flow)
A20: Total equity raises (existing + new) - CF row 16 | C20: =C5+C13 -> 7000000000 | D20: =D5+D13 -> 7500000000 | E20: =E5+E13 -> 20000000000 | F20: =F5+F13 -> 30000000000 | G20: =G5+G13 -> 6000000000 | H20: =SUM(C20:G20) -> 70500000000
A21: Total debt raises (existing + facility + asset fin) - CF row 17 | C21: =C6+C14+C15 -> 0 | D21: =D6+D14+D15 -> 2000000000 | E21: =E6+E14+E15 -> 5000000000 | F21: =F6+F14+F15 -> 8000000000 | G21: =G6+G14+G15 -> 14500000000 | H21: =SUM(C21:G21) -> 29500000000
A22: Pro-forma ending cash (live from Cash Flow) | C22: ='Cash Flow'!C22 -> 3.2496687e+09 | D22: ='Cash Flow'!D22 -> 4.5624008e+09 | E22: ='Cash Flow'!E22 -> 8.7723979e+09 | F22: ='Cash Flow'!F22 -> 2.1340017e+10 | G22: ='Cash Flow'!G22 -> 2.0109811e+10 | H22: =MIN(C22:G22) -> 3.2496687e+09
A23: - Min ending cash (pro-forma) — must be ≥ buffer | C23: =MIN(C22:G22) -> 3.2496687e+09 | E23: =IF(MIN(C22:G22)>=C12,"OK above buffer",IF(MIN(C22:G22)>=0,"OK but thin","FAIL — still negative")) -> OK above buffer
A25: FUNDING SUFFICIENCY
A26: Cumulative funding (equity+debt, pro-forma) | C26: =C20+C21 -> 7000000000 | D26: =C26+D20+D21 -> 16500000000 | E26: =D26+E20+E21 -> 41500000000 | F26: =E26+F20+F21 -> 79500000000 | G26: =F26+G20+G21 -> 100000000000
A27: Gross PP&E deployed (cumulative) | C27: ='Balance Sheet'!C10 -> 2.6798955e+09 | D27: ='Balance Sheet'!D10 -> 9.1387726e+09 | E27: ='Balance Sheet'!E10 -> 2.8321152e+10 | F27: ='Balance Sheet'!F10 -> 5.6838415e+10 | G27: ='Balance Sheet'!G10 -> 9.1327074e+10
A28: Funding surplus / (gap) — must be ≥ 0 | C28: =C26-C27 -> 4.3201045e+09 | D28: =D26-D27 -> 7.3612274e+09 | E28: =E26-E27 -> 1.3178848e+10 | F28: =F26-F27 -> 2.2661585e+10 | G28: =G26-G27 -> 8.6729261e+09
A29: Status | C29: =IF(MIN(C28:G28)>=0,"OK fully funded","GAP remains") -> OK fully funded
A31: DILUTION IMPACT (incremental round, this audit)
A32: Pre-money valuation [Assumption] | C32: 120000000000 | D32: - placeholder; refine from Valuation sheet (FD-03)
A33: New equity raised (this round, cumulative) | C33: =H13 -> 11000000000
A34: Post-money valuation | C34: =C32+C33 -> 131000000000
A35: New investor ownership % | C35: =C33/C34 -> 0.083969466
A36: Existing shareholders ownership % (post) | C36: =1-C35 -> 0.91603053
A37: Note | C37: Incremental dilution on the NEW Rp 11B equity only. Prior rounds (Rp 59.5B) already in the cap table; full cap table lives in Investor Returns.

Sheet Reading Guide
A1: VOLTLOOP — READING GUIDE
A2: How to read this workbook: a 5-minute path for a first look, then the full build order. Click any sheet name to jump.
A4: 5-MINUTE INVESTOR PATH
A5: Step | B5: Sheet | C5: What it answers
A6: 1 | B6: Exec_Fin_Dashboard | C6: The whole picture: revenue, EBITDA, cash, NPV, finance score
A7: 2 | B7: 01_Executive_Overview | C7: The pitch: problem, solution, market, why now
A8: 3 | B8: Cohort_Economics | C8: Does ONE mature hub make money? (the core question)
A9: 4 | B9: BreakEven_Bridge | C9: How Y5 net income reaches break-even (+Rp0.89B) — TARGET, driven by assumed operating levers (not yet pilot-proven)
A10: 5 | B10: Funding_Plan | C10: Is the cash enough? Funding gap closed, buffer held
A11: 6 | B11: FD_Decision_Log | C11: What decisions are still open before scaling
A13: FULL BUILD ORDER (how the model flows, left to right)
A14: # | B14: Section / lead sheet | C14: What it covers
A15: 1 | B15: Contents | C15: Index of all sheets & how to read this workbook
A16: 2 | B16: Contents | C16: Index of all sheets by section
A17: 3 | B17: 01_Executive_Overview | C17: Business story: problem, solution, target market
A18: 4 | B18: Market | C18: Problem, market size (TAM/SAM/SOM), customers, competitors
A19: 5 | B19: System_Architecture | C19: Product & technology: VoltSwap, VoltOS, VoltSmart, VoltGrid + BOMs
A20: 6 | B20: Assumptions | C20: The input engine — every key driver lives here
A21: 7 | B21: Revenue Model | C21: How money is made: price × volume, per stream
A22: 8 | B22: Swap Hub Econ | C22: Unit economics per hub & microgrid (feeds Cohort_Economics)
A23: 9 | B23: Cost_Drivers | C23: Cost structure (COGS, opex) and Capex Schedule
A24: 10 | B24: P&L | C24: Income statement → Cash Flow → Balance Sheet (3-statement, linked)
A25: 11 | B25: Funding_Plan | C25: Funding plan: blended financing closes the cash gap + buffer
A26: 12 | B26: BreakEven_Bridge | C26: FD-11: assumed operating levers that take Y5 NI from -5.5B to +0.9B (target, not pilot-proven)
... A30: 16 | B30: Assumptions_Log | C30: Audit trail: Assumptions_Log (every assumption, source, status), Change_Log (every edit), FD_Decision_Log (open decisions)
A32: BOTTOM LINE
A33: Capex-heavy energy-infrastructure bet, not a 5-year profit story. Funding gap is closed ON PLAN (assumes the Rp11B equity + Rp4.5B debt raise is completed). Y5 net income reaches break-even (+Rp0.9B) and EBITDA turns positive from Y3 ONLY IF the +Rp6.66B operating levers prove out — today these are assumptions, not pilot data. The gating risk: one mature hub still loses money at base (-Rp93.6M/yr); scale only after hub EBITDA > 0. Valuation is almost entirely terminal-value-driven (NPV excluding terminal is negative), and at the current Rp120B pre-money the investor MOIC is below 1x in every scenario. Verdict: worth an angel/seed conversation; NOT institutional-ready until (1) hub economics are proven, (2) the break-even levers are validated, and (3) pre-money is aligned to intrinsic value.
A35: KEY RISKS — READ BEFORE THE NUMBERS
A36: 1. Valuation ~100% terminal-dependent: NPV excluding terminal value is negative (-Rp46B). Enterprise value is positive only because of the terminal/exit value.
A37: 2. Investor MOIC < 1x in ALL scenarios at the current Rp120B pre-money (Base 0.29x). Entry valuation must come down toward intrinsic equity (~Rp38B base) for investors to make money.
A38: 3. Y5 break-even and EBITDA-positive-from-Y3 both depend on +Rp6.66B operating levers labelled [Assumption] (VoltOS/VoltSmart, anchor fleet, opex, battery lifecycle) — not yet validated in a pilot.
A39: 4. One mature hub still loses money at base case (-Rp93.6M/yr). Expansion is gated until mature-hub EBITDA turns positive; target case shows +Rp255.9M/hub is reachable.
A40: 5. Funding sufficiency and 'no negative cash' hold ON PLAN — they assume the new raise is completed. Numbers are model outputs; figures sourced from the pitch deck are unchanged.
A41: 6. Model ties to the pitch deck: revenue, COGS, EBITDA, break-even Year 3, NI-positive Year 5, and min cash all MATCH (see Deck_Reconciliation). Two deck claims are NOT reproduced: net margin 36% (model ~1.4% after D&A) and the larger ~Rp122B funding ask.

Sheet Valuation
A1: VOLTLOOP — 5-YEAR DCF VALUATION (with & without terminal value)
A2: Infrastructure-style valuation: long-lived assets, terminal/exit value at Y5. Blue = [Assumption]. References live P&L, Capex, Balance Sheet.
A4: WACC BUILD-UP (CAPM / Damodaran)
A5: Risk-free rate — Indonesia 10Y govt [Assumption] | C5: 0.068 | D5: Bank Indonesia / IBPA INDOGB 10Y — verify dated
A6: Equity risk premium — Indonesia [Assumption] | C6: 0.085 | D6: Damodaran country ERP (Indonesia)
A7: Levered beta [Assumption] | C7: 1.3 | D7: Energy-infra / early-stage proxy
A8: Cost of equity = rf + β×ERP | C8: =C5+C7*C6 -> 0.1785
A9: Pre-tax cost of debt [Assumption] | C9: 0.11
A10: Tax rate (live = TaxRate) | C10: =TaxRate -> 0.22
A11: After-tax cost of debt | C11: =C9*(1-C10) -> 0.0858
A12: Target equity weight [Assumption] | C12: 0.7
A13: Target debt weight | C13: =1-C12 -> 0.3
A14: WACC (build-up) - used in DCF | C14: =C12*C8+C13*C11 -> 0.15069
A15: Model named WACC (Assumptions) — reference | C15: =WACC -> 0.12 | D15: Note: build-up (~15%) > model 12%. DCF uses build-up; recommend aligning Assumptions!E10.
A17: FREE CASH FLOW TO FIRM (FCFF) — IDR
C18: Y1 | D18: Y2 | E18: Y3 | F18: Y4 | G18: Y5
A19: EBIT (operating income) | C19: ='P&L'!C18 -> -1.2178974e+09 | D19: ='P&L'!D18 -> -2.4478018e+09 | E19: ='P&L'!E18 -> -4.2105059e+09 | F19: ='P&L'!F18 -> -2.7665451e+09 | G19: ='P&L'!G18 -> 2.6437721e+09
A20: Less: cash tax on EBIT (0 if EBIT<0) | C20: =-MAX(0,C19)*$C$10 -> 0 | D20: =-MAX(0,D19)*$C$10 -> 0 | E20: =-MAX(0,E19)*$C$10 -> 0 | F20: =-MAX(0,F19)*$C$10 -> 0 | G20: =-MAX(0,G19)*$C$10 -> -5.8162986e+08
A21: NOPAT | C21: =C19+C20 -> -1.2178974e+09 | D21: =D19+D20 -> -2.4478018e+09 | E21: =E19+E20 -> -4.2105059e+09 | F21: =F19+F20 -> -2.7665451e+09 | G21: =G19+G20 -> 2.0621422e+09
A22: Plus: D&A | C22: =-'P&L'!C17 -> 5.4423206e+08 | D22: =-'P&L'!D17 -> 1.778252e+09 | E22: =-'P&L'!E17 -> 5.2245451e+09 | F22: =-'P&L'!F17 -> 1.0205055e+10 | G22: =-'P&L'!G17 -> 1.6331973e+10
A23: Less: Capex | C23: =-'Capex Schedule'!C11 -> -2.6798955e+09 | D23: =-'Capex Schedule'!D11 -> -6.4588771e+09 | E23: =-'Capex Schedule'!E11 -> -1.918238e+10 | F23: =-'Capex Schedule'!F11 -> -2.8517263e+10 | G23: =-'Capex Schedule'!G11 -> -3.4488659e+10
A24: Less: Δ net working capital (cash effect) | C24: ='Cash Flow'!C8 -> -1.9677041e+08 | D24: ='Cash Flow'!D8 -> -7.5884097e+08 | E24: ='Cash Flow'!E8 -> -2.0216623e+09 | F24: ='Cash Flow'!F8 -> -3.2536279e+09 | G24: ='Cash Flow'!G8 -> -4.1656628e+09
A25: FCFF | C25: =C21+C22+C23+C24 -> -3.5503313e+09 | D25: =D21+D22+D23+D24 -> -7.8872679e+09 | E25: =E21+E22+E23+E24 -> -2.0190003e+10 | F25: =F21+F22+F23+F24 -> -2.4332381e+10 | G25: =G21+G22+G23+G24 -> -2.0260206e+10
A26: Discount period (yrs) | C26: 1 | D26: 2 | E26: 3 | F26: 4 | G26: 5
A27: Discount factor @ WACC | C27: =1/(1+$C$14)^C26 -> 0.86904379 | D27: =1/(1+$C$14)^D26 -> 0.75523711 | E27: =1/(1+$C$14)^E26 -> 0.65633412 | F27: =1/(1+$C$14)^F26 -> 0.57038309 | G27: =1/(1+$C$14)^G26 -> 0.49568789
A28: PV of FCFF | C28: =C25*C27 -> -3.0853934e+09 | D28: =D25*D27 -> -5.9567574e+09 | E28: =E25*E27 -> -1.3251388e+10 | F28: =F25*F27 -> -1.3878779e+10 | G28: =G25*G27 -> -1.0042739e+10
A30: Sum PV of explicit FCFF = NPV WITHOUT terminal value | C30: =SUM(C28:G28) -> -4.6215056e+10
A32: TERMINAL / EXIT VALUE
A33: Exit EV/EBITDA multiple — base [Assumption] | C33: 10 | D33: High-growth energy infra; Y5 EBITDA still ramping
A34: Y5 EBITDA (live) | C34: ='P&L'!G15 -> 1.8975745e+10
A35: Terminal value (exit multiple) = mult × Y5 EBITDA | C35: =C33*C34 -> 1.8975745e+11
A36: PV of terminal value @ WACC | C36: =C35*G27 -> 9.406047e+10
A37: Perpetuity growth g [Assumption] | C37: 0.03
A38: TV (perpetuity, Gordon) = FCFF₅×(1+g)/(WACC−g) | C38: =G25*(1+C37)/(C14-C37) -> -1.7290589e+11
A39: PV of TV (perpetuity) | C39: =C38*G27 -> -8.5707357e+10
A40: Note | C40: Perpetuity is NOT meaningful while Y5 FCFF is negative (capex still ramping). Exit-multiple method is the primary basis.
A42: ENTERPRISE & EQUITY VALUE (base, exit-multiple)
A43: PV of explicit FCFF (Y1-Y5) | C43: =C30 -> -4.6215056e+10
A44: PV of terminal value | C44: =C36 -> 9.406047e+10
A45: Enterprise Value = NPV WITH terminal value | C45: =C43+C44 -> 4.7845414e+10
A46: Less: net debt at Y5 (debt − cash) | C46: =-('Balance Sheet'!G18+'Balance Sheet'!G19-'Balance Sheet'!G6) -> -9.390189e+09
A47: Equity Value (base case) | C47: =C45+C46 -> 3.8455225e+10
A49: VALUATION RANGE — Equity Value (vary exit multiple)
C50: Downside | D50: Base | E50: Upside
A51: Exit EV/EBITDA multiple [Assumption] | C51: 6 | D51: =C33 -> 10 | E51: 14
A52: PV of terminal value | C52: =C51*$C$34*$G$27 -> 5.6436282e+10 | D52: =D51*$C$34*$G$27 -> 9.406047e+10 | E52: =E51*$C$34*$G$27 -> 1.3168466e+11
A53: Enterprise Value (with terminal) | C53: =$C$30+C52 -> 1.0221226e+10 | D53: =$C$30+D52 -> 4.7845414e+10 | E53: =$C$30+E52 -> 8.5469601e+10
A54: Less: net debt (Y5) | C54: =$C$46 -> -9.390189e+09 | D54: =$C$46 -> -9.390189e+09 | E54: =$C$46 -> -9.390189e+09
A55: Equity Value | C55: =C53+C54 -> 8.3103669e+08 | D55: =D53+D54 -> 3.8455225e+10 | E55: =E53+E54 -> 7.6079412e+10
A57: INVESTOR RETURNS (new equity round)
A58: New equity invested (this round) | C58: =Funding_Plan!H13 -> 11000000000
A59: New investor ownership % | C59: =Funding_Plan!C35 -> 0.083969466
A60: Investor share of Y5 equity value (base, floored at 0) | C60: =MAX(0,D55)*C59 -> 3.2290647e+09
A61: MOIC (base, DCF-based) | C61: =C60/C58 -> 0.29355133
A62: Hold period (yrs) [Assumption] | C62: 4
A63: Gross IRR (base, DCF-based) | C63: =IF(C61>0,C61^(1/C62)-1,-1) -> -0.26392679
A64: Reality check | C64: At a strict 5-yr DCF, base equity value is negative — the round's implied valuation is NOT supported by 5-yr fundamentals. Value depends on EBITDA compounding beyond Y5 (see Cohort_Economics: mature hubs ARE profitable). Frame as long-horizon infrastructure, not a 5-yr exit.
A66: SENSITIVITY — Equity Value: WACC (down) vs Exit EV/EBITDA (across)
B67: WACC \ Exit x | C67: 6 | D67: 8 | E67: 10 | F67: 12 | G67: 14
B68: 0.11 | C68: =NPV($B68,$C$25:$G$25)+C$67*$C$34/(1+$B68)^5+$C$46 -> 5.7622221e+09 | D68: =NPV($B68,$C$25:$G$25)+D$67*$C$34/(1+$B68)^5+$C$46 -> 2.8284584e+10 | E68: =NPV($B68,$C$25:$G$25)+E$67*$C$34/(1+$B68)^5+$C$46 -> 5.0806947e+10 | F68: =NPV($B68,$C$25:$G$25)+F$67*$C$34/(1+$B68)^5+$C$46 -> 7.3329309e+10 | G68: =NPV($B68,$C$25:$G$25)+G$67*$C$34/(1+$B68)^5+$C$46 -> 9.5851671e+10
B69: 0.13 | C69: =NPV($B69,$C$25:$G$25)+C$67*$C$34/(1+$B69)^5+$C$46 -> 3.1740644e+09 | D69: =NPV($B69,$C$25:$G$25)+D$67*$C$34/(1+$B69)^5+$C$46 -> 2.3772613e+10 | E69: =NPV($B69,$C$25:$G$25)+E$67*$C$34/(1+$B69)^5+$C$46 -> 4.4371161e+10 | F69: =NPV($B69,$C$25:$G$25)+F$67*$C$34/(1+$B69)^5+$C$46 -> 6.4969709e+10 | G69: =NPV($B69,$C$25:$G$25)+G$67*$C$34/(1+$B69)^5+$C$46 -> 8.5568258e+10
B70: =C14 -> 0.15069 | C70: =NPV($B70,$C$25:$G$25)+C$67*$C$34/(1+$B70)^5+$C$46 -> 8.3103669e+08 | D70: =NPV($B70,$C$25:$G$25)+D$67*$C$34/(1+$B70)^5+$C$46 -> 1.9643131e+10 | E70: =NPV($B70,$C$25:$G$25)+E$67*$C$34/(1+$B70)^5+$C$46 -> 3.8455225e+10 | F70: =NPV($B70,$C$25:$G$25)+F$67*$C$34/(1+$B70)^5+$C$46 -> 5.7267318e+10 | G70: =NPV($B70,$C$25:$G$25)+G$67*$C$34/(1+$B70)^5+$C$46 -> 7.6079412e+10
B71: 0.17 | C71: =NPV($B71,$C$25:$G$25)+C$67*$C$34/(1+$B71)^5+$C$46 -> -1.0880481e+09 | D71: =NPV($B71,$C$25:$G$25)+D$67*$C$34/(1+$B71)^5+$C$46 -> 1.622205e+10 | E71: =NPV($B71,$C$25:$G$25)+E$67*$C$34/(1+$B71)^5+$C$46 -> 3.3532148e+10 | F71: =NPV($B71,$C$25:$G$25)+F$67*$C$34/(1+$B71)^5+$C$46 -> 5.0842246e+10 | G71: =NPV($B71,$C$25:$G$25)+G$67*$C$34/(1+$B71)^5+$C$46 -> 6.8152343e+10
B72: 0.19 | C72: =NPV($B72,$C$25:$G$25)+C$67*$C$34/(1+$B72)^5+$C$46 -> -2.8376192e+09 | D72: =NPV($B72,$C$25:$G$25)+D$67*$C$34/(1+$B72)^5+$C$46 -> 1.3065929e+10 | E72: =NPV($B72,$C$25:$G$25)+E$67*$C$34/(1+$B72)^5+$C$46 -> 2.8969477e+10 | F72: =NPV($B72,$C$25:$G$25)+F$67*$C$34/(1+$B72)^5+$C$46 -> 4.4873025e+10 | G72: =NPV($B72,$C$25:$G$25)+G$67*$C$34/(1+$B72)^5+$C$46 -> 6.0776573e+10

Sheet Model Checks
A1: VOLTLOOP — MODEL INTEGRITY CHECKS
A2: Live linkage and integrity checks across the three statements. Status updates automatically.
A4: # | B4: Check | C4: Basis | D4: Result | E4: Status
A5: 1 | B5: Balance Sheet balances (Assets = Liab + Equity), all 5 years | C5: Max |check| | D5: =MAX(ABS('Balance Sheet'!C26),ABS('Balance Sheet'!D26),ABS('Balance Sheet'!E26),ABS('Balance Sheet'!F26),ABS('Balance Sheet'!G26)) -> 0 | E5: =IF(D5<1000,"OK","Review Needed") -> OK
A6: 2 | B6: Net income (P&L) flows to Cash Flow, Y1 & Y5 | C6: Difference | D6: =ABS('Cash Flow'!C6-'P&L'!C21)+ABS('Cash Flow'!G6-'P&L'!G21) -> 0 | E6: =IF(D6<1,"OK","Review Needed") -> OK
A7: 3 | B7: Revenue (P&L) ties to Revenue Model, Y5 | C7: Difference | D7: =ABS('P&L'!G6-'Revenue Model'!G50) -> 0 | E7: =IF(D7<1,"OK","Review Needed") -> OK
A8: 4 | B8: Capex Schedule ties to Cash Flow investing, Y1 & Y5 | C8: Difference | D8: =ABS('Cash Flow'!C12+'Capex Schedule'!C11)+ABS('Cash Flow'!G12+'Capex Schedule'!G11) -> 0 | E8: =IF(D8<1,"OK","Review Needed") -> OK
A9: 5 | B9: Ending cash (Cash Flow) ties to Balance Sheet cash, Y5 | C9: Difference | D9: =ABS('Balance Sheet'!G6-'Cash Flow'!G22) -> 0 | E9: =IF(D9<1,"OK","Review Needed") -> OK
A10: 6 | B10: Minimum ending cash ≥ target buffer (Rp3.0B) | C10: Min cash | D10: =MIN('Cash Flow'!C22:G22) -> 3.2496687e+09 | E10: =IF(D10>=Funding_Plan!C12,"OK",IF(D10>=0,"Review Needed","Review Needed")) -> OK
A11: 7 | B11: EBITDA break-even year | C11: Year | D11: ='P&L'!H17 -> 3 | E11: =IF(D11<=5,"OK","Review Needed") -> OK
A12: 8 | B12: Net income positive by Year 5 | C12: Y5 net income | D12: ='P&L'!G21 -> 8.9214221e+08 | E12: =IF(D12>=0,"OK","Review Needed") -> OK
A13: 9 | B13: Funding sufficient vs deployment (min annual surplus ≥ 0) | C13: Min surplus | D13: =MIN(Funding_Plan!C28:G28) -> 4.3201045e+09 | E13: =IF(D13>=0,"OK","Review Needed") -> OK
A14: 10 | B14: Gross profit = Revenue − COGS, Y5 | C14: Difference | D14: =ABS('P&L'!G8-('P&L'!G6+'P&L'!G7)) -> 0 | E14: =IF(D14<1,"OK","Review Needed") -> OK
A15: 11 | B15: EBITDA = Gross profit − Operating expenses, Y5 | C15: Difference | D15: =ABS('P&L'!G15-('P&L'!G8+'P&L'!G12+'P&L'!G13+'P&L'!G14)) -> 0 | E15: =IF(D15<1,"OK","Review Needed") -> OK
A16: 12 | B16: No formula errors in core statements (P&L, Cash Flow, Balance Sheet) | C16: Error count | D16: {=SUMPRODUCT(--ISERROR('P&L'!C6:G21))+SUMPRODUCT(--ISERROR('Cash Flow'!C6:G22))+SUMPRODUCT(--ISERROR('Balance Sheet'!C6:G26))} -> 0 | E16: =IF(D16=0,"OK","Review Needed") -> OK
A18: SUMMARY
B19: Checks passing (OK) | C19: =COUNTIF(E5:E16,"OK") -> 12
B20: Checks needing review | C20: =COUNTIF(E5:E16,"Review Needed") -> 0
B22: Reviewed as of | C22: FY2026 model

Sheet Scenario_CF
A1: VOLTLOOP — SCENARIO CASH FLOWS (Conservative / Base / Aggressive, 5-Yr)
A2: Driver-based: each scenario = live base model × [Assumption] multipliers. Base column multipliers = 1.0 so Base ties to actual P&L/Cash Flow. Funding held at pro-forma plan to expose each scenario's gap.
A4: SCENARIO DRIVERS [Assumption] | B4: Conservative | C4: Base | D4: Aggressive
A5: Revenue multiplier | B5: 0.75 | C5: 1 | D5: 1.25
A6: Gross-margin delta (ppt) | B6: -0.05 | C6: 0 | D6: 0.05
A7: Opex multiplier | B7: 1 | C7: 1 | D7: 1.05
A8: Capex multiplier | B8: 0.85 | C8: 1 | D8: 1.15
A11: CONSERVATIVE (Rev ×0.75, GM −5ppt) | B11: Line (IDR) | C11: Y1 | D11: Y2 | E11: Y3 | F11: Y4 | G11: Y5
B12: Revenue | C12: ='P&L'!C6*$B$5 -> 338792340 | D12: ='P&L'!D6*$B$5 -> 2235132960 | E12: ='P&L'!E6*$B$5 -> 1.0586418e+10 | F12: ='P&L'!F6*$B$5 -> 2.6094104e+10 | G12: ='P&L'!G6*$B$5 -> 4.7960668e+10
B13: Gross margin % | C13: ='P&L'!C9+$B$6 -> -0.44132369 | D13: ='P&L'!D9+$B$6 -> 0.04019221 | E13: ='P&L'!E9+$B$6 -> 0.2931701 | F13: ='P&L'!F9+$B$6 -> 0.36988859 | G13: ='P&L'!G9+$B$6 -> 0.40263917
B14: EBITDA | C14: =C12*C13-('P&L'!C8-'P&L'!C15)*$B$7 -> -6.4641252e+08 | D14: =D12*D13-('P&L'!D8-'P&L'!D15)*$B$7 -> -8.4850368e+08 | E14: =E12*E13-('P&L'!E8-'P&L'!E15)*$B$7 -> -7.2626244e+08 | F14: =F12*F13-('P&L'!F8-'P&L'!F15)*$B$7 -> 2.4815994e+09 | G14: =G12*G13-('P&L'!G8-'P&L'!G15)*$B$7 -> 9.3414193e+09
B15: Capex | C15: ='Capex Schedule'!C11*$B$8 -> 2.2779112e+09 | D15: ='Capex Schedule'!D11*$B$8 -> 5.4900455e+09 | E15: ='Capex Schedule'!E11*$B$8 -> 1.6305023e+10 | F15: ='Capex Schedule'!F11*$B$8 -> 2.4239674e+10 | G15: ='Capex Schedule'!G11*$B$8 -> 2.931536e+10
B16: D&A | C16: ='P&L'!C17*$B$8 -> -4.6259725e+08 | D16: ='P&L'!D17*$B$8 -> -1.5115142e+09 | E16: ='P&L'!E17*$B$8 -> -4.4408633e+09 | F16: ='P&L'!F17*$B$8 -> -8.6742969e+09 | G16: ='P&L'!G17*$B$8 -> -1.3882177e+10
B17: Net income | C17: =C14+C16+'P&L'!C19+IF((C14+C16+'P&L'!C19)>0,-(C14+C16+'P&L'!C19)*TaxRate,0) -> -1.1090098e+09 | D17: =D14+D16+'P&L'!D19+IF((D14+D16+'P&L'!D19)>0,-(D14+D16+'P&L'!D19)*TaxRate,0) -> -2.3600179e+09 | E17: =E14+E16+'P&L'!E19+IF((E14+E16+'P&L'!E19)>0,-(E14+E16+'P&L'!E19)*TaxRate,0) -> -5.3671258e+09 | F17: =F14+F16+'P&L'!F19+IF((F14+F16+'P&L'!F19)>0,-(F14+F16+'P&L'!F19)*TaxRate,0) -> -6.8926975e+09 | G17: =G14+G16+'P&L'!G19+IF((G14+G16+'P&L'!G19)>0,-(G14+G16+'P&L'!G19)*TaxRate,0) -> -6.0407577e+09
B18: FCFF | C18: =(C14+C16)+IF((C14+C16)>0,-(C14+C16)*TaxRate,0)-C16-C15+'Cash Flow'!C8*$B$5 -> -3.0719015e+09 | D18: =(D14+D16)+IF((D14+D16)>0,-(D14+D16)*TaxRate,0)-D16-D15+'Cash Flow'!D8*$B$5 -> -6.9076799e+09 | E18: =(E14+E16)+IF((E14+E16)>0,-(E14+E16)*TaxRate,0)-E16-E15+'Cash Flow'!E8*$B$5 -> -1.8547532e+10 | F18: =(F14+F16)+IF((F14+F16)>0,-(F14+F16)*TaxRate,0)-F16-F15+'Cash Flow'!F8*$B$5 -> -2.4198295e+10 | G18: =(G14+G16)+IF((G14+G16)>0,-(G14+G16)*TaxRate,0)-G16-G15+'Cash Flow'!G8*$B$5 -> -2.3098188e+10
B19: Ending cash (pro-forma) | C19: =(C17-C16+'Cash Flow'!C8*$B$5)-C15+(Funding_Plan!C20+Funding_Plan!C21) -> 3.9280985e+09 | D19: =C19+(D17-D16+'Cash Flow'!D8*$B$5)-D15+(Funding_Plan!D20+Funding_Plan!D21) -> 6.5204186e+09 | E19: =D19+(E17-E16+'Cash Flow'!E8*$B$5)-E15+(Funding_Plan!E20+Funding_Plan!E21) -> 1.2772887e+10 | F19: =E19+(F17-F16+'Cash Flow'!F8*$B$5)-F15+(Funding_Plan!F20+Funding_Plan!F21) -> 2.5874592e+10 | G19: =F19+(G17-G16+'Cash Flow'!G8*$B$5)-G15+(Funding_Plan!G20+Funding_Plan!G21) -> 2.1776404e+10
A20: - NPV of FCFF @ WACC | C20: =NPV(Valuation!$C$14,C18:G18) -> -4.5311721e+10
A21: - Min ending cash | C21: =MIN(C19:G19) -> 3.9280985e+09
A22: - Break-even EBITDA year | C22: {=IFERROR(MATCH(1,INDEX((C14:G14>0)*1,0),0),"Not in 5yr")} -> 4
A25: BASE (= live model) | B25: Line (IDR) | C25: Y1 | D25: Y2 | E25: Y3 | F25: Y4 | G25: Y5
B26: Revenue | C26: ='P&L'!C6*$C$5 -> 451723120 | D26: ='P&L'!D6*$C$5 -> 2980177280 | E26: ='P&L'!E6*$C$5 -> 1.4115224e+10 | F26: ='P&L'!F6*$C$5 -> 3.4792139e+10 | G26: ='P&L'!G6*$C$5 -> 6.3947557e+10
B27: Gross margin % | C27: ='P&L'!C9+$C$6 -> -0.39132369 | D27: ='P&L'!D9+$C$6 -> 0.09019221 | E27: ='P&L'!E9+$C$6 -> 0.3431701 | F27: ='P&L'!F9+$C$6 -> 0.41988859 | G27: ='P&L'!G9+$C$6 -> 0.45263917
B28: EBITDA | C28: =C26*C27-('P&L'!C8-'P&L'!C15)*$C$7 -> -673665390 | D28: =D26*D27-('P&L'!D8-'P&L'!D15)*$C$7 -> -6.6954984e+08 | E28: =E26*E27-('P&L'!E8-'P&L'!E15)*$C$7 -> 1.0140392e+09 | F28: =F26*F27-('P&L'!F8-'P&L'!F15)*$C$7 -> 7.4385101e+09 | G28: =G26*G27-('P&L'!G8-'P&L'!G15)*$C$7 -> 1.8975745e+10
B29: Capex | C29: ='Capex Schedule'!C11*$C$8 -> 2.6798955e+09 | D29: ='Capex Schedule'!D11*$C$8 -> 6.4588771e+09 | E29: ='Capex Schedule'!E11*$C$8 -> 1.918238e+10 | F29: ='Capex Schedule'!F11*$C$8 -> 2.8517263e+10 | G29: ='Capex Schedule'!G11*$C$8 -> 3.4488659e+10
B30: D&A | C30: ='P&L'!C17*$C$8 -> -5.4423206e+08 | D30: ='P&L'!D17*$C$8 -> -1.778252e+09 | E30: ='P&L'!E17*$C$8 -> -5.2245451e+09 | F30: ='P&L'!F17*$C$8 -> -1.0205055e+10 | G30: ='P&L'!G17*$C$8 -> -1.6331973e+10
B31: Net income | C31: =C28+C30+'P&L'!C19+IF((C28+C30+'P&L'!C19)>0,-(C28+C30+'P&L'!C19)*TaxRate,0) -> -1.2178974e+09 | D31: =D28+D30+'P&L'!D19+IF((D28+D30+'P&L'!D19)>0,-(D28+D30+'P&L'!D19)*TaxRate,0) -> -2.4478018e+09 | E31: =E28+E30+'P&L'!E19+IF((E28+E30+'P&L'!E19)>0,-(E28+E30+'P&L'!E19)*TaxRate,0) -> -4.4105059e+09 | F31: =F28+F30+'P&L'!F19+IF((F28+F30+'P&L'!F19)>0,-(F28+F30+'P&L'!F19)*TaxRate,0) -> -3.4665451e+09 | G31: =G28+G30+'P&L'!G19+IF((G28+G30+'P&L'!G19)>0,-(G28+G30+'P&L'!G19)*TaxRate,0) -> 8.9214221e+08
B32: FCFF | C32: =(C28+C30)+IF((C28+C30)>0,-(C28+C30)*TaxRate,0)-C30-C29+'Cash Flow'!C8*$C$5 -> -3.5503313e+09 | D32: =(D28+D30)+IF((D28+D30)>0,-(D28+D30)*TaxRate,0)-D30-D29+'Cash Flow'!D8*$C$5 -> -7.8872679e+09 | E32: =(E28+E30)+IF((E28+E30)>0,-(E28+E30)*TaxRate,0)-E30-E29+'Cash Flow'!E8*$C$5 -> -2.0190003e+10 | F32: =(F28+F30)+IF((F28+F30)>0,-(F28+F30)*TaxRate,0)-F30-F29+'Cash Flow'!F8*$C$5 -> -2.4332381e+10 | G32: =(G28+G30)+IF((G28+G30)>0,-(G28+G30)*TaxRate,0)-G30-G29+'Cash Flow'!G8*$C$5 -> -2.0260206e+10
B33: Ending cash (pro-forma) | C33: =(C31-C30+'Cash Flow'!C8*$C$5)-C29+(Funding_Plan!C20+Funding_Plan!C21) -> 3.4496687e+09 | D33: =C33+(D31-D30+'Cash Flow'!D8*$C$5)-D29+(Funding_Plan!D20+Funding_Plan!D21) -> 5.0624008e+09 | E33: =D33+(E31-E30+'Cash Flow'!E8*$C$5)-E29+(Funding_Plan!E20+Funding_Plan!E21) -> 9.6723979e+09 | F33: =E33+(F31-F30+'Cash Flow'!F8*$C$5)-F29+(Funding_Plan!F20+Funding_Plan!F21) -> 2.2640017e+10 | G33: =F33+(G31-G30+'Cash Flow'!G8*$C$5)-G29+(Funding_Plan!G20+Funding_Plan!G21) -> 2.1709811e+10
A34: - NPV of FCFF @ WACC | C34: =NPV(Valuation!$C$14,C32:G32) -> -4.6215056e+10
A35: - Min ending cash | C35: =MIN(C33:G33) -> 3.4496687e+09
A36: - Break-even EBITDA year | C36: {=IFERROR(MATCH(1,INDEX((C28:G28>0)*1,0),0),"Not in 5yr")} -> 3
A39: AGGRESSIVE (Rev ×1.25, GM +5ppt) | B39: Line (IDR) | C39: Y1 | D39: Y2 | E39: Y3 | F39: Y4 | G39: Y5
B40: Revenue | C40: ='P&L'!C6*$D$5 -> 564653900 | D40: ='P&L'!D6*$D$5 -> 3725221600 | E40: ='P&L'!E6*$D$5 -> 1.764403e+10 | F40: ='P&L'!F6*$D$5 -> 4.3490173e+10 | G40: ='P&L'!G6*$D$5 -> 7.9934447e+10
B41: Gross margin % | C41: ='P&L'!C9+$D$6 -> -0.34132369 | D41: ='P&L'!D9+$D$6 -> 0.14019221 | E41: ='P&L'!E9+$D$6 -> 0.3931701 | F41: ='P&L'!F9+$D$6 -> 0.46988859 | G41: ='P&L'!G9+$D$6 -> 0.50263917
B42: EBITDA | C42: =C40*C41-('P&L'!C8-'P&L'!C15)*$D$7 -> -7.1446996e+08 | D42: =D40*D41-('P&L'!D8-'P&L'!D15)*$D$7 -> -4.630085e+08 | E42: =E40*E41-('P&L'!E8-'P&L'!E15)*$D$7 -> 2.9157272e+09 | F42: =F40*F41-('P&L'!F8-'P&L'!F15)*$D$7 -> 1.2906709e+10 | G42: =G40*G41-('P&L'!G8-'P&L'!G15)*$D$7 -> 2.9710288e+10
B43: Capex | C43: ='Capex Schedule'!C11*$D$8 -> 3.0818798e+09 | D43: ='Capex Schedule'!D11*$D$8 -> 7.4277086e+09 | E43: ='Capex Schedule'!E11*$D$8 -> 2.2059737e+10 | F43: ='Capex Schedule'!F11*$D$8 -> 3.2794852e+10 | G43: ='Capex Schedule'!G11*$D$8 -> 3.9661957e+10
B44: D&A | C44: ='P&L'!C17*$D$8 -> -6.2586687e+08 | D44: ='P&L'!D17*$D$8 -> -2.0449898e+09 | E44: ='P&L'!E17*$D$8 -> -6.0082268e+09 | F44: ='P&L'!F17*$D$8 -> -1.1735813e+10 | G44: ='P&L'!G17*$D$8 -> -1.8781769e+10
B45: Net income | C45: =C42+C44+'P&L'!C19+IF((C42+C44+'P&L'!C19)>0,-(C42+C44+'P&L'!C19)*TaxRate,0) -> -1.3403368e+09 | D45: =D42+D44+'P&L'!D19+IF((D42+D44+'P&L'!D19)>0,-(D42+D44+'P&L'!D19)*TaxRate,0) -> -2.5079983e+09 | E45: =E42+E44+'P&L'!E19+IF((E42+E44+'P&L'!E19)>0,-(E42+E44+'P&L'!E19)*TaxRate,0) -> -3.2924997e+09 | F45: =F42+F44+'P&L'!F19+IF((F42+F44+'P&L'!F19)>0,-(F42+F44+'P&L'!F19)*TaxRate,0) -> 3.6729824e+08 | G45: =G42+G44+'P&L'!G19+IF((G42+G44+'P&L'!G19)>0,-(G42+G44+'P&L'!G19)*TaxRate,0) -> 7.3542453e+09
B46: FCFF | C46: =(C42+C44)+IF((C42+C44)>0,-(C42+C44)*TaxRate,0)-C44-C43+'Cash Flow'!C8*$D$5 -> -4.0423128e+09 | D46: =(D42+D44)+IF((D42+D44)>0,-(D42+D44)*TaxRate,0)-D44-D43+'Cash Flow'!D8*$D$5 -> -8.8392684e+09 | E46: =(E42+E44)+IF((E42+E44)>0,-(E42+E44)*TaxRate,0)-E44-E43+'Cash Flow'!E8*$D$5 -> -2.1671087e+10 | F46: =(F42+F44)+IF((F42+F44)>0,-(F42+F44)*TaxRate,0)-F44-F43+'Cash Flow'!F8*$D$5 -> -2.4212776e+10 | G46: =(G42+G44)+IF((G42+G44)>0,-(G42+G44)*TaxRate,0)-G44-G43+'Cash Flow'!G8*$D$5 -> -1.7563022e+10
B47: Ending cash (pro-forma) | C47: =(C45-C44+'Cash Flow'!C8*$D$5)-C43+(Funding_Plan!C20+Funding_Plan!C21) -> 2.9576872e+09 | D47: =C47+(D45-D44+'Cash Flow'!D8*$D$5)-D43+(Funding_Plan!D20+Funding_Plan!D21) -> 3.6184189e+09 | E47: =D47+(E45-E44+'Cash Flow'!E8*$D$5)-E43+(Funding_Plan!E20+Funding_Plan!E21) -> 6.7473315e+09 | F47: =E47+(F45-F44+'Cash Flow'!F8*$D$5)-F43+(Funding_Plan!F20+Funding_Plan!F21) -> 1.9988556e+10 | G47: =F47+(G45-G44+'Cash Flow'!G8*$D$5)-G43+(Funding_Plan!G20+Funding_Plan!G21) -> 2.1755534e+10
A48: - NPV of FCFF @ WACC | C48: =NPV(Valuation!$C$14,C46:G46) -> -4.6928499e+10
A49: - Min ending cash | C49: =MIN(C47:G47) -> 2.9576872e+09
A50: - Break-even EBITDA year | C50: {=IFERROR(MATCH(1,INDEX((C42:G42>0)*1,0),0),"Not in 5yr")} -> 3

Sheet Cohort_Economics
A1: VOLTLOOP — MATURE HUB COHORT ECONOMICS (per hub, steady state)
A2: Shows whether a single MATURE swap hub is profitable on its own. Company-level net income is negative because of continuous new-hub capex/D&A + corporate overhead — not because units lose money. Blue = [Assumption], green links = named inputs.
A4: MATURE HUB ECONOMICS BY SCENARIO (live from 'Swap Hub Econ')
C5: ='Swap Hub Econ'!C5 -> Conservative | D5: ='Swap Hub Econ'!D5 -> Base | E5: ='Swap Hub Econ'!E5 -> Aggressive
A6: Capex per hub (IDR) | C6: ='Swap Hub Econ'!C6 -> 900000000 | D6: ='Swap Hub Econ'!D6 -> 800000000 | E6: ='Swap Hub Econ'!E6 -> 700000000
A7: Couriers per hub | C7: ='Swap Hub Econ'!C7 -> 30 | D7: ='Swap Hub Econ'!D7 -> 50 | E7: ='Swap Hub Econ'!E7 -> 70
A8: Utilization | C8: ='Swap Hub Econ'!C8 -> 0.4 | D8: ='Swap Hub Econ'!D8 -> 0.6 | E8: ='Swap Hub Econ'!E8 -> 0.8
A9: Subscription price (IDR/mo) | C9: ='Swap Hub Econ'!C9 -> 450000 | D9: ='Swap Hub Econ'!D9 -> 500000 | E9: ='Swap Hub Econ'!E9 -> 550000
A10: Monthly revenue/hub | C10: ='Swap Hub Econ'!C10 -> 5400000 | D10: ='Swap Hub Econ'!D10 -> 15000000 | E10: ='Swap Hub Econ'!E10 -> 30800000
A11: Monthly OPEX/hub | C11: ='Swap Hub Econ'!C15 -> 19000000 | D11: ='Swap Hub Econ'!D15 -> 22800000 | E11: ='Swap Hub Econ'!E15 -> 27200000
A12: Monthly EBITDA/hub | C12: ='Swap Hub Econ'!C16 -> -13600000 | D12: ='Swap Hub Econ'!D16 -> -7800000 | E12: ='Swap Hub Econ'!E16 -> 3600000
A13: Annual EBITDA/hub | C13: ='Swap Hub Econ'!C17 -> -163200000 | D13: ='Swap Hub Econ'!D17 -> -93600000 | E13: ='Swap Hub Econ'!E17 -> 43200000
A14: EBITDA margin | C14: ='Swap Hub Econ'!C18 -> -2.5185185 | D14: ='Swap Hub Econ'!D18 -> -0.52 | E14: ='Swap Hub Econ'!E18 -> 0.11688312
A15: Payback (months) | C15: ='Swap Hub Econ'!C19 -> -66.176471 | D15: ='Swap Hub Econ'!D19 -> -102.5641 | E15: ='Swap Hub Econ'!E19 -> 194.44444
A16: Breakeven utilization | C16: ='Swap Hub Econ'!C21 -> 1.4074074 | D16: ='Swap Hub Econ'!D21 -> 0.912 | E16: ='Swap Hub Econ'!E21 -> 0.70649351
A17: Unit verdict | C17: =IF(C13>0,"Positive ","NEGATIVE ") -> NEGATIVE | D17: =IF(D13>0,"Positive ","NEGATIVE ") -> NEGATIVE | E17: =IF(E13>0,"Positive ","NEGATIVE ") -> Positive
A19: BREAKEVEN GAP — BASE CASE (active scenario)
A20: Breakeven subscription price at 60% util | C20: ='Swap Hub Econ'!C32 -> 760000
A21: Current price | C21: ='Swap Hub Econ'!D9 -> 500000
A22: Price increase needed to break even | C22: ='Swap Hub Econ'!C33 -> 0.52
A23: Breakeven utilization needed (vs 60% now) | C23: ='Swap Hub Econ'!C35 -> 0.912
A25: KEY FINDING
A26: A mature hub is EBITDA-NEGATIVE at Base and Conservative assumptions (−Rp 93.6M/yr at Base). Units break even only at ~91% utilization, a +52% price increase, OR the Aggressive density (70 couriers/hub @ 80%). This — not just capex/D&A — is the root cause of company-level losses. It is the #1 thing to validate before raising. Routed to FOUNDER_DECISIONS.
A28: UTILIZATION SENSITIVITY — Base hub annual EBITDA
B29: Utilization - | C29: 0.4 | D29: 0.5 | E29: 0.6 | F29: 0.7 | G29: 0.8 | H29: 0.912
B30: Annual EBITDA | C30: =($D$7*C29*$D$9-'Swap Hub Econ'!$D$15)*12 -> -153600000 | D30: =($D$7*D29*$D$9-'Swap Hub Econ'!$D$15)*12 -> -123600000 | E30: =($D$7*E29*$D$9-'Swap Hub Econ'!$D$15)*12 -> -93600000 | F30: =($D$7*F29*$D$9-'Swap Hub Econ'!$D$15)*12 -> -63600000 | G30: =($D$7*G29*$D$9-'Swap Hub Econ'!$D$15)*12 -> -33600000 | H30: =($D$7*H29*$D$9-'Swap Hub Econ'!$D$15)*12 -> 0
A32: TURNAROUND LEVERS — PATH TO HUB EBITDA > 0 (blended) [Inference targets]
A33: Founder-adjustable targets. Blue = [Inference] (strategy, not from workbook). Base hub opex & EBITDA pulled live from Swap Hub Econ.
A34: LEVER A — Target swap price (IDR/mo) [Inference] | C34: 625000 | D34: vs base 500k / breakeven-only 760k
A35: LEVER B — Target utilization [Inference] | C35: 0.8 | D35: vs base 60% / breakeven-only 91%
A36: LEVER B2 — Couriers per hub (density) [Inference] | C36: 55 | D36: vs base 50 — density, not more hubs
A37: LEVER C — Opex efficiency cut % [Inference] | C37: 0.2 | D37: rent/staff/maint/battery handling; target 15-25%
A39: Base mature-hub EBITDA (live) | C39: ='Swap Hub Econ'!D17 -> -93600000
A40: New annual revenue = couriers × util × price × 12 | C40: =C36*C35*C34*12 -> 330000000
A41: New annual opex (fixed/var split — see row 71) | C41: =C71 -> 259737600
A42: Battery replacement reserve (2.5% rev) | C42: =C40*0.025 -> 8250000
A43: NEW mature-hub EBITDA (blended levers) | C43: =C40-C41-C42 -> 62012400
A44: Swing vs base | C44: =C43-C39 -> 155612400
A45: VERDICT | C45: =IF(C43>0,"Hub EBITDA-positive under blend - rollout unlock met","Still negative - push levers further") -> Hub EBITDA-positive under blend - rollout unlock met
A46: Caveat | B46: Opex cut applied to base-50-courier cost; higher density will raise some variable cost — re-estimate opex split (fixed vs variable) with pilot data before committing.
A48: SINGLE LEVER ALONE (why a blend is required)
A49: Price-only @760k (util 60%, 50 couriers) | C49: =50*0.6*760000*12-'Swap Hub Econ'!D15*12-(50*0.6*760000*12)*0.025 -> -6840000
A50: Utilization-only @91% (price 500k) | C50: =50*0.91*500000*12-'Swap Hub Econ'!D15*12-(50*0.91*500000*12)*0.025 -> -7425000
A51: Opex-cut-only @20% (price 500k, util 60%) | C51: =50*0.6*500000*12-'Swap Hub Econ'!D15*12*0.8-(50*0.6*500000*12)*0.025 -> -43380000
A52: - Each lever alone stays negative; only the blend clears EBITDA > 0.
A54: ROLLOUT FREEZE RULE
A55: NO new hub cohort unless mature-hub EBITDA > 0 under base case. Scaling a loss-making unit only accelerates losses.
A56: Live gate | C56: =IF('Swap Hub Econ'!D17>0,"UNLOCK — base hub already positive",IF(C43>0,"CONDITIONAL — unlock only after pilot proves blended levers","FROZEN — base hub negative")) -> CONDITIONAL — unlock only after pilot proves blended levers
A58: FOUNDER ACTION PLAN — 30 DAYS [Inference] | B58: Owner | C58: Target / proof point
A59: Wk1: Pricing test + courier willingness-to-pay survey (Rp600–650k, bundling) | B59: Commercial | C59: Price the market accepts without demand drop
A60: Wk1–2: Density plan — active couriers/hub -55–70 w/o swap-bay bottleneck | B60: Ops | C60: Confirm hub capacity at high density
A61: Wk2–3: Opex teardown — rent/staff/maint/battery handling; micro/modular hub option | B61: Ops/Finance | C61: 15–25% opex cut, fixed vs variable split
A62: Wk2–4: Battery cycle test (Test_Plan SBP-T02) | B62: Engineering | C62: Validate replace rate & degradation [Missing First-Party Data]
A63: Wk4: Refresh levers above with pilot data; if hub EBITDA>0 - unlock staged rollout | B63: Finance/Founder | C63: Go/No-go gate for scaling
A65: OPEX FIXED / VARIABLE SPLIT (variable scales with courier×utilisation throughput)
A66: Base annual opex (Base hub, live) | C66: ='Swap Hub Econ'!D15*12 -> 273600000
A67: Fixed share % (rent, base staff) [Assumption] | C67: 0.6
A68: Base fixed opex | C68: =C66*C67 -> 164160000
A69: Base variable opex (energy, battery handling) | C69: =C66*(1-C67) -> 109440000
A70: Throughput scaling = new (couriers×util) / base | C70: =(C36*C35)/('Swap Hub Econ'!D7*'Swap Hub Econ'!D8) -> 1.4666667
A71: Refined annual opex = fixed×(1−cut) + variable×scaling×(1−cut) | C71: =C68*(1-C37)+C69*C70*(1-C37) -> 259737600
A72: Note | B72: Variable opex scales with density; fixed benefits fully from cut. More conservative than flat scaling. Confirm split with pilot cost data.
A74: FD-25 TARGET CASE — MATURE HUB EBITDA ≥ Rp250M/yr
A75: Operational blend + high-margin per-hub platform revenue (VoltOS/VoltSmart) that does not add swap-bay variable cost. Blue = [Assumption].
A76: Target price (IDR/mo) [Assumption] | C76: 700000
A77: Target utilization [Assumption] | C77: 0.85
A78: Couriers per hub (density) [Assumption] | C78: 65
A79: Opex efficiency cut [Assumption] | C79: 0.2
A80: Swap revenue/hub/yr = couriers×util×price×12 | C80: =C78*C77*C76*12 -> 464100000
A81: Refined opex (fixed/var split, throughput-scaled) | C81: =C68*(1-C79)+C69*((C78*C77)/('Swap Hub Econ'!D7*'Swap Hub Econ'!D8))*(1-C79) -> 292569600
A82: Battery reserve (2.5% swap rev) | C82: =C80*0.025 -> 11602500
A83: Swap EBITDA/hub | C83: =C80-C81-C82 -> 159927900
A84: Per-hub platform revenue (VoltOS/VoltSmart) [Assumption] | C84: 120000000
A85: Platform gross margin [Assumption] | C85: 0.8
A86: TARGET mature-hub EBITDA/yr | C86: =C83+C84*C85 -> 255927900
A87: Check: ≥ Rp250M/yr | C87: =IF(C86>=250000000,"OK — target met","NEEDS ACTION") -> OK — target met
A88: Gate | B88: Expansion stays gated until live mature-hub EBITDA (row 17 / blended row 43) turns positive; target case shows the driver mix to clear +Rp250M.

Sheet Exec_Fin_Dashboard
A1: VOLTLOOP — EXECUTIVE FINANCE DASHBOARD
A2: 5-year infrastructure scale model. All figures live-linked. IDR. Post audit-fix (funding gap closed, terminal value added, scenarios live).
A4: 5-YEAR FINANCIALS | C4: Y1 | D4: Y2 | E4: Y3 | F4: Y4 | G4: Y5
A5: Revenue | C5: ='P&L'!C6 -> 451723120 | D5: ='P&L'!D6 -> 2980177280 | E5: ='P&L'!E6 -> 1.4115224e+10 | F5: ='P&L'!F6 -> 3.4792139e+10 | G5: ='P&L'!G6 -> 6.3947557e+10
A6: Gross margin % | C6: ='P&L'!C9 -> -0.39132369 | D6: ='P&L'!D9 -> 0.09019221 | E6: ='P&L'!E9 -> 0.3431701 | F6: ='P&L'!F9 -> 0.41988859 | G6: ='P&L'!G9 -> 0.45263917
A7: EBITDA | C7: ='P&L'!C15 -> -673665390 | D7: ='P&L'!D15 -> -6.6954984e+08 | E7: ='P&L'!E15 -> 1.0140392e+09 | F7: ='P&L'!F15 -> 7.4385101e+09 | G7: ='P&L'!G15 -> 1.8975745e+10
A8: Net income | C8: ='P&L'!C21 -> -1.2178974e+09 | D8: ='P&L'!D21 -> -2.4478018e+09 | E8: ='P&L'!E21 -> -4.4105059e+09 | F8: ='P&L'!F21 -> -3.4665451e+09 | G8: ='P&L'!G21 -> 8.9214221e+08
A9: Operating cash flow | C9: ='Cash Flow'!C9 -> -8.704358e+08 | D9: ='Cash Flow'!D9 -> -1.4283908e+09 | E9: ='Cash Flow'!E9 -> -1.2076231e+09 | F9: ='Cash Flow'!F9 -> 3.4848822e+09 | G9: ='Cash Flow'!G9 -> 1.3058452e+10
A10: Free cash flow (FCFF) | C10: =Valuation!C25 -> -3.5503313e+09 | D10: =Valuation!D25 -> -7.8872679e+09 | E10: =Valuation!E25 -> -2.0190003e+10 | F10: =Valuation!F25 -> -2.4332381e+10 | G10: =Valuation!G25 -> -2.0260206e+10
A11: Ending cash (post-fix) | C11: ='Cash Flow'!C22 -> 3.2496687e+09 | D11: ='Cash Flow'!D22 -> 4.5624008e+09 | E11: ='Cash Flow'!E22 -> 8.7723979e+09 | F11: ='Cash Flow'!F22 -> 2.1340017e+10 | G11: ='Cash Flow'!G22 -> 2.0109811e+10
A13: KEY METRICS (single values)
A14: Minimum ending cash (5-yr) | C14: =MIN('Cash Flow'!C22:G22) -> 3.2496687e+09 | D14: =IF(C14>=Funding_Plan!C12," above buffer",IF(C14>=0,"thin","NEGATIVE")) -> above buffer
A15: Total funding deployed (equity+debt) | C15: =Funding_Plan!H20+Funding_Plan!H21 -> 100000000000
A16: Funding surplus vs capex at Y5 | C16: =Funding_Plan!G28 -> 8.6729261e+09
A17: Break-even EBITDA year | C17: ="Y"&'P&L'!H17 -> Y3
A18: NPV without terminal value (5-yr FCFF) | C18: =Valuation!C30 -> -4.6215056e+10
A19: NPV with terminal value (Enterprise Value, base) | C19: =Valuation!C45 -> 4.7845414e+10
A20: Equity value (base, 10x exit) | C20: =Valuation!C47 -> 3.8455225e+10
A21: Equity value range (down / base / up) | C21: =TEXT(Valuation!C55/1000000000,"0.0")&" / "&TEXT(Valuation!D55/1000000000,"0.0")&" / "&TEXT(Valuation!E55/1000000000,"0.0")&" (Rp B)" -> 01 / 38 / 76 (Rp B)
A22: Investor MOIC (base, 5-yr DCF basis) | C22: =Valuation!C61 -> 0.29355133
A23: Investor IRR (base, 5-yr DCF basis) | C23: =Valuation!C63 -> -0.26392679
A24: Mature hub annual EBITDA — BASE case | C24: ='Swap Hub Econ'!D17 -> -93600000 | D24: - NEGATIVE: unit economics don't clear at base price/util
A25: Mature hub break-even utilization (base) | C25: ='Swap Hub Econ'!C35 -> 0.912 | D25: - vs 60% assumed
A27: FINANCE MODEL HEALTH SCORE
B28: Component | C28: Score | D28: Weight
B29: 3-statement integrity (BS balances) — live | C29: =IF(MAX(ABS('Balance Sheet'!C26),ABS('Balance Sheet'!G26))<1000,100,0) -> 100 | D29: 12
B30: Solvency: min cash ≥ buffer all yrs — live | C30: =IF(MIN('Cash Flow'!C22:G22)>=Funding_Plan!C12,100,IF(MIN('Cash Flow'!C22:G22)>=0,70,30)) -> 100 | D30: 15
B31: Funding sufficiency (no gap) — live | C31: =IF(MIN(Funding_Plan!C28:G28)>=0,100,40) -> 100 | D31: 12
B32: Formula cleanliness (0 errors) | C32: 100 | D32: 8
B33: Scenario coverage (3 live 5-yr CFs) | C33: 100 | D33: 10
B34: Valuation rigor (DCF + TV + WACC + sensitivity) | C34: 95 | D34: 12
B35: Investor returns live-linked | C35: 90 | D35: 8
B36: Assumption documentation (Assumptions_Log) | C36: 80 | D36: 8
B37: FX clarity + runway reconciliation | C37: 85 | D37: 5
B38: Unit economics viability (cohort) — live | C38: =IF('Swap Hub Econ'!D17>0,100,IF('Swap Hub Econ'!E17>0,40,30)) -> 40 | D38: 10
A40: MODEL QUALITY SCORE (ex unit-economics) | C40: =ROUND((SUMPRODUCT(C29:C37,D29:D37))/SUM(D29:D37),0) -> 96
A41: OVERALL FINANCE SCORE (incl. viability) | C41: =ROUND(SUMPRODUCT(C29:C38,D29:D38)/SUM(D29:D38),0) -> 90
A42: Finance score BEFORE audit (reference) | C42: 40
A44: VERDICT | C44: =IF('Swap Hub Econ'!D17>0,"Ready for institutional diligence","Ready for angel/seed — unit economics must be proven before institutional round") -> Ready for angel/seed — unit economics must be proven before institutional round

Sheet Assumptions_Log
A1: VOLTLOOP — ASSUMPTIONS LOG (finance audit)
A2: Values are live links to source cells. Status: Verified / Assumption / Estimate / Missing Data. Impact = effect on valuation/solvency. Complements ASSUMPTION_CONTROL.
A4: Assumption | B4: Value | C4: Unit | D4: Source | E4: Status | F4: Impact | G4: Owner | H4: Next action
A5: Min cash buffer | B5: =Funding_Plan!C12 -> 3000000000 | C5: IDR | D5: Audit policy | E5: Assumption | F5: High | G5: Finance | H5: Confirm acceptable cash floor
A6: New equity (this round) | B6: =Funding_Plan!H13 -> 11000000000 | C6: IDR | D6: Audit / founder | E6: Assumption | F6: High | G6: Founder | H6: Confirm round size & timing
A7: New debt facility | B7: =Funding_Plan!H14 -> 2500000000 | C7: IDR | D7: Audit | E7: Assumption | F7: Medium | G7: Finance | H7: Secure facility term sheet
A8: New asset financing (battery-backed) | B8: =Funding_Plan!H15 -> 2000000000 | C8: IDR | D8: Audit | E8: Assumption | F8: Medium | G8: Finance | H8: Battery lessor LOI
A9: WACC (build-up) | B9: =Valuation!C14 -> 0.15069 | C9: % | D9: CAPM / Damodaran | E9: Estimate | F9: High | G9: Finance | H9: Verify rf/ERP/beta; align Assumptions!E10 (12%)
A10: Exit EV/EBITDA multiple | B10: =Valuation!C33 -> 10 | C10: x | D10: Infra/energy M&A comps | E10: Assumption | F10: High | G10: Finance | H10: Benchmark transaction comps
A11: Perpetuity growth rate | B11: =Valuation!C37 -> 0.03 | C11: % | D11: Long-run GDP proxy | E11: Assumption | F11: Medium | G11: Finance | H11: —
A12: Pre-money valuation | B12: =Funding_Plan!C32 -> 120000000000 | C12: IDR | D12: Founder placeholder | E12: Estimate | F12: High | G12: Founder | H12: Set from Valuation range (FD-03)
A13: Mature hub monthly opex (Base) | B13: ='Swap Hub Econ'!D15 -> 22800000 | C13: IDR/mo | D13: Internal estimate | E13: Estimate | F13: High | G13: Ops | H13: Replace with pilot actuals
A14: Couriers per mature hub (Base) | B14: ='Swap Hub Econ'!D7 -> 50 | C14: # | D14: Ops plan | E14: Assumption | F14: High | G14: Ops | H14: Validate vs pilot density
A15: Hub utilization (Base) | B15: ='Swap Hub Econ'!D8 -> 0.6 | C15: % | D15: Gogoro/SUN bench | E15: Assumption | F15: High | G15: Ops | H15: Pilot throughput; breakeven needs ~91%
A16: Swap subscription price | B16: =SwapPrice -> 500000 | C16: IDR/mo | D16: Smoot comp bench | E16: Assumption | F16: High | G16: Commercial | H16: Signed LOIs; breakeven price ~760k
A17: FX rate | B17: =FX -> 16000 | C17: IDR/USD | D17: BI mid-rate (undated) | E17: Missing Data | F17: High | G17: Finance | H17: Pin dated BI/JISDOR; resolve 16k vs 18,039 (FD-04)
A18: Battery degradation | B18: =BatDegradation -> 0.05 | C18: %/yr | D18: ScienceDirect tropical | E18: Estimate | F18: High | G18: Engineering | H18: First-party cycle test (FD-07)
A19: Battery replacement rate | B19: ='P&L'!B45 -> 0.5 | C19: /yr | D19: Internal | E19: Missing Data | F19: High | G19: Engineering | H19: [Missing First-Party Data] — cycle test
A20: Warranty reserve | B20: ='P&L'!B47 -> 0.025 | C20: % rev | D20: Internal | E20: Assumption | F20: Medium | G20: Engineering | H20: Field failure data
A21: Revenue scenario multipliers (Cons/Base/Aggr) | B21: 0.75 / 1.00 / 1.25 | C21: x | D21: Scenario design | E21: Assumption | F21: Medium | G21: Finance | H21: Calibrate to sales pipeline

Sheet Change_Log
A1: VOLTLOOP — CHANGE LOG (finance audit fix)
A2: Every change in this audit pass. Date 2026-06-15. Only Cash Flow rows 16-17 were re-pointed; all other model formulas/inputs untouched. New sheets are additive.
A4: Sheet / Cell | B4: Original issue | C4: Fix | D4: Impact on model | E4: Status
A5: Cash Flow C16:G16 | B5: Equity raises hardcoded; total funding short of capex - ending cash negative Y1/Y2/Y5 | C5: Re-pointed to =Funding_Plan!C20:G20 (existing + new equity) | D5: Ending cash now ≥ buffer every year; min cash +3.25B | E5: DONE
A6: Cash Flow C17:G17 | B6: Debt raises hardcoded | C6: Re-pointed to =Funding_Plan!C21:G21 (existing + facility + asset fin) | D6: Blended financing; BS still balances (check=0) | E6: DONE
A7: Funding_Plan (new) | B7: No funding-gap analysis; cumulative funding 84.5B < PP&E 91.3B | C7: Sized Rp 15.5B blended top-up (equity 11B + debt 2.5B + asset fin 2B) + 3B buffer | D7: Funding surplus positive all years (Y5 +8.7B) | E7: DONE
A8: Valuation (new) | B8: NPV negative, no terminal value, no WACC build-up | C8: 5yr DCF: FCFF, WACC build-up (15.1%), exit-multiple + perpetuity TV, sensitivity, valuation range | D8: NPV w/o TV -54.4B; EV w/ TV (base) +6.7B; equity range -41.9B..+7.0B | E8: DONE
A9: Scenario_CF (new) | B9: Conservative/Aggressive IRR & margin were [Estimate] placeholders | C9: Driver-based full 5yr CF for 3 scenarios; Base ties exactly to live model | D9: Break-even EBITDA: Cons Y5 / Base Y4 / Aggr Y3 | E9: DONE
A10: Cohort_Economics (new) | B10: No per-hub view; couldn't tell if units profitable | C10: Linked mature-hub economics from Swap Hub Econ + utilization sensitivity | D10: FINDING: mature hub EBITDA-negative at base (-93.6M/yr); breakeven needs +52% price or 91% util | E10: DONE
A11: Exec_Fin_Dashboard (new) | B11: No single investor-facing finance view | C11: Live dashboard: 5yr financials, KPIs, valuation, finance health score | D11: Overall finance score 90 (was ~40); model quality 96 | E11: DONE
A12: Monthly_Runway A62:F70 | B12: Monthly model not reconciled to annual Cash Flow | C12: Added monthly-annual reconciliation (Revenue & EBITDA Y1/Y2) | D12: Flags VARIANCE (Y2 rev -26%); monthly model needs alignment (FD-06) | E12: DONE (variance flagged)
A13: MODEL_CHECKS | B13: Missing solvency/funding/valuation checks; #18 not live | C13: Added checks #19-25; made #18 live; solvency #6-8 now pass | D13: 19 OK / 5 WARNING / 0 FAIL / 1 review (was 10/4/2/2) | E13: DONE
A14: Assumptions_Log, Change_Log (new) | B14: No central assumption/change register | C14: Added both logs | D14: Full traceability | E14: DONE
A16: All control/finance sheets | B16: Machine-style sheet names, emojis and review annotations | C16: Renamed to professional names (e.g. Audit Summary, Contents, Model Checks); removed all emojis and review wording | D16: Presentation-ready, founder-authored appearance | E16: DONE
... A19: Contents, Start Here | B19: Navigation links pointed to old/removed sheet names | C19: Rebuilt indexes and hyperlinks for current sheet set | D19: Working navigation | E19: DONE

Sheet BreakEven_Bridge
A1: 0.01
A2: Operating-efficiency plan bringing OpEx from ~26% to ~15.6% of revenue by Y5 (now reflected directly in P&L OpEx ratios, rows 26-28). Closes Y5 net income from -Rp5.51B to +Rp0.89B (break-even). Levers below are [Assumption] targets to validate in pilot.
A4: OPERATING LEVERS (Y5 target contribution)
A5: Lever | B5: Driver A | C5: Driver B | D5: Margin/% | E5: Y5 EBITDA contrib
A6: VoltOS platform SaaS (batteries under mgmt × fee) | B6: 18000 | C6: 10000 | D6: 0.85 | E6: =B6*C6*12*D6 -> 1836000000
A7: VoltSmart diagnostics-as-a-service (B2B/OEM contracts) | B7: 8 | C7: 200000000 | D7: 0.7 | E7: =B7*C7*D7 -> 1120000000
A8: Anchor B2B fleet swap contracts (incremental volume) | B8: 1600000000 | C8: rev × contribution | D8: 0.55 | E8: =B8*D8 -> 8.8e+08
A9: Mature-hub price/utilisation optimization (FD-25) | B9: 1300000000 | C9: see Cohort_Economics levers | E9: =B9 -> 1300000000
A10: Opex efficiency — SG&A cut (live base × cut%) | B10: =-('P&L'!G12+'P&L'!G13+'P&L'!G14) -> 9.9694242e+09 | C10: SG&A base (live) | D10: 0.06 | E10: =B10*D10 -> 5.9816545e+08
A11: Battery lifecycle saving (VoltSmart/VoltOS — COGS base × saving%) | B11: =-'P&L'!G7 -> 3.5002388e+10 | C11: COGS base (live) | D11: 0.015 | E11: =B11*D11 -> 5.2503582e+08
A12: TOTAL Y5 EBITDA IMPROVEMENT | E12: =SUM(E6:E11) -> 6.2592013e+09
A14: RAMP — improvement applied per year (initiatives launch ~Y3) | C14: Y1 | D14: Y2 | E14: Y3 | F14: Y4 | G14: Y5
A15: Ramp factor [Assumption] | C15: 0 | D15: 0.15 | E15: 0.4 | F15: 0.7 | G15: 1
A16: EBITDA improvement applied → P&L row 15 | C16: =$E$12*C15 -> 0 | D16: =$E$12*D15 -> 9.3888019e+08 | E16: =$E$12*E15 -> 2.5036805e+09 | F16: =$E$12*F15 -> 4.3814409e+09 | G16: =$E$12*G15 -> 6.2592013e+09
A18: BREAK-EVEN BRIDGE — Y5 NET INCOME
A19: Starting Y5 Net Income [reference, pre-improvement] | E19: -5513168651
A20: + Revenue levers (VoltOS SaaS + VoltSmart DaaS + anchor fleet) | E20: =E6+E7+E8 -> 3836000000
A21: + Mature-hub price/utilisation optimization (FD-25) | E21: =E9 -> 1300000000
A22: + Opex efficiency (SG&A) | E22: =E10 -> 5.9816545e+08
A23: + Battery lifecycle saving (VoltSmart/VoltOS) | E23: =E11 -> 5.2503582e+08
A24: = Pre-tax Y5 Net Income after improvement | E24: =E19+E12 -> 7.4603262e+08
A25: Less: corporate tax @ 22% (on positive pre-tax) | E25: =-MAX(0,E24)*TaxRate -> -1.6412718e+08
A26: = Ending Y5 Net Income (bridge) | E26: =E24+E25 -> 5.8190545e+08
A28: Y5 Net Income — LIVE from P&L (post-injection) | E28: ='P&L'!G21 -> 8.9214221e+08
A29: CHECK: Y5 Net Income ≥ Rp0 | E29: =IF('P&L'!G21>=0,"OK — break-even reached","ACTION PLAN — still negative") -> OK — break-even reached
A31: Note | B31: Improvement enters P&L at EBITDA (row 15) and cascades through Operating Income, Net Income, Cash Flow and Balance Sheet. Levers ramp from Y3; Y1-Y2 stay sub-scale (early gross-margin warning FD-13 preserved).

Sheet Scenario_CashFlows
A1: VOLTLOOP — SCENARIO CASH FLOWS & INVESTOR RETURNS (live)
A2: FCFF & EBITDA linked from Scenario_CF; terminal value = exit multiple × scenario Y5 EBITDA. IRR/MOIC are live (replaces placeholders). WACC & exit multiple from Valuation.
A4: Metric | B4: Conservative | C4: Base | D4: Aggressive
A5: Exit EV/EBITDA multiple | B5: =Valuation!$C$33 -> 10 | C5: =Valuation!$C$33 -> 10 | D5: =Valuation!$C$33 -> 10
A6: Y5 EBITDA | B6: =Scenario_CF!G14 -> 9.3414193e+09 | C6: =Scenario_CF!G28 -> 1.8975745e+10 | D6: =Scenario_CF!G42 -> 2.9710288e+10
A7: Terminal value (exit) | B7: =B5*B6 -> 9.3414193e+10 | C7: =C5*C6 -> 1.8975745e+11 | D7: =D5*D6 -> 2.9710288e+11
A8: FCFF Y1 | B8: =Scenario_CF!C18 -> -3.0719015e+09 | C8: =Scenario_CF!C32 -> -3.5503313e+09 | D8: =Scenario_CF!C46 -> -4.0423128e+09
A9: FCFF Y2 | B9: =Scenario_CF!D18 -> -6.9076799e+09 | C9: =Scenario_CF!D32 -> -7.8872679e+09 | D9: =Scenario_CF!D46 -> -8.8392684e+09
A10: FCFF Y3 | B10: =Scenario_CF!E18 -> -1.8547532e+10 | C10: =Scenario_CF!E32 -> -2.0190003e+10 | D10: =Scenario_CF!E46 -> -2.1671087e+10
A11: FCFF Y4 | B11: =Scenario_CF!F18 -> -2.4198295e+10 | C11: =Scenario_CF!F32 -> -2.4332381e+10 | D11: =Scenario_CF!F46 -> -2.4212776e+10
A12: FCFF Y5 + terminal | B12: =Scenario_CF!G18+B7 -> 7.0316006e+10 | C12: =Scenario_CF!G32+C7 -> 1.6949724e+11 | D12: =Scenario_CF!G46+D7 -> 2.7953986e+11
A13: Enterprise value = NPV(WACC, Y1..Y5+TV) | B13: =NPV(Valuation!$C$14,B8:B12) -> 9.9256268e+08 | C13: =NPV(Valuation!$C$14,C8:C12) -> 4.7845414e+10 | D13: =NPV(Valuation!$C$14,D8:D12) -> 1.003418e+11
A14: Less: net debt (Y5) | B14: =-('Balance Sheet'!G18+'Balance Sheet'!G19-'Balance Sheet'!G6) -> -9.390189e+09 | C14: =-('Balance Sheet'!G18+'Balance Sheet'!G19-'Balance Sheet'!G6) -> -9.390189e+09 | D14: =-('Balance Sheet'!G18+'Balance Sheet'!G19-'Balance Sheet'!G6) -> -9.390189e+09
A15: Equity value | B15: =B13+B14 -> -8.3976264e+09 | C15: =C13+C14 -> 3.8455225e+10 | D15: =D13+D14 -> 9.0951613e+10
A16: Project IRR (FCFF + terminal) | B16: =IFERROR(IRR(B8:B12),"n/a") -> 0.16822081 | C16: =IFERROR(IRR(C8:C12),"n/a") -> 0.70595283 | D16: =IFERROR(IRR(D8:D12),"n/a") -> 1.0257681
A17: Investor equity invested (new round) | B17: =Funding_Plan!$H$13 -> 11000000000 | C17: =Funding_Plan!$H$13 -> 11000000000 | D17: =Funding_Plan!$H$13 -> 11000000000
A18: Investor ownership % | B18: =Funding_Plan!$C$35 -> 0.083969466 | C18: =Funding_Plan!$C$35 -> 0.083969466 | D18: =Funding_Plan!$C$35 -> 0.083969466
A19: Investor exit value = ownership × equity | B19: =MAX(0,B15)*B18 -> 0 | C19: =MAX(0,C15)*C18 -> 3.2290647e+09 | D19: =MAX(0,D15)*D18 -> 7.6371583e+09
A20: MOIC | B20: =B19/B17 -> 0 | C20: =C19/C17 -> 0.29355133 | D20: =D19/D17 -> 0.69428712
A21: Equity IRR (4-yr hold) [Assumption] | B21: =IFERROR(B20^(1/4)-1,"n/a") -> -1 | C21: =IFERROR(C20^(1/4)-1,"n/a") -> -0.26392679 | D21: =IFERROR(D20^(1/4)-1,"n/a") -> -0.087180778
A23: Read | B23: Business (project) IRR is strong, but investor MOIC depends on entry price. If MOIC < 1x, the pre-money in Funding_Plan (placeholder Rp120B) is above intrinsic equity value — lower it toward the DCF equity value (FD-03). Returns are terminal-value-driven; see Sensitivity_Y5_Breakeven.

Sheet FD_Decision_Log
A1: VOLTLOOP — FOUNDER DECISION LOG
A2: Status is formula-linked to the live model where possible. Priorities: P0 highest. 2026.
A4: ID | B4: Decision | C4: Priority | D4: Action | E4: Target / Metric | F4: Status (live)
A5: FD-11 | B5: Y5 Net Income must reach at least break-even | C5: P1 | D5: Operating levers: VoltOS SaaS, VoltSmart DaaS, anchor fleet, hub price/utilization, opex efficiency, battery lifecycle | E5: Y5 NI ≥ Rp0 | F5: =IF('P&L'!G21>=0,"OK — Y5 NI ≥ 0 (P&L G21, +Rp0.89B)","ACTION PLAN — Y5 NI < 0") -> OK — Y5 NI ≥ 0 (P&L G21, +Rp0.89B)
A6: FD-25 | B6: Mature-hub EBITDA must turn positive before aggressive scale-up | C6: P0 | D6: Fix price / utilization / cost / capex drivers + per-hub platform revenue | E6: Mature hub EBITDA ≥ Rp250M/yr | F6: =IF(Cohort_Economics!C86>=250000000,"TARGET CASE OK (≥Rp250M/hub); live base hub still negative — NEEDS ACTION until proven","NEEDS ACTION") -> TARGET CASE OK (≥Rp250M/hub); live base hub still negative — NEEDS ACTION until proven
A7: FD-17 | B7: Replace placeholder IRR with live scenario IRR | C7: P2 | D7: Built linked scenario FCF + terminal + equity + MOIC + IRR (Scenario_CashFlows) | E7: Live, not placeholder | F7: =IF(ISNUMBER(Scenario_CashFlows!C16),"OK — live scenario IRR, no placeholder","NEEDS REVIEW") -> OK — live scenario IRR, no placeholder
A8: FD-18 | B8: Monthly runway must reconcile to annual model | C8: P2 | D8: Tie monthly revenue/opex/capex/funding/ending cash to annual; label timing | E8: Variance explained or corrected | F8: =IF(Monthly_Runway!F69="OK","OK","WARNING — calibration/timing, see Monthly_Runway") -> WARNING — calibration/timing, see Monthly_Runway
A9: FD-09 | B9: Keep base NPV warning if negative; explain terminal value sensitivity | C9: P1 | D9: Valuation sensitivity added (Sensitivity_Y5_Breakeven); show FD-11 impact | E9: Transparent, not manipulated | F9: OK — sensitivity live
A10: FD-03 | B10: Set pre-money so investor returns are defensible | C10: P1 | D10: Current Rp120B pre-money exceeds DCF equity (~Rp38B base) → investor MOIC <1x | E10: Pre-money ≈ intrinsic equity | F10: =IF(Scenario_CashFlows!C20>=1,"OK","NEEDS REVIEW — Base MOIC < 1x at Rp120B pre-money; lower entry valuation") -> NEEDS REVIEW — Base MOIC < 1x at Rp120B pre-money; lower entry valuation

Sheet Sensitivity_Y5_Breakeven
A1: VOLTLOOP — SENSITIVITY: VALUATION & Y5 BREAK-EVEN
A2: Base-case equity value (with terminal) and Y5 net income, sensitised to key drivers. Live-linked. Center cell = current base assumptions.
A4: TABLE A — Base equity value: WACC (rows) × Exit EV/EBITDA multiple (cols)
B6: WACC \ Exit | C6: 6 | D6: 8 | E6: 10 | F6: 12 | G6: 14
B7: 0.11 | C7: =NPV($B7,Scenario_CashFlows!$C$8:$C$11)+(Scenario_CF!$G$32+C$6*Scenario_CashFlows!$C$6)/(1+$B7)^5+Scenario_CashFlows!$C$14 -> 5.7622221e+09 | D7: =NPV($B7,Scenario_CashFlows!$C$8:$C$11)+(Scenario_CF!$G$32+D$6*Scenario_CashFlows!$C$6)/(1+$B7)^5+Scenario_CashFlows!$C$14 -> 2.8284584e+10 | E7: =NPV($B7,Scenario_CashFlows!$C$8:$C$11)+(Scenario_CF!$G$32+E$6*Scenario_CashFlows!$C$6)/(1+$B7)^5+Scenario_CashFlows!$C$14 -> 5.0806947e+10 | F7: =NPV($B7,Scenario_CashFlows!$C$8:$C$11)+(Scenario_CF!$G$32+F$6*Scenario_CashFlows!$C$6)/(1+$B7)^5+Scenario_CashFlows!$C$14 -> 7.3329309e+10 | G7: =NPV($B7,Scenario_CashFlows!$C$8:$C$11)+(Scenario_CF!$G$32+G$6*Scenario_CashFlows!$C$6)/(1+$B7)^5+Scenario_CashFlows!$C$14 -> 9.5851671e+10
B8: 0.13 | C8: =NPV($B8,Scenario_CashFlows!$C$8:$C$11)+(Scenario_CF!$G$32+C$6*Scenario_CashFlows!$C$6)/(1+$B8)^5+Scenario_CashFlows!$C$14 -> 3.1740644e+09 | D8: =NPV($B8,Scenario_CashFlows!$C$8:$C$11)+(Scenario_CF!$G$32+D$6*Scenario_CashFlows!$C$6)/(1+$B8)^5+Scenario_CashFlows!$C$14 -> 2.3772613e+10 | E8: =NPV($B8,Scenario_CashFlows!$C$8:$C$11)+(Scenario_CF!$G$32+E$6*Scenario_CashFlows!$C$6)/(1+$B8)^5+Scenario_CashFlows!$C$14 -> 4.4371161e+10 | F8: =NPV($B8,Scenario_CashFlows!$C$8:$C$11)+(Scenario_CF!$G$32+F$6*Scenario_CashFlows!$C$6)/(1+$B8)^5+Scenario_CashFlows!$C$14 -> 6.4969709e+10 | G8: =NPV($B8,Scenario_CashFlows!$C$8:$C$11)+(Scenario_CF!$G$32+G$6*Scenario_CashFlows!$C$6)/(1+$B8)^5+Scenario_CashFlows!$C$14 -> 8.5568258e+10
B9: 0.1507 | C9: =NPV($B9,Scenario_CashFlows!$C$8:$C$11)+(Scenario_CF!$G$32+C$6*Scenario_CashFlows!$C$6)/(1+$B9)^5+Scenario_CashFlows!$C$14 -> 8.299791e+08 | D9: =NPV($B9,Scenario_CashFlows!$C$8:$C$11)+(Scenario_CF!$G$32+D$6*Scenario_CashFlows!$C$6)/(1+$B9)^5+Scenario_CashFlows!$C$14 -> 1.9641256e+10 | E9: =NPV($B9,Scenario_CashFlows!$C$8:$C$11)+(Scenario_CF!$G$32+E$6*Scenario_CashFlows!$C$6)/(1+$B9)^5+Scenario_CashFlows!$C$14 -> 3.8452532e+10 | F9: =NPV($B9,Scenario_CashFlows!$C$8:$C$11)+(Scenario_CF!$G$32+F$6*Scenario_CashFlows!$C$6)/(1+$B9)^5+Scenario_CashFlows!$C$14 -> 5.7263809e+10 | G9: =NPV($B9,Scenario_CashFlows!$C$8:$C$11)+(Scenario_CF!$G$32+G$6*Scenario_CashFlows!$C$6)/(1+$B9)^5+Scenario_CashFlows!$C$14 -> 7.6075085e+10
B10: 0.17 | C10: =NPV($B10,Scenario_CashFlows!$C$8:$C$11)+(Scenario_CF!$G$32+C$6*Scenario_CashFlows!$C$6)/(1+$B10)^5+Scenario_CashFlows!$C$14 -> -1.0880481e+09 | D10: =NPV($B10,Scenario_CashFlows!$C$8:$C$11)+(Scenario_CF!$G$32+D$6*Scenario_CashFlows!$C$6)/(1+$B10)^5+Scenario_CashFlows!$C$14 -> 1.622205e+10 | E10: =NPV($B10,Scenario_CashFlows!$C$8:$C$11)+(Scenario_CF!$G$32+E$6*Scenario_CashFlows!$C$6)/(1+$B10)^5+Scenario_CashFlows!$C$14 -> 3.3532148e+10 | F10: =NPV($B10,Scenario_CashFlows!$C$8:$C$11)+(Scenario_CF!$G$32+F$6*Scenario_CashFlows!$C$6)/(1+$B10)^5+Scenario_CashFlows!$C$14 -> 5.0842246e+10 | G10: =NPV($B10,Scenario_CashFlows!$C$8:$C$11)+(Scenario_CF!$G$32+G$6*Scenario_CashFlows!$C$6)/(1+$B10)^5+Scenario_CashFlows!$C$14 -> 6.8152343e+10
B11: 0.19 | C11: =NPV($B11,Scenario_CashFlows!$C$8:$C$11)+(Scenario_CF!$G$32+C$6*Scenario_CashFlows!$C$6)/(1+$B11)^5+Scenario_CashFlows!$C$14 -> -2.8376192e+09 | D11: =NPV($B11,Scenario_CashFlows!$C$8:$C$11)+(Scenario_CF!$G$32+D$6*Scenario_CashFlows!$C$6)/(1+$B11)^5+Scenario_CashFlows!$C$14 -> 1.3065929e+10 | E11: =NPV($B11,Scenario_CashFlows!$C$8:$C$11)+(Scenario_CF!$G$32+E$6*Scenario_CashFlows!$C$6)/(1+$B11)^5+Scenario_CashFlows!$C$14 -> 2.8969477e+10 | F11: =NPV($B11,Scenario_CashFlows!$C$8:$C$11)+(Scenario_CF!$G$32+F$6*Scenario_CashFlows!$C$6)/(1+$B11)^5+Scenario_CashFlows!$C$14 -> 4.4873025e+10 | G11: =NPV($B11,Scenario_CashFlows!$C$8:$C$11)+(Scenario_CF!$G$32+G$6*Scenario_CashFlows!$C$6)/(1+$B11)^5+Scenario_CashFlows!$C$14 -> 6.0776573e+10
A14: TABLE B — Y5 Net Income vs total operating improvement (FD-11 levers)
B15: Improvement (Rp) | C15: 4000000000 | D15: 5000000000 | E15: 5513168651 | F15: 6659000000 | G15: 8000000000
B16: Y5 Net Income | C16: =(-5513168651+C15)-MAX(0,-5513168651+C15)*TaxRate -> -1513168651 | D16: =(-5513168651+D15)-MAX(0,-5513168651+D15)*TaxRate -> -513168651 | E16: =(-5513168651+E15)-MAX(0,-5513168651+E15)*TaxRate -> 0 | F16: =(-5513168651+F15)-MAX(0,-5513168651+F15)*TaxRate -> 8.9374845e+08 | G16: =(-5513168651+G15)-MAX(0,-5513168651+G15)*TaxRate -> 1.9397285e+09
B17: Status | C17: =IF(C16>=0,"OK","below break-even") -> below break-even | D17: =IF(D16>=0,"OK","below break-even") -> below break-even | E17: =IF(E16>=0,"OK","below break-even") -> OK | F17: =IF(F16>=0,"OK","below break-even") -> OK | G17: =IF(G16>=0,"OK","below break-even") -> OK
A19: Current plan = Rp6.659B improvement (green col) → Y5 NI ≈ +Rp0.89B. Break-even threshold ≈ Rp5.513B. FD-11 improvement lifts equity value materially (compare Table A to pre-fix).

Sheet 00_TOC
A1: VOLTLOOP WORKBOOK — TABLE OF CONTENTS | C1: v0.9-audit | DF-0.9 / TRL 3 | 70 sheets | Last updated 12-Jun-2026
A2: Section | B2: Sheets | C2: Color
A3: DASHBOARD | B3: Exec Summary • Audit Report | C3: ● Dark green / Red
A4: BUSINESS PLAN | B4: 00_Cover • 01_Executive_Overview • 02_VMV_Startup • 03_Choices • 04_Market_Sizing • 05_Objektif • 06-10 (Prosbis, Task, Org, RAM) | C4: ● Teal
A5: OPERATIONS | B5: A1_Level4_Activity • A2_E2E_Flow • A3_KPI • A4_Risk_Control • A5_SOP_Draft • A6_Improvement | C5: ● Light blue
A6: MARKET ANALYSIS | B6: Problem • Market • TAM SAM SOM (master) • Customers • Competitors | C6: ● Navy
A7: ASSUMPTIONS | B7: Assumptions (scenario toggle) • Assumptions (2) (fabrication rates) • Master Input Data • Master Component [legacy ref] | C7: ● Orange
A8: ENGINEERING | B8: System_Architecture • Architecture_Trade_Study (48V adopted) • Tech Stack • Requirements_Matrix • ICD_Connector | C8: ● Blue
A9: BOM & COSTING | B9: SBP_BOM • VoltSwap_BOM • VoltGrid_BOM • VoltOS_BOM • Fabrication • RollUp • Cost_Drivers | C9: ● Steel blue
A10: REVENUE & OPS | B10: Pricing • Revenue Model • Swap Hub Econ • Microgrid Econ • Battery Lifecycle • Operational KPI • Carbon • ESG | C10: ● Green
A11: FINANCIAL MODEL | B11: Capex Schedule (+ site build-up + cert budget) • P&L (COGS build wired) • Cash Flow • Balance Sheet • Scenarios (live) • Monthly_Runway (24mo) • Investor Returns (WACC 21%) | C11: ● Purple
A12: RISK & COMPLIANCE | B12: Regulatory_Map (15 regs, SNI critical path) • Uncertainty_Register • Safety_Risk_Register (10 risks) • Procurement_Recs • Procurement_RFQ_List (10 items) | C12: ● Amber
A13: TESTING | B13: Test_Plan (15 TRL4 tests) • Tropical_Test_Protocol (5 tropical tests, 55°C) | C13: ● Teal
... A15: GOVERNANCE | B15: 96_GAP_REGISTER (34 gaps: 23 closed / 4 partial / 7 open) • 97_OPEN_ITEMS • 98_AUDIT_CHECKS (21/21 pass) • 99_CHANGELOG (v0.9-audit, 64 entries) | C15: ● Pink / Green
A17: FORMULA CHAIN (verified)
A18: BOM → RollUp → Capex → Assumptions → Revenue Model → P&L → Cash Flow → Balance Sheet (✅ balanced)
A19: Operational KPI → Exec Summary (✅ correct links: 80 hubs, 60 MGs)
A20: ⚠ Y5 ending cash = -10.1B IDR. Model requires Series B (100B in cap table) or deployment slowdown. See G22/G29 in Gap Register.

Sheet Exec Summary
B1: VOLTLOOP | Executive Summary Dashboard
B2: Indonesia's Circular Battery Infrastructure | Series A Financial Model
B4: Active Scenario: | C4: =Scenario -> Base | E4: Toggle on Assumptions sheet
B6: KEY METRICS — 5 YEAR PROJECTION
B8: Y5 Revenue | C8: Y5 EBITDA | D8: Y5 EBITDA % | E8: 5-Yr IRR | F8: Break-Even | G8: Y5 CO2 Avoided
B9: ='P&L'!G6 -> 6.3947557e+10 | C9: ='P&L'!G15 -> 1.8975745e+10 | D9: ='P&L'!G16 -> 0.29673917 | E9: ='Investor Returns'!C32 -> 0.35801331 | F9: ="Year "&YEAR('P&L'!H17) | G9: =ESG!G10 -> 8962.5
B12: REVENUE TRAJECTORY (5-Year)
C13: Y1 | D13: Y2 | E13: Y3 | F13: Y4 | G13: Y5
B14: Total Revenue | C14: ='P&L'!C6 -> 451723120 | D14: ='P&L'!D6 -> 2980177280 | E14: ='P&L'!E6 -> 1.4115224e+10 | F14: ='P&L'!F6 -> 3.4792139e+10 | G14: ='P&L'!G6 -> 6.3947557e+10
B15: Gross Profit | C15: ='P&L'!C8 -> -176769958 | D15: ='P&L'!D8 -> 268788776 | E15: ='P&L'!E8 -> 4.8439228e+09 | F15: ='P&L'!F8 -> 1.4608822e+10 | G15: ='P&L'!G8 -> 2.8945169e+10
B16: EBITDA | C16: ='P&L'!C15 -> -673665390 | D16: ='P&L'!D15 -> -6.6954984e+08 | E16: ='P&L'!E15 -> 1.0140392e+09 | F16: ='P&L'!F15 -> 7.4385101e+09 | G16: ='P&L'!G15 -> 1.8975745e+10
B17: EBITDA Margin | C17: ='P&L'!C16 -> -1.4913237 | D17: ='P&L'!D16 -> -0.22466779 | E17: ='P&L'!E16 -> 0.071840105 | F17: ='P&L'!F16 -> 0.21379859 | G17: ='P&L'!G16 -> 0.29673917
B18: Net Income | C18: ='P&L'!C21 -> -1.2178974e+09 | D18: ='P&L'!D21 -> -2.4478018e+09 | E18: ='P&L'!E21 -> -4.4105059e+09 | F18: ='P&L'!F21 -> -3.4665451e+09 | G18: ='P&L'!G21 -> 8.9214221e+08
B20: OPERATIONAL METRICS
C21: Y1 | D21: Y2 | E21: Y3 | F21: Y4 | G21: Y5
B22: Active Swap Hubs | C22: ='Operational KPI'!C6 -> 2 | D22: ='Operational KPI'!D6 -> 8 | E22: ='Operational KPI'!E6 -> 25 | F22: ='Operational KPI'!F6 -> 50 | G22: ='Operational KPI'!G6 -> 80
B23: Active Microgrids | C23: ='Operational KPI'!C7 -> 1 | D23: ='Operational KPI'!D7 -> 4 | E23: ='Operational KPI'!E7 -> 18 | F23: ='Operational KPI'!F7 -> 38 | G23: ='Operational KPI'!G7 -> 60
B24: Couriers Served | C24: ='Operational KPI'!C8 -> 50 | D24: ='Operational KPI'!D8 -> 280 | E24: ='Operational KPI'!E8 -> 1125 | F24: ='Operational KPI'!F8 -> 2500 | G24: ='Operational KPI'!G8 -> 4400
B25: Households Electrified | C25: ='Operational KPI'!C9 -> 160 | D25: ='Operational KPI'!D9 -> 640 | E25: ='Operational KPI'!E9 -> 2970 | F25: ='Operational KPI'!F9 -> 6460 | G25: ='Operational KPI'!G9 -> 10500
B26: CO2 Avoided (tons/yr) | C26: =ESG!C10 -> 96.475 | D26: =ESG!D10 -> 526.9 | E26: =ESG!E10 -> 2199.825 | F26: =ESG!F10 -> 5049.85 | G26: =ESG!G10 -> 8962.5
B27: Diesel Displaced (L/yr) | C27: =ESG!C11 -> 788400 | D27: =ESG!D11 -> 3153600 | E27: =ESG!E11 -> 14634675 | F27: =ESG!F11 -> 31831650 | G27: =ESG!G11 -> 51738750
B30: INVESTMENT ASK & CAPITAL STACK
B31: Round | C31: Timing | D31: Size | E31: Pre-Money | F31: Post-Money | G31: Dilution
B32: Pre-Seed | C32: Q4 2026 | D32: 500000000 | E32: 5000000000 | F32: 5500000000 | G32: 0.091
B33: Seed | C33: Q2 2027 | D33: 2000000000 | E33: 8000000000 | F33: 10000000000 | G33: 0.2
B34: Series A | C34: Q3 2028 | D34: 20000000000 | E34: 70000000000 | F34: 90000000000 | G34: 0.222
B35: Series B | C35: Q4 2030 | D35: 100000000000 | E35: 400000000000 | F35: 500000000000 | G35: 0.2
B38: "One Battery. Three Lives. Infinite Impact."

Sheet 00_Cover
A1: AXION — VOLTLOOP Ecosystem
A2: Business Process Architecture — Skenario Start-up (Modul 6 Kelompok 1)
A4: Konteks Perusahaan
A5: Nama Perusahaan | B5: AXION (VOLTLOOP Ecosystem)
A6: Industri | B6: Battery Lifecycle Management & EV Infrastructure
A7: Produk/Layanan | B7: VoltBattery, VoltSwap (battery swap network), VoltOS (battery intelligence platform), VoltGrid (2nd-life ESS)
A8: Target Customer | B8: B2C: pengendara motor listrik; B2B: fleet operator, ride-hailing, logistik last-mile, utility/ESS buyer; B2G: kemitraan kota & program elektrifikasi
A9: Model Bisnis | B9: Hybrid: Battery-as-a-Service (subscription), Pay-per-Swap, ESS Leasing, Data/Analytics Licensing
A10: Tahap Bisnis | B10: Early Stage / Pilot Project
A11: Tahap Bisnis | B11: Early Stage / Start-up (Skenario 2)
A12: Tujuan Dokumen | B12: Submission Modul 6 + Proposal Bisnis VOLTLOOP
A13: Daftar Isi (Sheet)
A14: Struktur Workbook
A15: BAGIAN A — PENDAHULUAN
A16: 00_Cover | B16: Halaman judul + konteks perusahaan + daftar isi
A17: 01_Executive_Overview | B17: Ringkasan proses inti, pendukung, value chain start-up
A18: BAGIAN B — TEMPLATE MODUL 6 (UTAMA)
A19: 02_VMV_Startup | B19: Visi, Misi (5), Value (8 — VOLT-LOOP-OP)
A20: 03_Choices | B20: Daftar pilihan dropdown (referensi internal)
A21: 04_Market_Sizing | B21: TAM, SAM, SOM 3 tahun
A22: 05_Objektif | B22: 8 SMART objectives horizon 3 tahun
A23: 06_Prosbis_Inti | B23: Proses bisnis inti hierarkis L1.L2.L3 (kategori 1–6)
A24: 07_Prosbis_Pendukung | B24: Proses bisnis pendukung hierarkis (kategori 7–13)
A25: 08_Task_Interdependency | B25: Keterkaitan input-output antar-proses
A26: 09_Struktur_Organisasi | B26: Bagan organisasi fungsional + rincian divisi
A27: 10_Matriks_RAM | B27: RACI 12 proses L1 × 7 departemen
A28: BAGIAN C — APPENDIX PENDUKUNG (AXION)
A29: A1_Level4_Activity | B29: Breakdown aktivitas Level 4 untuk 6 proses kritis
A30: A2_E2E_Flow | B30: End-to-end flow (Lead-to-Cash, P2P, O2D, dll.)
A31: A3_KPI | B31: KPI dengan formula & PIC
A32: A4_Risk_Control | B32: Risk register dengan heatmap probability-impact
A33: A5_SOP_Draft | B33: Draft SOP 3 proses paling kritis
A34: A6_Improvement | B34: Rekomendasi perbaikan proses

Sheet 01_Executive_Overview
A1: EXECUTIVE OVERVIEW — VOLTLOOP START-UP
A2: Ringkasan satu halaman untuk pembaca cepat — detail lengkap ada di sheet template & appendix.
A3: Komponen | B3: Deskripsi
A4: Proses Inti (Core Value Chain) | B4: Battery Procurement → Battery Testing → VoltBattery Registration → Fleet Deployment → VoltSwap Operation → VoltOS Monitoring → Battery Grading → Lifecycle Routing → VoltGrid / Recycling. Inti bisnis AXION adalah mengelola siklus hidup baterai lithium dari first-life (motor listrik) hingga second-life (ESS) dan end-of-life (recycling), didukung oleh digital twin VoltOS.
A5: Proses Pendukung (Support) | B5: HR (talent battery engineer, swap operator), Finance & Treasury, IT/Cloud Infrastructure untuk VoltOS, Asset Management (stasiun swap, gudang baterai), Procurement vendor cell, Legal & permit, Marketing-Sales B2B/B2C.
A6: Proses Tata Kelola (Governance) | B6: Risk management baterai (thermal runaway, fire safety), Compliance lingkungan (B3 waste, Permen LHK), Quality Assurance grading, Data governance VoltOS, ESG reporting, External Relationship (regulator, mitra recycling, utility).
A7: Alur Nilai (Input → Output) | B7: INPUT: cell baterai dari supplier, energi listrik PLN, modal investor, talenta engineer. PROSES: assembly + testing → deploy ke fleet/swap station → monitoring real-time → grading → routing ke second-life/recycle. OUTPUT: energi mobilitas terjangkau, BaaS subscription, ESS untuk grid, recovered material. CAPTURED VALUE: subscription fee, swap fee, ESS leasing, carbon credit, data licensing.
A8: Customer Utama | B8: (1) Pengendara motor listrik harian (B2C-swap), (2) Fleet operator ride-hailing/logistik (B2B-BaaS), (3) Pembeli ESS komersial & utility (B2B-VoltGrid), (4) Mitra pemerintah kota & program elektrifikasi (B2G).
A9: Value Creation | B9: Menciptakan nilai melalui ekstensi umur baterai (1st life + 2nd life = 2× revenue per unit), efisiensi waktu pengisian (<2 menit swap vs ~4 jam charging), dan intelijen data VoltOS untuk predictive maintenance.
A10: Value Delivery | B10: Mengirim nilai via jaringan VoltSwap (titik fisik), platform VoltOS (digital), dan layanan after-sales/SLA. Fleet B2B menerima SLA uptime baterai; B2C menerima kemudahan swap.
A11: Value Capture | B11: Multi-stream: (a) Battery-as-a-Service subscription bulanan, (b) Pay-per-Swap, (c) ESS leasing/sale ke VoltGrid buyer, (d) Material recovery dari recycling partner, (e) Data & analytics licensing, (f) Carbon credit & ESG incentive.

Sheet 02_VMV_Startup
B2: PERUMUSAN VISI, MISI, DAN VALUE PERUSAHAAN — SKENARIO START-UP (AXION / VOLTLOOP)
B3: Skenario 2 — DIFFERENTIATION: Battery Intelligence Premium untuk Fleet B2B
B7: VISI
B8: Pernyataan Visi | G8: Penjelasan
B9: Menjadi platform ekosistem baterai terdepan di Asia Tenggara yang menghadirkan mobilitas listrik terjangkau dan berkelanjutan melalui inovasi VOLTLOOP — mengubah satu baterai menjadi nilai berlapis dari first-life mobilitas hingga second-life energi. | G9: Visi start-up AXION fokus pada tiga pilar: (1) jangkauan regional Asia Tenggara sebagai panggung pertumbuhan, (2) ekosistem VOLTLOOP sebagai diferensiasi utama yang menutup loop nilai dari mobilitas ke grid storage, (3) keberlanjutan sebagai komitmen jangka panjang. Visi ini menantang namun realistis untuk start-up yang memulai dari Indonesia.
B14: MISI
B15: Pernyataan Misi | G15: Penjelasan
B16: 1. Membangun jaringan VoltSwap yang membuat pengisian baterai motor listrik secepat ganti baterai handphone, sehingga pengendara harian tidak lagi terhambat oleh waktu charging. | G16: Misi ini menjawab komponen Konsumen (rider B2C) dan Produk/Jasa (VoltSwap). Fokus pada pain point terbesar adopsi EV: waktu charging. Menjadi nilai jual utama untuk akuisisi rider.
B17: 2. Mengembangkan platform digital VoltOS yang menjadi otak intelijen setiap baterai, memungkinkan monitoring real-time, prediksi umur, dan keputusan lifecycle yang akurat bagi mitra fleet. | G17: Menjawab komponen Teknologi dan Pekerja. VoltOS adalah moat teknologi start-up. Menjelaskan bahwa AXION bukan hanya perusahaan hardware, tapi data-driven platform company.
B18: 3. Memperpanjang umur ekonomis setiap baterai melalui penyaluran ke VoltGrid (second-life ESS) dan kemitraan recycling tersertifikasi, sehingga satu pack menghasilkan nilai berlapis. | G18: Menjawab komponen Filosofi dan Pandangan Publik (sustainability). Inti dari ekosistem VOLTLOOP — sirkular economy yang menghasilkan revenue stream tambahan + ESG narrative untuk investor.
B19: 4. Menjalin kemitraan strategis dengan fleet operator, OEM motor listrik, utility, dan pemerintah daerah untuk mempercepat adopsi kendaraan listrik di kota-kota Indonesia. | G19: Menjawab komponen Pasar dan Pemerintah. Menegaskan model B2B2C dan B2G; start-up tidak bisa scale sendirian — partnership adalah strategi pertumbuhan utama.
B20: 5. Menjaga keselamatan operasi baterai dan kepatuhan terhadap regulasi B3 sebagai prasyarat mutlak bisnis baterai yang dapat dipercaya konsumen, regulator, dan investor. | G20: Menjawab komponen Self-Concept dan Pemerintah. Industri baterai punya risiko safety tinggi; misi ini menetapkan safety & compliance sebagai non-negotiable, bukan opsi.
B24: VALUES
B25: VALUES
B26: Pernyataan Value | G26: Penjelasan
B27: V — Velocity (Bergerak Cepat, Belajar Cepat) | G27: Start-up menang karena kecepatan eksekusi. Tim mengambil keputusan dengan data minimum yang memadai, merilis fitur dalam siklus pendek, dan belajar dari kegagalan secara cepat.
B28: O — Ownership (Tanggung Jawab Penuh atas Hasil) | G28: Setiap orang adalah pemilik. Tidak ada “bukan tugas saya”. Setiap engineer, operator, dan ops bertanggung jawab end-to-end pada output yang mereka janjikan.
B29: L — Longevity (Membangun untuk Jangka Panjang) | G29: Mencerminkan filosofi VOLTLOOP: memperpanjang umur baterai, memperpanjang umur perusahaan. Keputusan diambil dengan horizon multi-tahun, bukan untuk quick win semata.
B30: T — Trust (Aman, Transparan, Dapat Dipercaya) | G30: Bisnis baterai bergantung pada kepercayaan. Transparansi pada data baterai, billing, safety report, dan kepada regulator adalah kewajiban, bukan pilihan.
B31: L — Loop Thinking (Berpikir Sirkular) | G31: Setiap proses dirancang dengan akhir dalam pikiran: apa yang terjadi setelah pack ini pensiun? Mendorong inovasi second-life dan recycling sejak desain.
B32: O — Open Collaboration (Ekosistem, Bukan Silo) | G32: AXION tidak bisa scale sendirian. Bekerja terbuka dengan OEM, fleet, utility, regulator, dan komunitas riset — saling bagi nilai, saling tumbuh.
B33: O — Operational Discipline (Disiplin Operasional & K3) | G33: Kecepatan tidak boleh mengorbankan keselamatan. Discipline pada SOP K3, audit, dan compliance B3 adalah harga mati dalam industri baterai.
B34: P — Planet-First (Berpihak pada Bumi) | G34: Setiap keputusan bisnis dievaluasi tidak hanya pada profit, tapi pada dampak terhadap lingkungan. Carbon avoided dan circular metric adalah KPI yang dilaporkan.

Sheet 03_Choices
A1: DAFTAR PILIHAN (DROPDOWN REFERENCE) — AXION/VOLTLOOP
A3: Faktor Lingkungan Bisnis | B3: Tingkat | C3: Ketersediaan | D3: Komponen Misi
A4: Industri | B4: Low | C4: Ada | D4: Konsumen
A5: Bahan Baku | B5: Medium | C5: Tidak Ada | D5: Produk / Jasa
A6: Tenaga Kerja | B6: High | D6: Pasar
A7: Keuangan | D7: Teknologi
A8: Pasar | D8: Filosofi
A9: Teknologi | D9: Self-Concept
A10: Kondisi Ekonomi | D10: Pandangan Publik
A11: Pemerintah | D11: Pekerja
A12: Kebudayaan | D12: Fokus
A13: Alam
A14: Internasional

Sheet 04_Market_Sizing
B2: PENENTUAN UKURAN PASAR (MARKET SIZING) — AXION / VOLTLOOP (Start-up)
B4: ⚠ BACKGROUND CONTEXT ONLY (G09) — Top-down TAM ceiling (50-60T IDR). For revenue/SAM/SOM use 'TAM SAM SOM' sheet (bottom-up, 7.7T addressable). See reconciliation there.
B6: Penjelasan Deskriptif Lingkup Market Sizing
B7: AXION beroperasi di tiga pasar terhubung: (1) Battery-as-a-Service untuk motor listrik dan fleet operator di kota-kota Indonesia tier-1 dan tier-2, (2) Energy Storage System (ESS) second-life untuk klien komersial dan utility, (3) data & analytics baterai sebagai add-on. Market sizing fokus pada pasar Indonesia 2026–2030 dengan asumsi laju adopsi EV mengikuti roadmap Kementerian ESDM. [Asumsi: data populasi motor & penetrasi EV menggunakan referensi publik AISI/Kemenperin yang perlu validasi terkini].
B10: TOTAL AVAILABLE MARKET (TAM)
B11: Komponen TAM | F11: Nilai/Estimasi | I11: Asumsi & Sumber | L11: Source Link
B12: Total populasi motor di Indonesia | F12: ± 125 juta unit | I12: Populasi motor nasional [Perlu Validasi — AISI / Korlantas Polri] | L12: BPS Statistik Kendaraan
B13: Potensi konversi motor BBM → motor listrik dalam 5 tahun (10%) | F13: ± 12,5 juta unit | I13: [Asumsi] roadmap akselerasi EV ESDM target 2025–2030 | L13: ESDM Roadmap EV 2030
B14: Nilai pasar layanan energi (BaaS + swap) per unit/tahun | F14: Rp 3–4 juta/unit/tahun | I14: [Asumsi] tarif swap Rp 8–10 rb x 350–400 swap/tahun per rider aktif | L14: Internal estimate
B15: TAM Mobility (BaaS) — estimasi | F15: ± Rp 40–50 triliun/tahun | I15: 12,5 jt unit x Rp 3,5 jt/tahun [Asumsi gabungan] | L15: Kalkulasi internal
B16: TAM ESS Indonesia (industri, telco, gedung komersial) | F16: ± Rp 8–12 triliun/tahun | I16: [Perlu Validasi] referensi pasar ESS BloombergNEF / PLN | L16: Mordor Intelligence ASEAN ESS
B17: TAM TOTAL (Mobility + ESS) | F17: ± Rp 50–60 triliun/tahun | I17: Penjumlahan kasar TAM kedua segmen | L17: Penjumlahan TAM
B20: SERVICEABLE AVAILABLE MARKET (SAM)
B21: Komponen SAM | F21: Nilai/Estimasi | I21: Asumsi & Sumber | L21: Source Link
B22: Kota target 5 tahun (Jabodetabek, Bandung, Surabaya, Medan, Makassar) | F22: 5 kota tier-1 | I22: Lokasi dgn kepadatan motor + dukungan kebijakan EV Pemda [Asumsi] | L22: Internal — target kota
B23: Populasi rider motor harian di 5 kota target | F23: ± 20 juta rider | I23: [Asumsi] berbasis data BPS kota; perlu validasi | L23: BPS Kota
B24: Potensi konversi ke EV + adopsi swap (5%) | F24: ± 1 juta rider | I24: [Asumsi] adoption rate konservatif start-up | L24: Internal adoption rate
B25: SAM Mobility (5 kota, 5 tahun) | F25: ± Rp 3,5–4 triliun/tahun | I25: 1 jt rider x Rp 3,5 jt/tahun | L25: Kalkulasi internal
B26: SAM ESS untuk klien fleet, telco, gedung komersial di 5 kota | F26: ± Rp 1,5 triliun/tahun | I26: [Asumsi] ±15% pangsa ESS di kota target | L26: IndexBox Indonesia AESS
B27: SAM TOTAL | F27: ± Rp 5–5,5 triliun/tahun | I27: Penjumlahan segmen yang bisa dilayani secara realistis | L27: Penjumlahan SAM
B30: SERVICEABLE OBTAINABLE MARKET (SOM)
B31: Komponen SOM (3 tahun pertama) | F31: Nilai/Estimasi | I31: Asumsi & Sumber | L31: Source Link
B32: Tahun 1 — Pilot Jakarta (3 area + 2 fleet operator anchor) | F32: 200 swap station, 5.000 rider aktif, 3 kontrak fleet | I32: [Asumsi] kapasitas eksekusi start-up tahap awal | L32: Internal — pilot plan
B33: Tahun 2 — Ekspansi Jabodetabek + Bandung | F33: 500 station, 20.000 rider, 10 fleet, ESS pilot 5 site | I33: [Asumsi] berbasis funding Series A | L33: Internal — Series A
B34: Tahun 3 — 5 kota tier-1 aktif | F34: 1.200 station, 60.000 rider, 25 fleet, 30 ESS site | I34: [Asumsi] berbasis funding Series B | L34: Internal — Series B
B35: SOM Mobility revenue Tahun 3 | F35: ± Rp 210 miliar/tahun | I35: 60.000 rider x Rp 3,5 jt/tahun | L35: Kalkulasi internal
B36: SOM ESS revenue Tahun 3 | F36: ± Rp 45 miliar/tahun | I36: 30 site x ±Rp 1,5 mil/tahun [Asumsi] | L36: Kalkulasi internal
B37: SOM TOTAL Tahun 3 | F37: ± Rp 255 miliar/tahun | I37: Sekitar 5% dari SAM — wajar untuk start-up agresif | L37: 5% SAM — benchmark
B40: RINGKASAN
B41: TAM | F41: ± Rp 50–60 triliun/tahun
B42: SAM | F42: ± Rp 5–5,5 triliun/tahun
B43: SOM (Tahun 3) | F43: ± Rp 255 miliar/tahun
B44: Catatan | F44: Seluruh angka di sheet ini bersifat indikatif berbasis asumsi start-up. Validasi resmi diperlukan sebelum dipakai dalam proposal investor.

Sheet 05_Objektif
B2: PENETAPAN OBJEKTIF — AXION / VOLTLOOP (Skenario Start-up)
B7: OBJEKTIF STRATEGIS START-UP — HORIZON 3 TAHUN
B8: No. | C8: Objektif (SMART) | F8: Komponen Misi yang Dijawab | H8: Alasan | K8: Referensi / Sumber
B9: 1 | C9: Membangun dan menjalankan 200 VoltSwap station di Jakarta serta menjaring 5.000 rider aktif dan 3 kontrak fleet anchor dalam 12 bulan pertama operasional. | F9: Misi 1 (jaringan swap), Misi 4 (kemitraan fleet) | H9: Tanpa kepadatan station, value proposition swap < 2 menit tidak tercapai. Anchor fleet memberi base load demand yang menjamin utilisasi station di fase awal. | K9: Asumsi internal start-up; perlu validasi rencana CAPEX dan kemitraan lokasi [Perlu Validasi]
B10: 2 | C10: Mencapai swap success rate ≥ 99% dan avg swap time ≤ 120 detik pada akhir Tahun 1, serta NPS rider ≥ 40. | F10: Misi 1, Value Velocity & Trust | H10: Reliability operasional menjadi syarat retention rider; tanpa ini akuisisi rider akan bocor oleh churn dan biaya akuisisi membengkak. | K10: KPI internal Operations (sheet 9_KPI)
B11: 3 | C11: Merilis VoltOS v1.0 dengan modul: real-time monitoring, billing, dan API integrasi fleet partner pada Q3 Tahun 1; mencapai uptime ≥ 99,5% pada Q4 Tahun 1. | F11: Misi 2 (platform VoltOS) | H11: VoltOS adalah moat teknologi sekaligus enabler operasional. Tanpa platform yang reliable, sulit menarik fleet B2B. | K11: Roadmap CTO; sejajar dgn rencana Series A fundraising
B12: 4 | C12: Menjaga zero major safety incident (thermal runaway/kebakaran) dan 100% manifest B3 compliance selama 3 tahun operasional. | F12: Misi 5 (safety & compliance), Value Operational Discipline | H12: Satu insiden besar dapat menghancurkan kepercayaan publik dan menutup izin operasional. Non-negotiable bagi industri baterai. | K12: Permen LHK No. 6/2021 (B3); SNI baterai; sheet 10_Risk_Control
B13: 5 | C13: Membangun first second-life ESS deployment dengan minimal 5 site klien komersial pada akhir Tahun 2 dan 30 site pada Tahun 3. | F13: Misi 3 (perpanjangan umur baterai) | H13: Membuktikan tesis VOLTLOOP (1 pack = 2x revenue). Tanpa ini, start-up hanya akan dilihat sebagai operator swap, bukan platform sirkular. | K13: Roadmap VoltGrid; data pilot grading [Perlu Validasi]
B14: 6 | C14: Mengamankan pendanaan Seed → Series A dengan total Rp 250–350 miliar dalam 24 bulan untuk membiayai CAPEX baterai dan ekspansi station. | F14: Semua misi (enabler) | H14: Industri baterai sangat CAPEX-intensif. Tanpa cadangan kas yang sehat, ekspansi macet dan risiko going concern muncul. | K14: Pitch deck investor; cashflow projection finance team
B15: 7 | C15: Membangun tim inti 80–120 orang pada akhir Tahun 1 dengan turnover engineer < 10% dan mempertahankan ESOP sebagai retention tool utama. | F15: Misi 2 (VoltOS), Value Ownership | H15: Talenta battery engineer dan data scientist langka. Tim adalah aset strategis; turnover tinggi akan menggagalkan roadmap produk. | K15: Manpower plan HR; pasar talenta tech Indonesia
B16: 8 | C16: Menjalin minimal 5 kemitraan strategis (OEM motor listrik, fleet operator besar, utility, recycling, dan Pemda) yang aktif berkontribusi pada operasi pada Tahun 2. | F16: Misi 4 (kemitraan) | H16: Start-up tidak bisa scale sendirian. Ekosistem adalah strategi akuisisi pelanggan dan distribusi yang paling efisien. | K16: Pipeline kemitraan; sheet 13_Architecture (F. External)

Sheet 06_Prosbis_Inti
B2: PROSES BISNIS INTI & KETERSINAMBUNGAN ANTARPROSES — AXION / VOLTLOOP (Start-up)
B6: Proses Bisnis Inti | F6: Data yang akan diubah | H6: Asal Input | I6: Keterangan
B7: L1 | C7: L2 | D7: L3 | E7: Nama Proses | F7: Input | G7: Output | H7: (kode proses)
B8: 1 | E8: Mengembangkan Visi, Misi, dan Strategi Perusahaan
B9: 1 | C9: 1 | E9: Menyusun arah dasar start-up AXION
B10: 1 | C10: 1 | D10: 1 | E10: Memahami kebutuhan pasar mobilitas listrik & kapabilitas start-up | F10: Feedback rider pilot, kapasitas mitra produksi, benchmark kompetitor swap (Gogoro, SUN Mobility), regulasi EV ESDM | G10: Ringkasan peluang pasar, pain point prioritas, pemetaan keunggulan & keterbatasan | H10: — | I10: Sumber: hasil interview rider awal, desk research
B11: 1 | C11: 1 | D11: 2 | E11: Merumuskan identitas & nilai strategis start-up | F11: Hasil pemetaan keunggulan/keterbatasan, analisis tren EV | G11: Visi, misi, nilai inti (VOLT-LOOP), narasi brand awal, landasan pitch | H11: 1.1.1 | I11: Output utama dipakai di seluruh dokumen strategi
B12: 1 | C12: 1 | D12: 3 | E12: Menyusun prioritas & target strategis jangka pendek–menengah | F12: Visi, misi, nilai inti, landasan pitch | G12: Rencana prioritas 6–12 bulan, KPI strategis awal, draft roadmap 3 tahun | H12: 1.1.2 | I12: Menjadi basis OKR korporat dan target fundraising
B13: 1 | C13: 2 | E13: Menyusun strategi fundraising & investment thesis
B14: 1 | C14: 2 | D14: 1 | E14: Menyusun financial model & unit economics per pack | F14: Asumsi CAPEX baterai, tariff swap, OPEX station | G14: Financial model 3 tahun, payback per pack | H14: 1.1.3 | I14: Validasi dgn industri benchmark
B15: 1 | C15: 2 | D15: 2 | E15: Menyusun pitch deck & investor narrative | F15: Financial model, traction pilot, market sizing | G15: Pitch deck Seed/Series A | H15: 1.2.1, 1.1.2 | I15: Input untuk roadshow
B16: 2 | E16: Mengembangkan dan Mengelola Produk (VoltBattery, VoltSwap, VoltOS, VoltGrid)
B17: 2 | C17: 1 | E17: Mengembangkan VoltBattery pack
B18: 2 | C18: 1 | D18: 1 | E18: Menyusun spesifikasi pack (form-factor, kapasitas, BMS, safety) | F18: Profil motor listrik target, regulasi SNI baterai | G18: Spec sheet VoltBattery v1.0 | H18: — | I18: Mengacu pada standar interoperability swap
B19: 2 | C19: 1 | D19: 2 | E19: Membuat prototipe & uji bench | F19: Spec sheet, vendor sample cell | G19: Prototipe teruji + laporan uji lab | H19: 2.1.1 | I19: 3–5 iterasi prototipe
B20: 2 | C20: 1 | D20: 3 | E20: Mendapatkan sertifikasi (SNI, LSPro) | F20: Prototipe final, dokumen uji | G20: Sertifikat SNI VoltBattery | H20: 2.1.2 | I20: Prasyarat penjualan komersial
B21: 2 | C21: 2 | E21: Membangun platform VoltOS
B22: 2 | C22: 2 | D22: 1 | E22: Mendesain arsitektur cloud + IoT VoltOS | F22: Requirement fleet/rider, volume telemetri estimasi | G22: Arsitektur, spec API | H22: 1.1.3 | I22: Multi-tenant, scalable
B23: 2 | C23: 2 | D23: 2 | E23: Membangun modul core (monitoring, billing, integrasi) | F23: Arsitektur, spec API | G23: VoltOS v1.0 release | H23: 2.2.1 | I23: Sprint 6–9 bulan
B24: 2 | C24: 3 | E24: Mendesain VoltSwap station
B25: 2 | C25: 3 | D25: 1 | E25: Mendesain form-factor station, locker, sensor, dan UX | F25: Spec VoltBattery, lokasi pilot, safety code | G25: Blueprint station v1.x | H25: 2.1.1 | I25: Modular agar mudah deploy
B26: 3 | E26: Memasarkan dan Menjual Produk
B27: 3 | C27: 1 | E27: Akuisisi rider B2C
B28: 3 | C28: 1 | D28: 1 | E28: Menyusun strategi growth (digital + komunitas) | F28: Segmentasi rider, pricing | G28: Campaign plan & content calendar | H28: 1.1.2 | I28: Channel: ride-hailing, komunitas motor
B29: 3 | C29: 1 | D29: 2 | E29: Menjalankan akuisisi & onboarding rider | F29: Campaign plan, app, station ready | G29: Rider terdaftar & aktif | H29: 3.1.1 | I29: Target 5.000 rider aktif Tahun 1
B30: 3 | C30: 2 | E30: Akuisisi fleet B2B (BaaS)
B31: 3 | C31: 2 | D31: 1 | E31: Mengidentifikasi & qualify lead fleet | F31: Database fleet operator, pipeline | G31: Qualified pipeline B2B | H31: — | I31: Fokus ride-hailing & logistik
B32: 3 | C32: 2 | D32: 2 | E32: Pilot 30 hari + konversi ke kontrak BaaS | F32: Qualified pipeline, SLA template | G32: Kontrak BaaS aktif | H32: 3.2.1 | I32: 3 anchor di Tahun 1
B33: 3 | C33: 3 | E33: Penjualan VoltGrid (ESS second-life)
B34: 3 | C34: 3 | D34: 1 | E34: Identifikasi klien ESS (komersial, telco, utility) | F34: Profil demand ESS, inventory baterai grade B/C | G34: Pipeline ESS | H34: 5.2.2 | I34: Mulai Tahun 2
B35: 3 | C35: 3 | D35: 2 | E35: Closing kontrak ESS | F35: Pipeline ESS, proposal teknis | G35: Kontrak ESS | H35: 3.3.1 | I35: Target 5 site Tahun 2
B36: 4 | E36: Mengelola Rantai Pasok Produk Fisik (Procure-to-Deploy)
B37: 4 | C37: 1 | E37: Pengadaan cell baterai & komponen
B38: 4 | C38: 1 | D38: 1 | E38: Forecast demand baterai | F38: Pipeline B2B, akuisisi rider | G38: Demand forecast kuartalan | H38: 3.1.2, 3.2.2 | I38: Update bulanan
B39: 4 | C39: 1 | D39: 2 | E39: Sourcing supplier & menetapkan AVL | F39: Spec, demand forecast, audit supplier | G39: Approved Vendor List + PO | H39: 4.1.1, 2.1.1 | I39: Dual-source mandatory
B40: 4 | C40: 2 | E40: Assembly & testing VoltBattery
B41: 4 | C41: 2 | D41: 1 | E41: Incoming QC + assembly | F41: Cell + BMS + casing, work instruction | G41: Pack rakitan + log QC | H41: 4.1.2 | I41: 100% EOL test
B42: 4 | C42: 2 | D42: 2 | E42: Registrasi VoltBattery di VoltOS | F42: Pack lulus QC, UID range | G42: VoltBattery teregistrasi siap deploy | H42: 4.2.1, 2.2.2 | I42: Pairing BMS otomatis
B43: 4 | C43: 3 | E43: Distribusi & reverse logistics
B44: 4 | C44: 3 | D44: 1 | E44: Distribusi pack baru ke station | F44: Inventory plan, fleet & station data | G44: Stok station terisi | H44: 4.2.2 | I44: Fill rate ≥ 95%
B45: 4 | C45: 3 | D45: 2 | E45: Reverse logistics pack aging/EOL | F45: Routing decision VoltOS | G45: Pack terkumpul di hub sortir | H45: 5.2.2 | I45: Sesuai grading A/B/C/X
B46: 5 | E46: Memberikan Layanan (VoltSwap, VoltOS, VoltGrid)
B47: 5 | C47: 1 | E47: Operasi VoltSwap network
B48: 5 | C48: 1 | D48: 1 | E48: Transaksi swap rider (autentikasi → swap → billing) | F48: Akun rider aktif, pack charged | G48: Successful swap + billing entry | H48: 4.3.1, 3.1.2 | I48: Target < 120 detik
B49: 5 | C49: 1 | D49: 2 | E49: Recharge baterai kosong di locker | F49: Pack kosong, profil charging | G49: Pack ter-recharge, kembali ke pool | H49: 5.1.1 | I49: Termal monitor real-time
B50: 5 | C50: 2 | E50: Operasi VoltOS battery intelligence
B51: 5 | C51: 2 | D51: 1 | E51: Real-time monitoring & anomaly detection | F51: Telemetri BMS, GPS | G51: Health score, alert | H51: 2.2.2, 5.1.2 | I51: Latency < 5 detik
B52: 5 | C52: 2 | D52: 2 | E52: Battery grading & lifecycle routing | F52: Riwayat siklus, SoH | G52: Grade A/B/C/X + routing decision | H52: 5.2.1 | I52: Akurasi target ≥ 95%
B53: 5 | C53: 3 | E53: Operasi VoltGrid (ESS)
B54: 5 | C54: 3 | D54: 1 | E54: Instalasi & commissioning ESS | F54: Pack grade B/C, site, inverter | G54: ESS operasional + SLA aktif | H54: 5.2.2, 3.3.2 | I54: Time-to-deploy 14 hari
B55: 5 | C55: 3 | D55: 2 | E55: Operasi & maintenance ESS | F55: Telemetri ESS, kontrak SLA | G55: kWh dilayani, uptime ESS | H55: 5.3.1 | I55: Uptime ≥ 99%
B56: 5 | C56: 4 | E56: End-of-life recycling routing
B57: 5 | C57: 4 | D57: 1 | E57: Manifest B3 & serah-terima ke mitra recycling | F57: Pack grade X, izin pengangkut | G57: Bukti recycling + recovered material | H57: 5.2.2 | I57: Compliance 100%
B58: 6 | E58: Mengelola Layanan Pelanggan
B59: 6 | C59: 1 | E59: Customer service rider & fleet
B60: 6 | C60: 1 | D60: 1 | E60: Penerimaan & triage tiket | F60: Tiket masuk (in-app, call) | G60: Tiket terklasifikasi & prioritas | H60: 5.1.1 | I60: FRT ≤ 5 menit
B61: 6 | C61: 1 | D61: 2 | E61: Penyelesaian / eskalasi tiket | F61: Tiket prioritas, log VoltOS | G61: Tiket closed + survey | H61: 6.1.1 | I61: FCR target ≥ 70%
B62: 6 | C62: 2 | E62: Customer success & retention
B63: 6 | C63: 2 | D63: 1 | E63: Quarterly Business Review (QBR) untuk fleet anchor | F63: Data utilisasi, SLA, NPS | G63: Action plan retention | H63: 5.1.1, 6.1.1 | I63: QBR setiap kuartal

Sheet 07_Prosbis_Pendukung
B2: PROSES BISNIS PENDUKUNG & KETERSINAMBUNGAN ANTARPROSES — AXION / VOLTLOOP (Start-up)
B6: Proses Bisnis Pendukung | F6: Data yang akan diubah | H6: Asal Input | I6: Keterangan
B7: L1 | C7: L2 | D7: L3 | E7: Nama Proses | F7: Input | G7: Output | H7: (kode proses)
B8: 7 | E8: Mengembangkan dan Mengelola Sumber Daya Manusia
B9: 7 | C9: 1 | E9: Merancang strategi SDM start-up
B10: 7 | C10: 1 | D10: 1 | E10: Mengidentifikasi kebutuhan SDM sesuai tahap start-up | F10: Target pertumbuhan 12 bulan, kondisi tim saat ini | G10: Daftar kebutuhan SDM prioritas + skill gap | H10: 1.1.3 | I10: Engineer, ops, data scientist prioritas
B11: 7 | C11: 1 | D11: 2 | E11: Merancang kebijakan dasar pengelolaan SDM + ESOP | F11: Skill gap, praktik kerja, regulasi ketenagakerjaan | G11: Kebijakan kerja dasar, skema ESOP | H11: 7.1.1 | I11: ESOP kunci retention engineer
B12: 7 | C12: 2 | E12: Rekrutmen & onboarding
B13: 7 | C13: 2 | D13: 1 | E13: Menjalankan rekrutmen battery engineer & data scientist | F13: Manpower plan, JD | G13: Kandidat hired | H13: 7.1.1 | I13: Time-to-hire ≤ 45 hari
B14: 7 | C14: 2 | D14: 2 | E14: Onboarding + training K3 baterai wajib | F14: Profil kandidat baru, materi K3 | G14: Karyawan tersertifikasi K3 | H14: 7.2.1 | I14: Tanpa sertifikat K3, dilarang akses baterai
B15: 7 | C15: 3 | E15: Performance & retention
B16: 7 | C16: 3 | D16: 1 | E16: Performance review semesteran | F16: OKR, feedback | G16: Hasil review + action plan | H16: 1.1.3 | I16: Tied to OKR perusahaan
B17: 8 | E17: Mengelola Sistem Teknologi Informasi
B18: 8 | C18: 1 | E18: Operasi VoltOS platform & SRE
B19: 8 | C19: 1 | D19: 1 | E19: Monitoring uptime & incident response | F19: Logs, metrics, runbook | G19: Uptime ≥ 99,5%, RCA | H19: 2.2.2 | I19: On-call rotation 24/7
B20: 8 | C20: 1 | D20: 2 | E20: Release management & deployment | F20: Backlog, hasil QA | G20: Rilis stabil | H20: 2.2.2 | I20: CI/CD pipeline
B21: 8 | C21: 2 | E21: Cybersecurity & data governance
B22: 8 | C22: 2 | D22: 1 | E22: IAM & access control | F22: Daftar role, karyawan | G22: Akses tervalidasi | H22: 7.2.1 | I22: Least-privilege
B23: 8 | C23: 2 | D23: 2 | E23: Compliance UU PDP & ISO 27001 readiness | F23: Policy, threat intel | G23: Audit & sertifikasi readiness | H23: 11.1.1 | I23: Wajib untuk fleet enterprise
B24: 9 | E24: Mengelola Sumber Daya Finansial
B25: 9 | C25: 1 | E25: Finance, accounting, treasury
B26: 9 | C26: 1 | D26: 1 | E26: Closing bulanan & laporan keuangan | F26: Transaksi, invoice, payroll | G26: Laporan keuangan bulanan | H26: 5.1.1 | I26: Audit-ready
B27: 9 | C27: 1 | D27: 2 | E27: Manajemen kas & cashflow forecast | F27: AR/AP, fundraising plan | G27: Cash position + runway | H27: 9.1.1 | I27: Runway minimum 9 bulan
B28: 9 | C28: 2 | E28: Unit economics & investor reporting
B29: 9 | C29: 2 | D29: 1 | E29: Tracking payback per pack & gross margin per kontrak | F29: Revenue swap, OPEX, depresiasi | G29: Dashboard unit economics | H29: 5.1.1, 10.1.1 | I29: Payback < 36 bulan
B30: 9 | C30: 2 | D30: 2 | E30: Reporting investor kuartalan | F30: Laporan keuangan, KPI | G30: Investor update | H30: 9.2.1, 1.2.2 | I30: Sesuai term sheet
B31: 10 | E31: Memperoleh, Membangun, dan Mengelola Aset
B32: 10 | C32: 1 | E32: Manajemen aset baterai & station
B33: 10 | C33: 1 | D33: 1 | E33: Asset registry & tracking (GPS, UID) | F33: UID, lokasi | G33: Asset register up-to-date | H33: 4.2.2 | I33: Loss rate < 0,5%
B34: 10 | C34: 1 | D34: 2 | E34: Maintenance station & ESS | F34: Jadwal preventif, alert VoltOS | G34: Station/ESS terawat | H34: 5.2.1 | I34: Predictive maintenance
B35: 10 | C35: 2 | E35: Manajemen utilisasi & depresiasi
B36: 10 | C36: 2 | D36: 1 | E36: Monitoring utilisasi pack & station | F36: Data swap, telemetri | G36: Laporan utilisasi | H36: 5.1.1 | I36: Input ke unit economics
B37: 11 | E37: Mengelola Risiko, Kepatuhan, dan Resiliensi
B38: 11 | C38: 1 | E38: Battery safety, K3, HSE
B39: 11 | C39: 1 | D39: 1 | E39: Audit safety station & gudang | F39: Checklist K3, regulasi | G39: Laporan audit + CAR | H39: 5.1.1 | I39: Triwulan + sidak
B40: 11 | C40: 1 | D40: 2 | E40: Drill kebakaran & emergency response | F40: Skenario insiden | G40: Tim terlatih | H40: 7.2.2 | I40: Min 2x/tahun per site
B41: 11 | C41: 1 | D41: 3 | E41: B3 waste & manifest compliance | F41: Pack grade X, manifest | G41: Manifest valid 100% | H41: 5.4.1 | I41: Permen LHK
B42: 11 | C42: 2 | E42: Enterprise Risk & BCP
B43: 11 | C43: 2 | D43: 1 | E43: Risk register & quarterly risk review | F43: Insiden, audit, scenario | G43: Risk register update | H43: 11.1.1 | I43: Top 10 risk tracked
B44: 11 | C44: 2 | D44: 2 | E44: BCP test (DR, gangguan listrik, supply chain) | F44: BCP plan | G44: Test report | H44: 11.2.1 | I44: 1x/tahun min
B45: 12 | E45: Mengelola Hubungan Eksternal
B46: 12 | C46: 1 | E46: Regulator, recycling partner, utility
B47: 12 | C47: 1 | D47: 1 | E47: Pemeliharaan izin operasional (ESDM, LHK, Pemda) | F47: Regulasi, laporan | G47: Izin valid | H47: 11.1.3 | I47: Wajib aktif
B48: 12 | C48: 1 | D48: 2 | E48: Pengelolaan kemitraan recycling & utility | F48: MoU, jadwal audit | G48: Hubungan mitra aktif | H48: 5.4.1 | I48: Minimal 3 mitra recycling
B49: 12 | C49: 2 | E49: Hubungan investor & komunitas
B50: 12 | C50: 2 | D50: 1 | E50: Board meeting & ESG report | F50: Financial, ESG metric | G50: Board update + ESG disclosure | H50: 9.2.2 | I50: Tahap awal: GRI/SASB-light
B51: 13 | E51: Mengembangkan dan Mengelola Kapabilitas Bisnis
B52: 13 | C52: 1 | E52: [Belum prioritas pada tahap start-up] | F52: — | G52: — | H52: — | I52: Akan aktif saat scale-up (PMO, transformation office)

Sheet 08_Task_Interdependency
B2: TASK INTERDEPENDENCY — AXION / VOLTLOOP (Start-up)
B3: Sheet ini memetakan keterkaitan input-output antara dua proses bisnis. Proses A membutuhkan output dari Proses B sebagai input. Mengacu pada kode hierarki di sheet T8 (Inti) dan T11 (Pendukung).
B6: No. | C6: Proses Bisnis (A) | G6: Proses Bisnis Relevan (B) | K6: Input dari B | M6: Output ke A
C7: Kode | D7: Nama Aktivitas A | G7: Kode | H7: Nama Aktivitas B
B8: 1 | C8: 4.1.1 | D8: Forecast demand baterai | G8: 3.2.2 | H8: Closing kontrak BaaS dengan fleet | K8: Volume pack berdasarkan kontrak fleet yang akan aktif | M8: Pipeline kontrak terkalibrasi ke forecast
B9: 2 | C9: 4.1.2 | D9: Sourcing supplier & PO cell baterai | G9: 4.1.1 | H9: Forecast demand baterai | K9: Demand forecast kuartalan | M9: Jumlah PO yang harus diterbitkan
B10: 3 | C10: 4.2.1 | D10: Assembly & EOL test VoltBattery | G10: 4.1.2 | H10: Sourcing & penerimaan cell | K10: Cell + BMS lulus incoming QC | M10: Bahan baku siap dirakit
B11: 4 | C11: 4.2.2 | D11: Registrasi VoltBattery di VoltOS | G11: 4.2.1 | H11: Assembly & EOL test | K11: Pack lulus QC + serial number | M11: Pack siap diberi UID & paired ke VoltOS
B12: 5 | C12: 4.3.1 | D12: Distribusi pack ke station | G12: 4.2.2 | H12: Registrasi di VoltOS | K12: Pack terdaftar dgn status “Ready to Deploy” | M12: Inventory siap dialokasi ke station
B13: 6 | C13: 5.1.1 | D13: Transaksi swap rider | G13: 4.3.1 | H13: Distribusi pack ke station | K13: Stok pack charged di station | M13: Locker terisi siap swap
B14: 7 | C14: 5.2.2 | D14: Battery grading & routing | G14: 5.2.1 | H14: Real-time monitoring & anomaly detection | K14: Riwayat siklus, SoH per pack | M14: Data lengkap untuk grading
B15: 8 | C15: 5.3.1 | D15: Instalasi & commissioning ESS | G15: 5.2.2 | H15: Battery grading & routing | K15: Pack grade B/C diputuskan utk VoltGrid | M15: Pack tersedia untuk ESS deployment
B16: 9 | C16: 11.1.3 | D16: B3 waste & manifest compliance | G16: 5.2.2 | H16: Battery grading & routing | K16: Pack grade X diputuskan utk recycle | M16: Material untuk manifest B3
B17: 10 | C17: 6.1.2 | D17: Penyelesaian tiket rider | G17: 5.1.1 | H17: Transaksi swap rider | K17: Log transaksi & telemetri pack | M17: Data audit untuk resolve tiket
B18: 11 | C18: 9.1.2 | D18: Manajemen kas & cashflow forecast | G18: 5.1.1 | H18: Transaksi swap rider | K18: Revenue swap harian | M18: Input AR & cashflow
B19: 12 | C19: 9.2.1 | D19: Tracking payback per pack | G19: 10.2.1 | H19: Monitoring utilisasi pack | K19: Utilisasi & cycle count per pack | M19: Denominator unit economics
... B25: 18 | C25: 12.2.1 | D25: Board meeting & ESG report | G25: 9.2.1 | H25: Tracking payback per pack | K25: Unit economics dashboard | M25: Materi update kinerja ke board

Sheet 09_Struktur_Organisasi
B2: STRUKTUR ORGANISASI — AXION / VOLTLOOP (Skenario Start-up)
B6: Tipe Struktur Organisasi: | E6: Fungsional (Functional)
B7: Alasan Pemilihan: | E7: Pada tahap start-up early, struktur fungsional dipilih agar setiap fungsi inti (Produk, Operasi, Teknologi, Komersial, Keuangan) memiliki ekspertise mendalam dan jalur pelaporan jelas. Saat scale-up nanti, struktur dapat berevolusi ke matrix atau divisional per region/produk.
B10: BAGAN STRUKTUR ORGANISASI
G12: BOARD OF DIRECTORS
G13: │
G14: CEO / FOUNDER
G15: │
B17: COO (Chief Operating Officer) | D17: CTO (Chief Technology Officer) | F17: CCO (Chief Commercial Officer) | H17: CFO (Chief Financial Officer) | J17: Head of People & Risk
B20: Dept. Battery Production & Supply Chain | D20: Dept. VoltOS Engineering & Data | F20: Dept. Sales & Partnerships | H20: Dept. Finance & Treasury | J20: Dept. HR & HSE/Compliance
B21: Dept. Network Operations (Swap Station & VoltGrid) | D21: Dept. Platform & Cybersecurity | F21: Dept. Marketing & Customer Experience | H21: Dept. FP&A & Accounting | J21: Dept. External Affairs
B25: RINCIAN DIVISI DI BAWAH DEPARTEMEN
B27: Departemen | D27: Divisi | F27: Tanggung Jawab Utama
B28: Battery Production & Supply Chain | D28: Procurement | F28: Sourcing cell, BMS, komponen; vendor management
B29: Battery Production & Supply Chain | D29: Assembly & QA Lab | F29: Assembly pack, incoming/EOL test, sertifikasi
B30: Battery Production & Supply Chain | D30: Logistics & Reverse Logistics | F30: Distribusi pack, penarikan pack EOL
B31: Network Operations | D31: Swap Network Operations | F31: Operasional harian swap station, monitoring lapangan
B32: Network Operations | D32: VoltGrid (ESS) Operations | F32: Instalasi, commissioning, O&M ESS
B33: Network Operations | D33: Asset Management | F33: Registry, depresiasi, utilisasi, maintenance
B34: VoltOS Engineering & Data | D34: Software Engineering | F34: Build & rilis modul VoltOS
B35: VoltOS Engineering & Data | D35: Data Science & Battery Intelligence | F35: Algoritma grading, predictive maintenance
B36: VoltOS Engineering & Data | D36: IoT & Embedded | F36: BMS firmware, IoT gateway
B37: Platform & Cybersecurity | D37: SRE & Cloud | F37: Cloud infra, uptime, incident response
B38: Platform & Cybersecurity | D38: Cybersecurity & Data Governance | F38: IAM, security, ISO 27001 readiness, UU PDP
... B51: External Affairs | D51: ESG & Communications | F51: ESG report, komunikasi publik, mitra recycling

Sheet 10_Matriks_RAM
B2: RESPONSIBILITY ASSIGNMENT MATRIX (RAM) — AXION / VOLTLOOP (Skenario Start-up)
B3: R = Responsible (mengerjakan) | A = Accountable (penanggung jawab akhir) | C = Consulted | I = Informed
B6: Proses Bisnis (L1) | D6: Direktur Utama (CEO) | E6: Battery Production & Supply Chain | G6: Network Operations | I6: VoltOS Engineering & Data | K6: Sales & Partnerships | M6: Finance & Treasury | O6: HR & HSE / Compliance | Q6: External Affairs
B7: Kode | C7: Nama Proses | D7: CEO | E7: Kepala Dept | F7: Divisi | G7: Kepala Dept | H7: Divisi | I7: Kepala Dept | J7: Divisi | K7: Kepala Dept | L7: Divisi | M7: Kepala Dept | N7: Divisi | O7: Kepala Dept | P7: Divisi | Q7: Kepala Dept | R7: Divisi
B8: 1 | C8: Mengembangkan Visi, Misi, dan Strategi | D8: A/R | E8: C | F8: I | G8: C | H8: I | I8: C | J8: I | K8: C | L8: I | M8: C | N8: I | O8: C | P8: I | Q8: C | R8: I
B9: 2 | C9: Mengembangkan & Mengelola Produk | D9: A | E9: C | F9: C | G9: C | H9: I | I9: R | J9: R | K9: C | L9: I | M9: I | N9: I | O9: I | P9: I | Q9: I | R9: I
B10: 3 | C10: Memasarkan & Menjual Produk | D10: A | E10: I | F10: I | G10: C | H10: I | I10: I | J10: I | K10: R | L10: R | M10: C | N10: I | O10: I | P10: I | Q10: C | R10: I
B11: 4 | C11: Mengelola Rantai Pasok Produk Fisik | D11: I | E11: A | F11: R | G11: C | H11: C | I11: C | J11: I | K11: I | L11: I | M11: C | N11: I | O11: I | P11: I | Q11: I | R11: I
B12: 5 | C12: Memberikan Layanan (Swap, VoltOS, ESS) | D12: I | E12: C | F12: I | G12: A | H12: R | I12: C | J12: C | K12: I | L12: I | M12: I | N12: I | O12: I | P12: I | Q12: I | R12: I
B13: 6 | C13: Mengelola Layanan Pelanggan | D13: I | E13: I | F13: I | G13: C | H13: I | I13: C | J13: I | K13: A | L13: R | M13: I | N13: I | O13: I | P13: I | Q13: I | R13: I
B14: 7 | C14: Mengembangkan & Mengelola SDM | D14: I | E14: C | F14: I | G14: C | H14: I | I14: C | J14: I | K14: C | L14: I | M14: I | N14: I | O14: A | P14: R | Q14: I | R14: I
B15: 8 | C15: Mengelola Sistem Teknologi Informasi | D15: I | E15: I | F15: I | G15: C | H15: I | I15: A | J15: R | K15: I | L15: I | M15: I | N15: I | O15: C | P15: I | Q15: I | R15: I
B16: 9 | C16: Mengelola Sumber Daya Finansial | D16: C | E16: C | F16: I | G16: C | H16: I | I16: C | J16: I | K16: C | L16: I | M16: A | N16: R | O16: C | P16: I | Q16: I | R16: I
B17: 10 | C17: Memperoleh, Membangun & Mengelola Aset | D17: I | E17: C | F17: C | G17: A | H17: R | I17: C | J17: I | K17: I | L17: I | M17: C | N17: I | O17: I | P17: I | Q17: I | R17: I
B18: 11 | C18: Mengelola Risiko, Kepatuhan & Resiliensi | D18: I | E18: C | F18: I | G18: C | H18: I | I18: C | J18: I | K18: I | L18: I | M18: C | N18: I | O18: A | P18: R | Q18: C | R18: I
B19: 12 | C19: Mengelola Hubungan Eksternal | D19: C | E19: I | F19: I | G19: C | H19: I | I19: I | J19: I | K19: C | L19: I | M19: C | N19: I | O19: C | P19: I | Q19: A | R19: R

Sheet A1_Level4_Activity
A1: 5. APQC LEVEL 4 ACTIVITY BREAKDOWN — 6 PROSES TERPILIH
A2: 3 Core: Battery Testing & Registration | Rider Swap Transaction | Battery Grading & Routing | 2 Support: Procurement | VoltOS Reliability | 1 Governance: Battery Safety & B3 Compliance
A4: Proses Lv3 | B4: # | C4: Aktivitas Level 4 | D4: Aktor Penanggung Jawab | E4: Dokumen/Data Dibutuhkan | F4: Sistem/Tools | G4: Output Aktivitas | H4: Kontrol Kualitas
A5: CORE — 4.2.1/4.2.2 Battery Testing & VoltOS Registration
B6: 1 | C6: Terima batch cell dari supplier & cocokkan dengan PO | D6: Warehouse Officer | E6: Packing list, PO | F6: WMS, barcode scanner | G6: Batch diterima & terdokumentasi | H6: 3-way match (PO, DO, fisik)
B7: 2 | C7: Sampling visual & dimensi cell | D7: QC Inspector | E7: Spec drawing | F7: Caliper, checklist | G7: Sample lulus visual | H7: AQL sampling plan
B8: 3 | C8: Capacity & internal resistance test | D8: QA Lab Engineer | E8: Protokol test | F8: Battery cycler, IR meter | G8: Hasil test per cell | H8: Reject cell di luar 3% nominal
B9: 4 | C9: Assembly pack VoltBattery (cell + BMS + casing) | D9: Production Operator | E9: Work instruction | F9: Jig assembly, torque wrench | G9: Pack rakitan | H9: Torque & isolation check tiap unit
B10: 5 | C10: End-of-line test (charge, discharge, BMS comm) | D10: QA Engineer | E10: EOL test sheet | F10: EOL tester | G10: Pack lulus QC + sertifikat | H10: 100% test, signed by QA
B11: 6 | C11: Generate UID & registrasi ke VoltOS | D11: VoltOS Engineer | E11: Asset registry | F11: VoltOS API, NFC writer | G11: Pack terdaftar dengan UID unik | H11: Validasi unique UID + pairing BMS
B12: 7 | C12: Status “Ready to Deploy” & masuk gudang | D12: Warehouse + VoltOS | E12: WMS record | F12: WMS, VoltOS | G12: Stok siap deploy | H12: Status sinkron antar sistem
A14: CORE — 5.1.1 Rider Battery Swap Transaction
B15: 1 | C15: Rider tap NFC / scan QR di stasiun | D15: Rider | E15: Akun aktif | F15: Swap kiosk, App | G15: Sesi autentikasi | H15: Validasi saldo + status akun
B16: 2 | C16: VoltOS pilih locker dgn baterai SoC tertinggi | D16: VoltOS | E16: Inventory locker | F16: VoltOS allocation | G16: Locker terpilih | H16: Hanya locker dgn SoC > 90% dipilih
B17: 3 | C17: Rider taruh baterai kosong di locker yg ditunjuk | D17: Rider | E17: — | F17: Swap kiosk | G17: Baterai kosong tersimpan | H17: Sensor berat & UID match
B18: 4 | C18: VoltOS unlock locker baterai full | D18: VoltOS | E18: Token sesi | F18: Locker actuator | G18: Locker terbuka | H18: Timeout & retry handler
B19: 5 | C19: Rider ambil baterai full & pasang di motor | D19: Rider | E19: — | F19: — | G19: Swap fisik selesai | H19: Konfirmasi pairing baterai-motor
B20: 6 | C20: Bill ke akun & catat di VoltOS | D20: VoltOS Billing | E20: Tariff plan | F20: Payment gateway | G20: Transaksi tercatat | H20: Reconcile harian
B21: 7 | C21: Mulai siklus charging baterai kosong di locker | D21: Station | E21: Charging profile | F21: BMS, charger | G21: Baterai naik SoC | H21: Termal & abnormal monitor
A23: CORE — 5.2.2 Battery Grading & Lifecycle Routing
B24: 1 | C24: Agregasi data siklus & SoH per pack | D24: VoltOS Data Eng | E24: History telemetri | F24: Data lake, BI | G24: Profil baterai per UID | H24: Data completeness > 98%
B25: 2 | C25: Jalankan algoritma grading (A/B/C/X) | D25: VoltOS Algorithm | E25: Model grading | F25: ML pipeline | G25: Grade tentatif | H25: Confidence threshold + audit sample
B26: 3 | C26: Review manual QA untuk grade borderline | D26: QA Engineer | E26: Laporan grading | F26: VoltOS QA module | G26: Grade final | H26: 4-eyes principle
B27: 4 | C27: Tentukan jalur lanjut (continue 1st life / VoltGrid / recycle) | D27: COO + VoltGrid Head | E27: Kapasitas ESS demand | F27: VoltOS routing | G27: Routing decision | H27: Approval sign-off
B28: 5 | C28: Buat work order pemindahan asset | D28: Logistics | E28: WO | F28: WMS | G28: WO terbit | H28: Chain-of-custody log
B29: 6 | C29: Update asset registry & status di VoltOS | D29: Asset Manager | E29: Asset registry | F29: VoltOS | G29: Status baru tercatat | H29: Audit trail tertulis
A31: SUPPORT — 4.1.1 Battery Procurement & Vendor Management
B32: 1 | C32: Forecast demand baterai per kuartal | D32: FP&A + Ops | E32: Sales pipeline, churn rate | F32: ERP, BI | G32: Demand forecast | H32: Review forecast vs actual bulanan
B33: 2 | C33: Update Approved Vendor List | D33: Procurement, QA | E33: Audit supplier, sample test | F33: Vendor portal | G33: AVL terbaru | H33: Re-audit tahunan
B34: 3 | C34: Terbitkan RFQ ke 3+ supplier | D34: Procurement | E34: Spec teknis, volume | F34: e-Procurement | G34: Quote masuk | H34: Minimal 3 quote
B35: 4 | C35: Evaluasi teknis & komersial | D35: Procurement + CTO | E35: Scoring matrix | F35: Spreadsheet | G35: Vendor terpilih | H35: Dual sign-off
B36: 5 | C36: Negosiasi & terbitkan PO | D36: Procurement, Legal | E36: Draft kontrak | F36: ERP | G36: PO terbit | H36: PO sesuai anggaran (CFO approval)
B37: 6 | C37: Monitoring pengiriman & QC incoming | D37: Procurement + QA | E37: Tracking, packing list | F37: WMS | G37: Cell diterima | H37: OTD tracking + defect rate
A39: SUPPORT — 8.1.1 VoltOS Reliability Engineering
B40: 1 | C40: Setup observability (metric, log, trace) | D40: SRE | E40: Runbook | F40: Prometheus, Grafana, ELK | G40: Dashboard SRE | H40: SLO defined per service
B41: 2 | C41: On-call rotation & paging | D41: SRE Team | E41: Schedule | F41: PagerDuty/OpsGenie | G41: Engineer standby 24/7 | H41: Ack < 5 menit
B42: 3 | C42: Incident response saat alert | D42: On-call SRE | E42: Runbook | F42: Incident channel | G42: Mitigasi | H42: MTTR < 30 menit untuk SEV-1
B43: 4 | C43: Root cause analysis & post-mortem | D43: SRE + Eng | E43: Logs, timeline | F43: Wiki | G43: RCA doc | H43: Blameless template + action item tracker
B44: 5 | C44: Capacity planning & chaos drill | D44: SRE + Platform Lead | E44: Forecast load | F44: k6, ChaosMonkey | G44: Sistem resilient | H44: Drill kuartalan
A46: GOVERNANCE — 11.1.1 Battery Safety & B3 Waste Compliance
B47: 1 | C47: Pemetaan regulasi (Permen LHK, K3, SNI baterai) | D47: Compliance Officer | E47: Database regulasi | F47: GRC tool / spreadsheet | G47: Daftar regulasi berlaku | H47: Update kuartalan
B48: 2 | C48: Audit safety swap station & gudang | D48: HSE Auditor | E48: Checklist K3 | F48: Audit app | G48: Laporan temuan | H48: Audit terjadwal + sidak
B49: 3 | C49: Corrective action atas temuan | D49: Site Manager | E49: CAR log | F49: GRC tool | G49: CAR closed | H49: Verifikasi penutupan oleh auditor
B50: 4 | C50: Manifest B3 untuk baterai EOL | D50: Compliance + Logistics | E50: Manifest LHK, izin pengangkut | F50: Sistem manifest LHK | G50: Manifest tervalidasi | H50: Tanda tangan pihak ke-3 wajib
B51: 5 | C51: Drill kebakaran & emergency response | D51: HSE | E51: Skenario | F51: — | G51: Tim terlatih | H51: Min 2x/tahun per site
B52: 6 | C52: Lapor ke regulator & investor (ESG) | D52: External Affairs + CFO | E52: Data kepatuhan | F52: Reporting tool | G52: Laporan terkirim | H52: Sign-off CEO sebelum submit

Sheet A2_E2E_Flow
A1: 6. END-TO-END BUSINESS PROCESS FLOW
A3: Alur (Cycle) | B3: Input | C3: Process (langkah utama) | D3: Output | E3: Customer Value
A4: Lead-to-Cash (B2B Fleet) | B4: Lead fleet operator | C4: Qualify → Demo → Pilot 30 hari → Negosiasi SLA → Kontrak BaaS → Deploy baterai → Billing bulanan → Renewal | D4: Kontrak BaaS aktif & cash in | E4: Fleet beroperasi tanpa downtime, OPEX prediktabel
A5: Procure-to-Pay (Cell Battery) | B5: Demand forecast | C5: RFQ → Evaluasi → PO → Receive → QC → 3-way match → Invoice → Pembayaran supplier | D5: Cell baterai lulus QC + AP lunas | E5: Supplier puas, supply chain stabil
A6: Order-to-Delivery (Rider Swap) | B6: Rider request swap | C6: Autentikasi → Locker assignment → Swap fisik → Billing → Recharge baterai kosong | D6: Successful swap < 2 menit | E6: Rider lanjut beroperasi tanpa antri charge
A7: Concept-to-Launch (VoltOS Feature) | B7: Insight fleet/data | C7: Discovery → Spec → Design → Build → QA → Beta → Rilis → Adopsi | D7: Fitur VoltOS rilis | E7: Customer (fleet) dapat insight & kontrol lebih baik
A8: Issue-to-Resolution (Rider/Fleet) | B8: Tiket / alert insiden | C8: Receive → Triage → Diagnose → Resolve / Escalate → Close → Survey | D8: Tiket closed & CSAT | E8: Customer merasa didukung, churn turun
A9: Hire-to-Retire (Battery Engineer) | B9: Manpower plan | C9: Sourcing → Seleksi → Hire → Onboarding → Training K3 → Performance review → Career path / exit | D9: Talenta produktif | E9: Engineer kompeten = produk handal
A10: Record-to-Report | B10: Transaksi harian | C10: Capture → Klasifikasi → Rekonsiliasi → Closing bulanan → Laporan keuangan & investor | D10: Laporan keuangan akurat | E10: Investor & manajemen punya keputusan berbasis data
A11: Risk-to-Mitigation | B11: Risk register / kejadian | C11: Identifikasi → Asesmen → Treatment plan → Implementasi kontrol → Monitoring → Review | D11: Residual risk acceptable | E11: Operasi aman & compliant
A12: Battery Lifecycle (UNIK — VOLTLOOP) | B12: Cell baterai baru | C12: Procurement → Testing → VoltOS Registration → Fleet Deployment → VoltSwap Operation → VoltOS Monitoring → Grading → Routing (1st life / VoltGrid / Recycling) | D12: Baterai menghasilkan revenue 2x umur normal | E12: Customer + planet diuntungkan (sirkular)

Sheet A3_KPI
A1: 9. KPI & PERFORMANCE MEASUREMENT — VOLTLOOP
A3: Kategori | B3: Proses | C3: KPI | D3: Definisi KPI | E3: Formula | F3: Target Awal | G3: Frekuensi | H3: PIC
A4: Operational Efficiency | B4: VoltSwap Operation | C4: Swap Success Rate | D4: % transaksi swap selesai sukses | E4: (Swap sukses / total attempt) × 100% | F4: >= 99% | G4: Harian | H4: Head of Operations
A5: Operational Efficiency | B5: VoltSwap Operation | C5: Average Swap Time | D5: Waktu rata-rata per transaksi | E5: Avg(end-time − start-time) | F5: <= 120 detik | G5: Harian | H5: Head of Operations
A6: Operational Efficiency | B6: Distribution | C6: Station Fill-Rate | D6: % station memiliki baterai charged tersedia | E6: Station-hour dgn stok ≥ 1 / total station-hour | F6: >= 95% | G6: Harian | H6: Head of Logistics
A7: Cost Efficiency | B7: Procurement | C7: Cost per kWh | D7: Biaya cell + assembly per kWh | E7: Total cost / total kWh diproduksi | F7: Turun 10% YoY | G7: Bulanan | H7: COO + CFO
A8: Cost Efficiency | B8: Unit Economics | C8: Payback Period per Battery Pack | D8: Berapa lama hingga 1 pack break-even | E8: CAPEX pack / (revenue − OPEX per bulan) | F8: <= 36 bulan | G8: Bulanan (per cohort) | H8: CFO + FP&A
A9: Customer Satisfaction | B9: Customer Service | C9: NPS | D9: Net Promoter Score rider & fleet | E9: % promoter − % detractor | F9: >= 40 | G9: Triwulan | H9: Head of CS
A10: Customer Satisfaction | B10: Customer Service | C10: First Response Time (FRT) | D10: Waktu rata-rata respon pertama | E10: Avg(first reply − ticket open) | F10: <= 5 menit | G10: Harian | H10: Head of CS
A11: Revenue Growth | B11: Sales B2B & B2C | C11: ARR (Annual Recurring Revenue) | D11: Total kontrak subscription tahunan | E11: Sum(MRR aktif) × 12 | F11: Target per fundraising stage | G11: Bulanan | H11: CEO + CFO
A12: Revenue Growth | B12: Sales B2B | C12: Jumlah baterai aktif di fleet | D12: Active pack di kontrak BaaS | E12: Count(active pack) | F12: Tumbuh 20% QoQ [Asumsi] | G12: Bulanan | H12: Head of B2B Sales
A13: Product Reliability | B13: Battery Lifecycle | C13: Cycle Life Achieved | D13: Rata-rata siklus pack sebelum SoH < 80% | E13: Avg(siklus → SoH 80%) | F13: >= 2000 cycles | G13: Triwulan | H13: CTO + QA
A14: Product Reliability | B14: Quality | C14: Field Defect Rate | D14: % pack gagal di lapangan | E14: Failed pack / deployed pack | F14: <= 0.5% per tahun | G14: Bulanan | H14: QA + COO
A15: Risk & Compliance | B15: HSE | C15: Safety Incident (Thermal/Fire) | D15: Jumlah insiden kebakaran/thermal runaway | E15: Count(insiden) per bulan | F15: 0 insiden | G15: Bulanan | H15: Head of HSE
A16: Risk & Compliance | B16: B3 Waste | C16: Manifest Compliance Rate | D16: % baterai EOL dgn manifest B3 lengkap | E16: Manifest valid / total EOL pack | F16: 1 | G16: Bulanan | H16: Compliance Officer
A17: Technology Performance | B17: VoltOS Platform | C17: Platform Uptime | D17: % waktu VoltOS available | E17: Uptime / total time | F17: >= 99.9% | G17: Bulanan | H17: CTO / SRE
A18: Technology Performance | B18: VoltOS Monitoring | C18: Grading Accuracy | D18: Akurasi algoritma grading vs lab | E18: Correct grade / total sample | F18: >= 95% | G18: Triwulan | H18: VoltOS Data Lead
A19: Lifecycle / Sustainability | B19: Battery Lifecycle | C19: Second-Life Conversion Rate | D19: % pack 1st-life yang lanjut ke VoltGrid | E19: Pack masuk VoltGrid / pack pensiun 1st life | F19: >= 60% | G19: Triwulan | H19: Head of VoltGrid

Sheet A4_Risk_Control
A1: 10. RISK & CONTROL POINT
A3: Proses | B3: Risiko | C3: Penyebab | D3: Dampak | E3: Probability | F3: Impact | G3: Control Point | H3: Mitigasi | I3: Early Warning Indicator
A4: Battery Procurement | B4: Cell counterfeit / kualitas rendah | C4: Supplier tidak tersertifikasi, harga miring | D4: Kebakaran lapangan, recall massal | E4: Medium | F4: High | G4: Incoming QC + audit supplier | H4: AVL, dual-source, sample test 100% batch awal | I4: Defect rate batch naik
A5: Assembly & Testing | B5: Lolos cell defective | C5: Sampling tidak ketat / EOL test lemah | D5: Thermal runaway saat dipakai | E5: Low | F5: Catastrophic | G5: 100% EOL test + 4-eye sign-off | H5: Investasi tester, training, traceability UID | I5: Escape rate > 0.1%
A6: VoltSwap Operation | B6: Stockout di jam sibuk | C6: Distribusi kurang, demand surge | D6: Rider churn, reputasi rusak | E6: High | F6: Medium | G6: Real-time stock monitoring + reorder threshold | H6: Demand forecast, dynamic dispatch, buffer 20% | I6: Fill-rate < 90%
A7: VoltSwap Operation | B7: Vandalisme / pencurian baterai | C7: Lokasi rawan, kontrol fisik lemah | D7: Asset loss, biaya pengganti | E7: Medium | F7: Medium | G7: CCTV, GPS tracking, locker terkunci | H7: Lokasi terpilih, asuransi, geofencing | I7: Loss rate > 0.5%/bulan
A8: VoltOS Monitoring | B8: Data outage / IoT gateway down | C8: Konektivitas/komponen gagal | D8: Tidak bisa mendeteksi anomali | E8: Medium | F8: High | G8: Heartbeat monitoring + dual-network (4G+LoRa) | H8: Redundansi gateway, offline buffer | I8: Drop telemetri > 2%
A9: Battery Grading | B9: Grading salah → ESS underperform | C9: Model belum matang | D9: Klaim SLA, biaya replace | E9: Medium | F9: High | G9: Lab cross-check & confidence threshold | H9: Continuous model retraining, audit sampling | I9: Akurasi turun < 90%
A10: EOL Recycling | B10: Pelanggaran B3 | C10: Mitra tidak berlisensi | D10: Denda LHK, izin dicabut | E10: Low | F10: High | G10: Manifest B3 + verifikasi izin partner | H10: Hanya partner ber-izin, audit triwulan | I10: Manifest invalid > 0
A11: Sales B2B | B11: Pricing tidak profitable | C11: Tekanan negosiasi | D11: Margin negatif | E11: Medium | F11: High | G11: Approval CFO untuk diskon > X% | H11: Pricing tool berbasis unit economics | I11: Gross margin per kontrak turun
A12: Customer Service | B12: Penanganan lambat → churn | C12: Volume tinggi, agent kurang | D12: Reputasi & retention turun | E12: Medium | F12: Medium | G12: SLA tier + auto-escalation | H12: Self-service portal, chatbot, training | I12: FRT > target, CSAT turun
A13: Finance | B13: Cash burn > runway | C13: CAPEX baterai besar, fundraising mundur | D13: Risiko going concern | E13: Medium | F13: Catastrophic | G13: Monthly cash review + scenario plan | H13: Multi-stage fundraising, asset financing, leasing | I13: Runway < 9 bulan
A14: IT / VoltOS | B14: Cyber attack / data breach | C14: Vulnerability, phishing | D14: Data rider/fleet bocor, sanksi UU PDP | E14: Medium | F14: High | G14: SOC, pentest, IAM | H14: ISO 27001 readiness, security training | I14: Anomali login / IOC
A15: HR | B15: Hilangnya key engineer | C15: Kompetisi talenta tinggi | D15: Roadmap VoltOS molor | E15: Medium | F15: High | G15: Succession plan + knowledge mgmt | H15: ESOP, dokumentasi, knowledge sharing | I15: Turnover engineer > 15%/tahun

Sheet A5_SOP_Draft
A1: 11. SOP DRAFT — 3 PROSES PALING KRITIS
A3: SOP-001 — Battery Testing & VoltOS Registration
A4: Tujuan | B4: Memastikan setiap VoltBattery yang diproduksi memenuhi spec teknis dan memiliki digital identity yang valid di VoltOS sebelum di-deploy.
A5: Ruang Lingkup | B5: Dari kedatangan cell baterai sampai status “Ready to Deploy” di VoltOS.
A6: Penanggung Jawab | B6: Production Manager (R), Head of QA (A), CTO (C), Asset Manager (I)
A7: Input | B7: Cell baterai, BMS, casing, protokol test, UID range
A8: Langkah Kerja | B8: (1) Verifikasi PO & terima batch (2) Visual + dimensi sampling per AQL (3) Capacity & IR test sample (n=sesuai AQL) (4) Assembly pack sesuai work instruction (5) End-of-line test 100% (charge, discharge, BMS comm, isolation) (6) Generate UID + pairing BMS + registrasi di VoltOS (7) Verifikasi UID unik & data tersinkron (8) Pindahkan ke gudang dengan status “Ready to Deploy”
A9: Output | B9: VoltBattery lulus QC + UID aktif di VoltOS + sertifikat QC
A10: Dokumen Terkait | B10: QC checklist, EOL test sheet, asset registry, work instruction WI-PROD-001
A11: KPI | B11: First-pass yield ≥ 98%; Escape rate ≤ 0.1%; Registrasi sukses first-try ≥ 99%
A12: Risiko & Mitigasi | B12: Lolos cell defective → 100% EOL test + 4-eyes sign-off; Salah UID → validasi otomatis di VoltOS; Data hilang → backup harian
A14: SOP-002 — Rider Battery Swap Transaction
A15: Tujuan | B15: Memastikan setiap rider dapat melakukan swap baterai cepat, aman, dan tercatat di VoltOS.
A16: Ruang Lingkup | B16: Dari rider tap NFC di stasiun sampai baterai kosong mulai recharge.
A17: Penanggung Jawab | B17: Station Operator/VoltOS (R), Head of Operations (A), CS (C/I)
A18: Input | B18: Akun aktif rider, baterai charged di locker, station online
A19: Langkah Kerja | B19: (1) Rider autentikasi (NFC/QR/App) (2) VoltOS validasi saldo & status akun (3) Pilih locker baterai SoC tertinggi (4) Buka locker kosong untuk drop baterai habis (5) Validasi UID baterai yg dimasukkan (sensor berat + UID match) (6) Buka locker baterai full (7) Rider ambil baterai full (8) Catat transaksi & billing di VoltOS (9) Mulai siklus recharge baterai kosong (10) Kirim notifikasi sukses ke app rider
A20: Output | B20: Swap sukses < 2 menit + billing entry + telemetri recharge mulai
A21: Dokumen Terkait | B21: Tariff plan, swap log, BMS profile, runbook station
A22: KPI | B22: Swap success rate ≥ 99%; Avg swap time ≤ 120 detik; Billing dispute rate ≤ 0.2%
A23: Risiko & Mitigasi | B23: Locker stuck → protokol unlock manual + tiket otomatis; SoC < target → station hanya release pack > 90% SoC; Pencurian → UID match + CCTV + denda akun
A25: SOP-003 — Battery Safety & B3 Waste Compliance
A26: Tujuan | B26: Memastikan operasional baterai aman dari thermal incident dan pembuangan baterai end-of-life sesuai regulasi B3 Permen LHK.
A27: Ruang Lingkup | B27: Seluruh swap station, gudang baterai, dan jalur transport baterai EOL ke mitra recycling.
A28: Penanggung Jawab | B28: Head of HSE (R), Compliance Officer (A), COO (C), External Affairs (I)
A29: Input | B29: Regulasi LHK & K3, daftar mitra recycling tersertifikasi, manifest B3
A30: Langkah Kerja | B30: (1) Pemetaan regulasi terbaru (kuartalan) (2) Audit safety swap station & gudang (checklist K3) (3) Drill kebakaran 2x/tahun per site (4) Identifikasi baterai grade X dari VoltOS (5) Segregasi & labelling B3 (6) Terbitkan manifest B3 dgn izin pengangkut tervalidasi (7) Transport oleh pihak tersertifikasi ke mitra recycling (8) Berita acara serah-terima + recovered material report (9) Lapor ke regulator & investor (ESG report)
A31: Output | B31: Manifest valid 100%, bukti recycling, izin aktif, laporan ESG
A32: Dokumen Terkait | B32: Manifest B3 LHK, izin pengangkut, sertifikat mitra recycling, audit checklist K3, ESG report
A33: KPI | B33: Safety incident = 0; Manifest compliance 100%; Audit pass rate 100%; % EOL terdaur ≥ 95%
A34: Risiko & Mitigasi | B34: Pelanggaran B3 → hanya mitra ber-izin, verifikasi triwulan; Kebakaran → thermal sensor, fire suppression, training; Reputasi → transparansi ESG ke publik

Sheet A6_Improvement
A1: 12. IMPROVEMENT RECOMMENDATION
A3: Dimensi | B3: Kondisi Saat Ini (Pilot) | C3: Rekomendasi Perbaikan | D3: Expected Impact | E3: Prioritas
A4: Efisiensi Biaya | B4: Cost per kWh masih tinggi karena volume rendah & dependency 1 supplier [Perlu Validasi] | C4: Dual-source cell, joint purchasing dgn ekosistem EV lokal, leverage skema asset financing untuk CAPEX | D4: Turun 10–15% cost/kWh dalam 12 bulan | E4: Tinggi
A5: Kecepatan Proses | B5: Average swap time masih 90–150 detik [Asumsi]; deployment station 2–3 minggu | C5: Modular kiosk, prefabrikasi off-site, otomatisasi locker assignment via VoltOS | D5: Swap < 90 detik; deploy station < 7 hari | E5: Tinggi
A6: Kualitas Output | B6: Grading masih membutuhkan review manual besar | C6: Latih model grading dengan dataset lab + auto-confidence; baru manual review untuk borderline | D6: Akurasi ≥ 95%, review manual turun 70% | E6: Tinggi
A7: Risiko Operasional | B7: Risiko thermal & B3 masih bergantung audit periodik | C7: Real-time thermal alert (VoltOS) + integrasi GRC tool + drill kebakaran terjadwal | D7: Insiden = 0, audit pass 100% | E7: Wajib
A8: Skalabilitas | B8: Operasi station masih manual / semi-manual; biaya per station tinggi | C8: Self-service station + remote ops center (1 ops menangani 30+ station) | D8: OPEX per station turun 40% | E8: Tinggi
A9: Kesiapan Teknologi | B9: VoltOS masih dalam pengembangan core modules | C9: Prioritaskan modul: digital twin baterai, predictive maintenance, billing, API fleet partner | D9: Time-to-value fleet < 14 hari, fitur core complete H2 | E9: Tinggi
A10: Kebutuhan SDM | B10: Engineer baterai & data scientist scarce | C10: Program magang “Battery Academy” dgn kampus vokasi + retention ESOP | D10: Turnover engineer < 10%; pipeline talenta stabil | E10: Sedang
A11: Customer Experience | B11: Onboarding rider belum self-service penuh | C11: App + KYC digital + tutorial in-station; multibahasa | D11: Aktivasi < 5 menit, retention bulan-1 ≥ 70% | E11: Sedang
A12: Sustainability/ESG | B12: Belum ada disclosure ESG formal | C12: Adopsi GRI/SASB-light; lapor carbon avoided + circular metric | D12: ESG-ready untuk investor seri A/B | E12: Sedang

Sheet Problem
B1: PROBLEM VALIDATION — 6 Root Causes
B3: # | C3: Problem | D3: Quantified Stat | E3: Urgency | F3: Future Risk Projection | G3: Source
B4: 01 | C4: EV Battery Waste Crisis | D4: 39 T IDR residual @ 13M batteries Y2030 | E4: HIGH | F4: 5-yr window before structural waste accumulates | G4: MEMR roadmap; ORF 2024
B5: 02 | C5: Logistics Electrification Bottleneck | D5: 60% logistics use motors; 60–80 km/courier/day | E5: HIGH | F5: Battery = 30–50% TCO; charging downtime kills couriers | G5: ITDP Indonesia Aug 2025
B6: 03 | C6: Off-Grid Island Energy Inequality | D6: 5,200 PLTD; 2.7 BL/yr diesel = Rp 33T | E6: HIGH | F6: Annual Rp 14T diesel cost burns each year of inaction | G6: IEEFA 2024; PLN
B7: 04 | C7: Battery Lifecycle Data Gap | D7: Tropical bat hits 55°C internal (r=0.83 ISR) | E7: MEDIUM | F7: EU Battery Passport mandate live 18 Feb 2027 | G7: ScienceDirect 2026; EU Reg 2023/1542
B8: 05 | C8: Diesel Dependency Rural Indonesia | D8: PLN diesel cost Rp 8,748/kWh vs tariff Rp 1,500 | E8: HIGH | F8: USD 11B annual PLN subsidy | G8: IEEFA 2024
B9: 06 | C9: Lack of Circular Battery Infrastructure | D9: Zero integrated 4-lifecycle player in ASEAN | E9: MEDIUM-HIGH | F9: Window closes once CATL/NIO integrate downstream | G9: Internal benchmark
B13: INFRASTRUCTURE GAP — Indonesia vs Benchmarks
B14: Country | C14: Swap Stations | D14: 2nd Life Infra | E14: Battery Passport | F14: Cumulative Swaps
B15: China (NIO) | C15: 3523 | D15: CATL-Sinopec 500-site | E15: National std | F15: 70000000
B16: Taiwan (Gogoro) | C16: 12500 | D16: Limited | E16: Proprietary | F16: 650000000
B17: India (SUN/Battery Smart) | C17: 900 | D17: Battery Smart 100M+ | E17: EPR 2022 | F17: 100000000
B18: Indonesia (TODAY) | C18: 2182 | D18: ZERO at scale | E18: ZERO | F18: 5000000
B19: VoltLoop Y5 target | C19: 80 | D19: 60 microgrids | E19: VoltLoop OS | F19: 7000000

Sheet Market
B1: MARKET RESEARCH — Indonesia / ASEAN / Global
B3: INDONESIA MACRO INDICATORS
B4: # | C4: Metric | D4: Value | E4: Unit | F4: Year | G4: Source
B5: 1 | C5: Population | D5: 280 | E5: M | F5: 2025 | G5: BPS
B6: 2 | C6: Motorcycles in operation | D6: 130 | E6: M units | F6: 2025 | G6: TYCORUN 2025
B7: 3 | C7: 2024 motorcycle sales | D7: 6.5 | E7: M units | F7: 2024 | G7: MotorcyclesData
B8: 4 | C8: 2W EV market value | D8: 900 | E8: USD M | F8: 2025 | G8: TYCORUN
B9: 5 | C9: EV battery market 2025 | D9: 900 | E9: USD M | F9: 2025 | G9: P&S Intelligence
B10: 6 | C10: EV battery market 2032 | D10: 1990 | E10: USD M | F10: 2032 | G10: P&S Intelligence
B11: 7 | C11: Electrification ratio | D11: 99.83 | E11: % | F11: 2024 | G11: PLN Jan 2025
B12: 8 | C12: PLN PLTD units | D12: 5200 | E12: units | F12: 2024 | G12: PLN/IEEFA
B13: 9 | C13: Annual PLTD diesel consumption | D13: 2.7 | E13: B liters | F13: 2024 | G13: IEEFA 2024
B14: 10 | C14: Last-mile motor share | D14: 60 | E14: % | F14: 2025 | G14: ITDP Aug 2025
B17: ADJACENT MARKETS — Size & CAGR
B18: Market | C18: 2025 Size | D18: 2030/31 Size | E18: CAGR | F18: Source
B19: SEA Battery Swapping (USD B) | C19: 0.94 | D19: 3.85 | E19: 0.3252 | F19: Mordor Intelligence
B20: Global Battery Swap (USD B) | C20: 1.46 | D20: 13 | E20: 0.326 | F20: Coherent Market Insights
B21: Second-life EV battery (USD B) | C21: 1.2 | D21: 4.7 | E21: 0.255 | F21: MarketsandMarkets
B22: Battery-as-a-Service (USD B) | C22: 0.74 | D22: 3.2 | E22: 0.2761 | F22: Mordor Intelligence
B23: Indonesia voluntary carbon (USD M cum) | C23: 4.9 | D23: 0 | E23: 0 | F23: IEEFA Sep 2025
B24: Indonesia 2W EV (USD B) | C24: 0.9 | D24: 4.5 | E24: 0.38 | F24: TYCORUN proj

Sheet TAM SAM SOM
B1: TAM / SAM / SOM — Indonesia & ASEAN
B3: INDONESIA TAM 2030 BUILD-UP (IDR)
B4: # | C4: Stream | D4: Customers | E4: ARPU/mo | F4: Months | G4: TAM 2030 | H4: Method
B5: 1 | C5: Swap Subscription | D5: 800000 | E5: 500000 | F5: 12 | G5: =D5*E5*F5 -> 4800000000000 | H5: B2B couriers x ARPU x 12 (50% adopt)
B6: 2 | C6: Microgrid Subscription | D6: 960000 | E6: 150000 | F6: 12 | G6: =D6*E6*F6 -> 1728000000000 | H6: 6,000 villages x 160 HH x ARPU x 12
B7: 3 | C7: Battery-as-a-Service | D7: 100000 | E7: 600000 | F7: 12 | G7: =D7*E7*F7 -> 720000000000 | H7: OEM B2B leases
B8: 4 | C8: Carbon Credit | D8: 200000 | E8: 7500 | F8: 12 | G8: =D8*E8*F8 -> 18000000000 | H8: tCO2 x USD 15-20
B9: 5 | C9: Data SaaS / Passport | D9: 5000000 | E9: 8000 | F9: 12 | G9: =D9*E9*F9 -> 480000000000 | H9: OEM compliance + ESG SaaS
C10: TOTAL TAM 2030 (Indonesia) | G10: =SUM(G5:G9) -> 7746000000000
B12: SAM / SOM (Indonesia)
B13: Layer | C13: Definition | D13: % of TAM | E13: Value
B14: TAM | C14: Indonesia total accessible 2030 | D14: 1 | E14: =G10 -> 7746000000000
B15: SAM | C15: Reachable infrastructure footprint (35%) | D15: 0.35 | E15: =E14*D15 -> 2711100000000
B16: SOM Y5 | C16: VoltLoop realistic capture (1.1% of SAM) | D16: 0.0107 | E16: =E15*D16 -> 29008770000
B19: ASEAN TAM 2035 (USD 3B = Rp 48T)
B20: Indonesia (existing) | D20: 20000000000000 | E20: 0.417
B21: Philippines (Y3) | D21: 10000000000000 | E21: 0.208
B22: Thailand+Vietnam+Malaysia | D22: 18000000000000 | E22: 0.375
B23: TOTAL ASEAN 2035 | D23: =SUM(D20:D22) -> 48000000000000
A26: TAM RECONCILIATION (G09) — THIS SHEET IS MASTER
A27: This sheet (bottom-up): TAM 2030 = 7.7T IDR. Built from specific revenue streams (customers x ARPU x 12). This is the ADDRESSABLE SERVICES revenue VoltLoop can charge for.
A28: 04_Market_Sizing (top-down): TAM = 50-60T IDR. Based on total motorcycle energy spend (125M units x energy/yr). This is the THEORETICAL CEILING of all 2-wheel energy, most of which VoltLoop never touches.
A29: Reconciliation: The two measure different things. 7.7T (services VoltLoop bills) is a ~13-15% slice of 50-60T (total energy spend incl. electricity/fuel bought directly). Use 7.7T for SAM/SOM/revenue. 04_Market_Sizing is background context only.

Sheet Customers
B1: CUSTOMER SEGMENTS & PERSONAS
B3: # | C3: Persona | D3: Goals | E3: Frustrations | F3: Budget | G3: Decision Process | H3: WTP
B4: 01 | C4: Logistics Co (J&T, SiCepat, JNE, AnterAja) | D4: Lower last-mile OPEX; ESG | E4: Battery cost, charging downtime | F4: Rp 50–500B/yr OPEX | G4: COO + Sustainability, 4–6mo | H4: Rp 500K/motor/mo
B5: 02 | C5: Fleet EV Operators (Electrum, Smoot, Volta) | D5: Battery turnover; network efficiency | E5: Tropical degradation, residual value | F5: Capex-heavy | G5: CEO+CFO direct | H5: Per-cycle swap fee
B6: 03 | C6: PLN Regional Operators | D6: Cut diesel subsidy; electrification | E6: Tariff uniformity, financing gap | F6: State subsidy budget | G6: Wilayah Usaha + PPA tender | H6: USD 0.10-0.18/kWh
B7: 04 | C7: Village Cooperatives (BUMDes) | D7: Affordable reliable electricity | E7: Capital, technician shortage | F7: Rp 50K–500K/HH/mo | G7: Village head + community | H7: Rp 50–150K/HH/mo
B8: 05 | C8: Gov Agencies (MEMR, KLHK, Bappenas) | D8: Hit NDC 2030 targets | E8: Implementation gap | F8: Rp 61 T state budget | G8: Multi-ministry | H8: Co-finance 30–50%
B9: 06 | C9: Battery OEMs (CATL, LG, HLI Green Power) | D9: TKDN compliance; EU circular | E9: No domestic recycling/passport | F9: Capex 1–5% revenue | G9: Strategic partnership | H9: Passport fee + tipping fee
B10: 07 | C10: Climate Finance (ADB, GCF, USAID, ICCTF) | D10: Deploy USD 200M GCF Fund | E10: Bankable pipeline gap | F10: USD 1–50M tickets | G10: 6–18mo DD | H10: SOFR + 100-200bp

Sheet Competitors
B1: COMPETITOR BENCHMARKING
B3: # | C3: Company | D3: 1st Life Swap | E3: 2nd Life | F3: Recovery | G3: Passport | H3: Tropical Data | I3: Indo-native | J3: Valuation/Round | K3: Source Link
B4: 01 | C4: VoltLoop (ours) | D4: B2B | E4: Core | F4: Roadmap | G4: Core | H4: Native | I4: YES | J4: Seeking Series A Rp 15-30M | K4: voltloop.id (internal)
B5: 02 | C5: Gogoro (NASDAQ:GGR) | D5: B2C | E5: No | F5: No | G5: Proprietary | H5: No | I5: Partner only | J5: $2.35B SPAC 2022 | K5: Gogoro IR
B6: 03 | C6: Swap Energy Indonesia | D6: B2C | E6: No | F6: No | G6: No | H6: Limited | I6: YES | J6: $22M @ $76M post-money Jan 2024 | K6: Swap Energy
B7: 04 | C7: Electrum (TBS-GoTo JV) | D7: B2C/ride-hail | E7: No | F7: No | G7: No | H7: Limited | I7: YES | J7: $15M ADB+ACFP+DBS Dec 2024 | K7: Electrum / TBS Energi
B8: 05 | C8: SUN Mobility India | D8: B2B 2W/3W | E8: No | F8: No | G8: No | H8: India tropical | I8: No | J8: $135M cumul, Helios/PIDG 2025 | K8: SUN Mobility
B9: 06 | C9: Connected Energy UK | D9: No | E9: Core | F9: No | G9: In dev | H9: No | I9: No | J9: £15M (Caterpillar/Hinduja/Volvo) | K9: Connected Energy
B10: 07 | C10: Tesla Energy | D10: No | E10: Utility | F10: Yes | G10: Yes | H10: No | I10: No | J10: Public | K10: Tesla Energy
B11: 08 | C11: CATL (Chocolate Battery) | D11: China only | E11: Yes | F11: Yes | G11: Yes | H11: No | I11: Plant only | J11: Public | K11: CATL
B12: 09 | C12: NIO Power Swap | D12: B2C/B2B | E12: Yes | F12: Yes | G12: Yes | H12: No | I12: No | J12: 70M cumul swaps Apr 2025 | K12: NIO Power
B15: PORTER'S FIVE FORCES
B16: Force | C16: Intensity | D16: Rationale | E16: Source | F16: Source Link
B17: New Entry | C17: Medium | D17: Grand View Research
B18: Supplier Power | C18: Med-High | D18: SNE Research (CnEVPost)
B19: Buyer Power | C19: Low | D19: ITDP Indonesia
B20: Substitutes | C20: Medium | D20: MDPI (Open Access)
B21: Rivalry | C21: Medium | D21: ScienceDirect

Sheet Assumptions
A1: VOLTLOOP ASSUMPTIONS & DRIVERS | Series A Financial Model
A3: SCENARIO SELECTOR
A4: Active Scenario | B4: Base | D4: Blue = Input | F4: Green = Cross-sheet link
A5: Toggle index (1=Cons, 2=Base, 3=Aggr) | B5: =IF(B4="Conservative",1,IF(B4="Base",2,3)) -> 2 | D5: Black = Formula | F5: Yellow BG = Active toggle
A7: MACRO ASSUMPTIONS
A8: Variable | B8: Conservative | C8: Base | D8: Aggressive | E8: Active | F8: Unit | G8: Source | H8: Source URL
A9: Indonesia Inflation Rate | B9: 0.03 | C9: 0.035 | D9: 0.04 | E9: =CHOOSE(ScenIdx,B9,C9,D9) -> 0.035 | F9: % YoY | G9: Bank Indonesia 2025 | H9: bi.go.id/inflasi
A10: Discount Rate (WACC) | B10: 0.15 | C10: 0.12 | D10: 0.1 | E10: =CHOOSE(ScenIdx,B10,C10,D10) -> 0.12 | F10: % | G10: Climate-tech bench | H10: climatepolicyinitiative.org
A11: FX IDR per USD | B11: 16500 | C11: 16000 | D11: 15500 | E11: =CHOOSE(ScenIdx,B11,C11,D11) -> 16000 | F11: [Assumption — no official Bank Indonesia rate date. Source: Internal estimate. Re-validate against BI rate before investor use.] | G11: BI mid-rate | H11: bi.go.id/kurs
A12: Capex inflation | B12: 0.04 | C12: 0.03 | D12: 0.02 | E12: =CHOOSE(ScenIdx,B12,C12,D12) -> 0.03 | F12: % YoY | G12: Internal | H12: internal (BI inflation proxy)
A13: Battery cost trajectory ($/kWh) | B13: 110 | C13: 99 | D13: 85 | E13: =CHOOSE(ScenIdx,B13,C13,D13) -> 99 | F13: USD/kWh | G13: BloombergNEF 2025 | H13: about.bnef.com/EVO
A14: Diesel price (PLN PLTD) | B14: 9500 | C14: 8748 | D14: 8000 | E14: =CHOOSE(ScenIdx,B14,C14,D14) -> 8748 | F14: IDR/kWh | G14: IEEFA 2024 | H14: ieefa.org/indonesia
A15: Carbon price IDXCarbon | B15: 50000 | C15: 96000 | D15: 200000 | E15: =CHOOSE(ScenIdx,B15,C15,D15) -> 96000 | F15: IDR/tCO2 | G15: IDXCarbon Jan 2025 | H15: idxcarbon.co.id
A16: Carbon price voluntary | B16: 4 | C16: 12 | D16: 20 | E16: =CHOOSE(ScenIdx,B16,C16,D16) -> 12 | F16: USD/tCO2 | G16: Verra/Gold Standard | H16: verra.org/VCS
A17: Corporate tax rate | B17: 0.22 | C17: 0.22 | D17: 0.22 | E17: =CHOOSE(ScenIdx,B17,C17,D17) -> 0.22 | F17: % | G17: Indonesia | H17: pajak.go.id/corporate-tax
A20: BUSINESS DRIVERS
A21: Variable | B21: Conservative | C21: Base | D21: Aggressive | E21: Active | F21: Unit | G21: Source
A22: EV motorcycle adoption growth %YoY | B22: 0.3 | C22: 0.5 | D22: 0.8 | E22: =CHOOSE(ScenIdx,B22,C22,D22) -> 0.5 | F22: % | G22: MEMR roadmap | H22: esdm.go.id (MEMR)
A23: Courier population growth %YoY | B23: 0.05 | C23: 0.08 | D23: 0.12 | E23: =CHOOSE(ScenIdx,B23,C23,D23) -> 0.08 | F23: % | G23: ITDP 2025 | H23: itdp.org/indonesia
A24: Battery degradation rate (annual) | B24: 0.06 | C24: 0.05 | D24: 0.04 | E24: =CHOOSE(ScenIdx,B24,C24,D24) -> 0.05 | F24: % | G24: ScienceDirect tropical | H24: sciencedirect.com
A25: Hub utilization (steady state) | B25: 0.4 | C25: 0.6 | D25: 0.8 | E25: =CHOOSE(ScenIdx,B25,C25,D25) -> 0.6 | F25: % | G25: Gogoro/SUN bench | H25: gogoro.com/news
A26: Microgrid uptime | B26: 0.95 | C26: 0.98 | D26: 0.995 | E26: =CHOOSE(ScenIdx,B26,C26,D26) -> 0.98 | F26: % | G26: PLN PLTS spec | H26: pln.co.id
A27: Customer churn (monthly) | B27: 0.05 | C27: 0.03 | D27: 0.015 | E27: =CHOOSE(ScenIdx,B27,C27,D27) -> 0.03 | F27: % | G27: B2B SaaS bench | H27: bvp.com/atlas (SaaS bench)
A28: Battery acquisition cost | B28: 4000000 | C28: 3000000 | D28: 2500000 | E28: =CHOOSE(ScenIdx,B28,C28,D28) -> 3000000 | F28: IDR/unit | G28: Electrum/CATL bench | H28: catl.com
A29: Swap subscription price | B29: 450000 | C29: 500000 | D29: 550000 | E29: =CHOOSE(ScenIdx,B29,C29,D29) -> 500000 | F29: IDR/motor/mo | G29: Smoot bench | H29: smoot.id
A30: Microgrid subscription price | B30: 120000 | C30: 150000 | D30: 180000 | E30: =CHOOSE(ScenIdx,B30,C30,D30) -> 150000 | F30: IDR/HH/mo | G30: MENTARI ADB | H30: mentari.info (ADB)
A31: Hub capex | B31: =C31*1.125 -> 9.0029269e+08 | C31: ='Capex Schedule'!C30 -> 8.0026017e+08 | D31: =C31*0.875 -> 7.0022765e+08 | E31: =CHOOSE(ScenIdx,B31,C31,D31) -> 8.0026017e+08 | F31: IDR/hub | G31: Internal eng | H31: Internal engineering estimate
A32: Microgrid capex (160 HH) | B32: =C32*1.25 -> 3.4921896e+08 | C32: ='Capex Schedule'!C40 -> 2.7937516e+08 | D32: =C32*0.786 -> 2.1958888e+08 | E32: =CHOOSE(ScenIdx,B32,C32,D32) -> 2.7937516e+08 | F32: IDR | G32: Internal eng | H32: Internal engineering estimate
A33: Battery passport SaaS ARPU | B33: 60 | C33: 150 | D33: 300 | E33: =CHOOSE(ScenIdx,B33,C33,D33) -> 150 | F33: USD/battery/yr | G33: Comp bench | H33: connected-energy.co.uk
A34: OEM analytics API ARPU | B34: 5000 | C34: 25000 | D34: 50000 | E34: =CHOOSE(ScenIdx,B34,C34,D34) -> 25000 | F34: USD/OEM/yr | G34: Connected Energy | H34: connected-energy.co.uk
A35: Carbon monetization rate | B35: 0.5 | C35: 0.7 | D35: 0.85 | E35: =CHOOSE(ScenIdx,B35,C35,D35) -> 0.7 | F35: % | G35: Verra MRV bench | H35: verra.org/methodologies
A36: Hub deployment rate Y1 | B36: 2 | C36: 2 | D36: 3 | E36: =CHOOSE(ScenIdx,B36,C36,D36) -> 2 | F36: hubs | G36: Internal plan | H36: Internal deployment plan
A37: Microgrid deployment rate Y1 | B37: 1 | C37: 1 | D37: 2 | E37: =CHOOSE(ScenIdx,B37,C37,D37) -> 1 | F37: units | G37: Internal plan | H37: Internal deployment plan
A38: Hub site uplift × (capex / hw-only) | C38: 4.94
A39: MG site uplift × (capex / hw-only) | C39: 5.75
A40: DEPLOYMENT TRAJECTORY (5-Year, Active Scenario)
A41: Metric | B41: Y1 | C41: Y2 | D41: Y3 | E41: Y4 | F41: Y5 | G41: Notes
A42: Active Swap Hubs (EoY) | B42: 2 | C42: 8 | D42: 25 | E42: 50 | F42: 80 | G42: Cumulative
A43: Active Microgrids (EoY) | B43: 1 | C43: 4 | D43: 18 | E43: 38 | F43: 60 | G43: Cumulative
A44: Avg couriers per hub | B44: 25 | C44: 35 | D44: 45 | E44: 50 | F44: 55 | G44: Ramp
A45: Avg homes per microgrid | B45: 160 | C45: 160 | D45: 165 | E45: 170 | F45: 175 | G45: Density
A46: Total batteries deployed | B46: 50 | C46: 250 | D46: 900 | E46: 2200 | F46: 4000 | G46: All assets
A47: OEM analytics customers | B47: 0 | C47: 1 | D47: 3 | E47: 6 | F47: 10 | G47: API tier 2-3

Sheet Assumptions (2)
A1: GLOBAL ASSUMPTIONS — ALL BLUE CELLS ARE EDITABLE INPUTS
A3: Parameter | B3: Value | C3: Unit | D3: Confidence | E3: Source / Note
A4: A. Currency & FX
A5: FX USD/IDR | B5: =Assumptions!E11 -> 16000 | C5: IDR/USD | D5: [Estimated] | E5: Mid-2026 planning rate; add buffer in import logistics %
A6: FX CNY/IDR | B6: 2250 | C6: IDR/CNY | D6: [Estimated] | E6: Planning rate
A7: B. Labor & Machine Rates (Bandung/Cirebon, loaded)
A8: Assembly labor rate | B8: 45000 | C8: IDR/hr | D8: [Assumption] | E8: UMK + overhead + supervision, loaded
A9: Technician / test / QC rate | B9: 90000 | C9: IDR/hr | D9: [Assumption] | E9: Skilled EE technician, loaded
A10: CNC machining rate | B10: 350000 | C10: IDR/hr | D10: [Estimated] | E10: Local job-shop 3-axis incl. operator
A11: Laser cutting rate | B11: 250000 | C11: IDR/hr | D11: [Estimated] | E11: Fiber laser job-shop
A12: Press brake bending rate | B12: 200000 | C12: IDR/hr | D12: [Estimated] | E12: Job-shop
A13: Welding rate (MIG/TIG incl. welder) | B13: 150000 | C13: IDR/hr | D13: [Estimated] | E13: Job-shop
A14: Fab shop labor (deburr/fit) | B14: 60000 | C14: IDR/hr | D14: [Assumption]
A15: Powder coating rate | B15: 75000 | C15: IDR/m2 | D15: [Estimated] | E15: Industrial powder coat, RAL std
A16: C. Raw Material Prices
A17: Steel sheet SPCC/SS400 | B17: 19000 | C17: IDR/kg | D17: [Estimated] | E17: Local distributor 2026
A18: Stainless steel 304 sheet | B18: 95000 | C18: IDR/kg | D18: [Estimated]
A19: Aluminum 5052/6061 | B19: 65000 | C19: IDR/kg | D19: [Estimated]
A20: Copper C1100 bar | B20: 145000 | C20: IDR/kg | D20: [Estimated] | E20: LME + local premium
A21: PA66-GF30 slab (machining) | B21: 180000 | C21: IDR/kg | D21: [Estimated] | E21: Engineering plastic stock
A22: PA66-GF30 pellets (molding) | B22: 62000 | C22: IDR/kg | D22: [Estimated] | E22: Resin distributor
A23: Nickel strip (cell interconnect) | B23: 550000 | C23: IDR/kg | D23: [Estimated] | E23: Pure Ni 0.15-0.2mm
A24: D. Logistics, Scrap, Contingency
A25: Import landed adder (ship+duty+PPN buffer) | B25: 0.18 | C25: of price | D25: [Assumption] | E25: Applied to overseas-sourced parts
A26: Local purchase landed adder | B26: 0.05 | C26: of price | D26: [Assumption] | E26: Domestic freight/handling
A27: Scrap % — fabricated material | B27: 0.08 | D27: [Assumption] | E27: Inside Fabrication sheet models
A28: Scrap/attrition % — electronics | B28: 0.02 | D28: [Assumption]
A29: Scrap % — mechanical purchased | B29: 0.03 | D29: [Assumption]
A30: Contingency — Prototype | B30: 0.15 | D30: [Assumption] | E30: TRL 3 design churn
A31: Contingency — Pilot | B31: 0.12 | D31: [Assumption]
A32: Contingency — Low-volume | B32: 0.1 | D32: [Assumption]
A33: Contingency — Mass | B33: 0.08 | D33: [Assumption]
A34: E. Volumes & Scenario Factors
A35: Prototype quantity | B35: 3 | C35: units/product | D35: [Assumption]
A36: Pilot quantity (tooling amortization base) | B36: 25 | C36: units | D36: [Assumption]
A37: Low-volume quantity | B37: 250 | C37: units | D37: [Assumption]
A38: Mass quantity (hard tooling amortization base) | B38: 5000 | C38: units | D38: [Assumption]
A39: Scenario factor — Low | B39: 0.82 | C39: x Base | D39: [Assumption] | E39: Cheapest supplier / simplified process
A40: Scenario factor — High | B40: 1.3 | C40: x Base | D40: [Assumption] | E40: Local supplier, small MOQ, conservative
A41: F. Tooling / NRE (one-off, not in unit price unless amortized)
A42: SBP soft tooling set (top/bottom/holder/handle molds) | B42: 220000000 | C42: IDR | D42: [Assumption] | E42: Aluminum molds, pilot path
A43: SBP hard tooling set (production molds + gasket die) | B43: 750000000 | C43: IDR | D43: [Assumption] | E43: P20/H13 steel molds
A44: VoltSwap connector-dock mold + jigs | B44: 90000000 | C44: IDR | D44: [Assumption]
A45: VoltSwap sheet-metal jigs/fixtures | B45: 30000000 | C45: IDR | D45: [Assumption]
A46: VoltGrid sheet-metal jigs/fixtures | B46: 35000000 | C46: IDR | D46: [Assumption]
A47: VoltOS software NRE (cloud+edge dev) — reference only | B47: 1500000000 | C47: IDR | D47: [TBD] | E47: NOT in hardware unit cost; size via dev plan
A48: G. Smart Battery Pack Architecture (HOLD FOR VALIDATION)
A49: Nominal voltage (13s NMC) | B49: 48 | C49: V | D49: [Assumption] | E49: Scooter swap class; LFP 16s alternative open
A50: Capacity | B50: 30 | C50: Ah | D50: [Assumption]
A51: Cell: NMC 21700 5Ah — series | B51: 13 | C51: s | D51: [Assumption]
A52: Cell: parallel | B52: 6 | C52: p | D52: [Assumption]
A53: Cell count (s x p) | B53: ='Assumptions (2)'!$B$51*'Assumptions (2)'!$B$52 -> 78 | C53: cells | D53: Formula
A54: Pack energy | B54: ='Assumptions (2)'!$B$49*'Assumptions (2)'!$B$50/1000 -> 1.44 | C54: kWh | D54: Formula

Sheet Master Input Data
A1: No | B1: Produk/Kategori | C1: Variabel Input | D1: Nilai Kerja | E1: Satuan | F1: Rumus/Konversi | G1: Status | H1: Source + Link Verifikasi Manual | I1: Catatan Pemakaian
A2: 1 | B2: Makro | C2: Kurs USD/IDR | D2: 18039 | E2: Rp/USD | F2: BI JISDOR 5 Juni 2026 | G2: Source-based | H2: Bank Indonesia JISDOR | I2: Pakai untuk semua konversi USD ke rupiah
A3: 2 | B3: Pajak | C3: PPN umum efektif | D3: 0.11 | E3: % | F3: 12% × 11/12 DPP | G3: Source-based | H3: DJP/Pajak.go.id | I3: Untuk barang/jasa non-mewah
A4: 3 | B4: Pajak | C4: Tarif PPN formal | D4: 0.12 | E4: % | F4: Tarif umum formal | G4: Source-based | H4: DJP/Pajak.go.id | I4: Hati-hati: tidak selalu efektif 12% untuk barang non-mewah
A5: 4 | B5: Listrik | C5: Tarif listrik bisnis B-2 | D5: 1444.7 | E5: Rp/kWh | F5: Tarif benchmark B-2 | G5: Market benchmark | H5: SUN Energy tarif listrik 2026 | I5: Cocok untuk charging station skala kecil-menengah
A6: 5 | B6: Listrik | C6: Tarif listrik industri I-3 | D6: 1114.74 | E6: Rp/kWh | F6: Tarif benchmark I-3 | G6: Market benchmark | H6: SUN Energy tarif listrik 2026 | I6: Cocok untuk workshop/charging skala industri
A7: 6 | B7: Tenaga Kerja | C7: UMP DKI Jakarta 2026 | D7: 5729876 | E7: Rp/bulan | F7: Minimum wage | G7: Source-based | H7: JDIH DKI Jakarta | I7: Benchmark gaji minimum Jakarta
A8: 7 | B8: Tenaga Kerja | C8: UMK Kota Bandung 2026 | D8: 4737678 | E8: Rp/bulan | F8: Minimum wage | G8: Source-based | H8: Pemprov Jabar/Kota Bandung | I8: Benchmark operator/teknisi Bandung
A9: 8 | B9: Tenaga Kerja | C9: UMK Kota Bekasi 2026 | D9: 5999443 | E9: Rp/bulan | F9: Minimum wage | G9: Source-based | H9: Pemprov Jabar | I9: Benchmark area manufaktur besar
A10: 9 | B10: Tenaga Kerja | C10: UMK Kabupaten Bekasi 2026 | D10: 5938885 | E10: Rp/bulan | F10: Minimum wage | G10: Source-based | H10: Pemprov Jabar/Jakarta Globe | I10: Alternatif lokasi manufaktur/logistik
A11: 10 | B11: VoltBattery | C11: Kapasitas battery pack | D11: 1.44 | E11: kWh/pack | F11: 72V × 20Ah / 1000 | G11: Assumption | H11: Internal desain VOLTLOOP | I11: Harus konsisten dengan spesifikasi teknis proposal
A12: 11 | B12: VoltBattery | C12: Global Li-ion pack average 2025 | D12: 108 | E12: USD/kWh | F12: — | G12: Source-based | H12: BloombergNEF | I12: Benchmark umum pack lithium-ion
A13: 12 | B13: VoltBattery | C13: LFP pack average 2025 | D13: 81 | E13: USD/kWh | F13: — | G13: Source-based | H13: BloombergNEF | I13: Cocok karena desain awal VOLTLOOP mengarah ke LFP
... A15: 14 | B15: VoltBattery | C15: Two-/three-wheeler pack estimate | D15: 133 | E15: USD/kWh | F15: — | G15: Unverified | H15: Perlu full BNEF report / sumber lain | I15: Jangan dipakai sebagai source-based sebelum ketemu dokumen publik
A16: 15 | B16: VoltBattery | C16: Core pack cost berdasar global average | D16: =D12*D11*$D$2 -> 2805425.3 | E16: Rp/pack | F16: 108 × 1,44 × 18.039 | G16: Calculated | H16: BloombergNEF + BI | I16: Belum termasuk casing, BMS, QC, margin, warranty
A17: 16 | B17: VoltBattery | C17: Core LFP pack cost | D17: =D13*D11*$D$2 -> 2104069 | E17: Rp/pack | F17: 81 × 1,44 × 18.039 | G17: Calculated | H17: BloombergNEF + BI | I17: Angka target optimistis, bukan harga siap pakai
A18: 17 | B18: VoltBattery | C18: Core China pack cost | D18: =D14*D11*$D$2 -> 2181997.4 | E18: Rp/pack | F18: 84 × 1,44 × 18.039 | G18: Calculated | H18: BloombergNEF + BI | I18: Cocok untuk benchmark impor/China supply
A19: 18 | B19: VoltBattery | C19: Swappable lithium battery pack umum | D19: 240–680 | E19: USD/pack | F19: — | G19: Market benchmark | H19: HelloPower | I19: Range untuk 48–72V pack
A20: 19 | B20: VoltBattery | C20: Swappable pack umum dalam rupiah | D20: 4.329.360–12.266.520 | E20: Rp/pack | F20: 240–680 × 18.039 | G20: Calculated | H20: HelloPower + BI | I20: Pakai sebagai range procurement
A21: 20 | B21: VoltBattery | C21: Swappable high-performance pack | D21: 440–680 | E21: USD/pack | F21: — | G21: Market benchmark | H21: HelloPower | I21: Lebih relevan untuk 60–72V e-motorcycle
A22: 21 | B22: VoltBattery | C22: High-performance pack dalam rupiah | D22: 7.937.160–12.266.520 | E22: Rp/pack | F22: 440–680 × 18.039 | G22: Calculated | H22: HelloPower + BI | I22: Cocok untuk pilot procurement conservative
A23: 22 | B23: VoltBattery | C23: Battery cycle life benchmark | D23: 800–1.200 | E23: full cycles | F23: — | G23: Market benchmark | H23: HelloPower | I23: Untuk replacement schedule
A24: 23 | B24: VoltBattery | C24: SoH setelah cycle benchmark | D24: ±80% | E24: capacity remaining | F24: Setelah 800–1.200 cycles | G24: Market benchmark | H24: HelloPower | I24: Perlu uji AXION sendiri
A25: 24 | B25: VoltBattery | C25: Warranty provision | D25: 3–5% | E25: % COGS | F25: COGS × 3–5% | G25: Assumption | H25: Supplier quotation needed | I25: Perlu data warranty vendor/pilot
A26: 25 | B26: VoltBattery | C26: Reject/scrap rate awal | D26: 3–8% | E26: % produksi | F26: Output reject / total output | G26: Assumption | H26: Pilot-required | I26: Harus dari trial assembly
A27: 26 | B27: VoltBattery | C27: Target COGS pilot conservative | D27: 7,9–12,3 juta | E27: Rp/pack | F27: dari high-performance pack range | G27: Market benchmark | H27: HelloPower + BI | I27: Aman untuk pilot karena berbasis procurement
A28: 27 | B28: VoltBattery | C28: Target COGS scale-up assembly | D28: 5,5–7,5 juta | E28: Rp/pack | F28: Estimasi assembly lokal | G28: Assumption | H28: Supplier quotation needed | I28: Harus divalidasi dengan BOM vendor
A29: 28 | B29: VoltSwap | C29: Smart swap cabinet 10-slot | D29: 1.400–2.000 | E29: USD/unit | F29: — | G29: Market benchmark | H29: HelloPower | I29: Cabinet saja, belum seluruh station
A30: 29 | B30: VoltSwap | C30: Smart swap cabinet 10-slot rupiah | D30: 25.254.600–36.078.000 | E30: Rp/unit | F30: 1.400–2.000 × 18.039 | G30: Calculated | H30: HelloPower + BI | I30: Untuk CAPEX cabinet
A31: 30 | B31: VoltSwap | C31: Jumlah slot per cabinet | D31: 10 | E31: slot/cabinet | F31: — | G31: Market benchmark | H31: HelloPower | I31: Base design awal station
A32: 31 | B32: VoltSwap | C32: Battery pool per 10-slot cabinet | D32: 20–30 | E32: pack/station | F32: — | G32: Market benchmark | H32: HelloPower | I32: Battery pool harus > slot
A33: 32 | B33: VoltSwap | C33: Entry pilot station budget | D33: 10.000–20.000 | E33: USD/station | F33: 1 cabinet + 20 batteries | G33: Market benchmark | H33: HelloPower | I33: Exclude kendaraan & civil works lokal
A34: 33 | B34: VoltSwap | C34: Entry pilot station budget rupiah | D34: 180.390.000–360.780.000 | E34: Rp/station | F34: 10.000–20.000 × 18.039 | G34: Calculated | H34: HelloPower + BI | I34: Input CAPEX pilot
A35: 34 | B35: VoltSwap | C35: City node station budget | D35: 15.000–30.000 | E35: USD/station | F35: 1 cabinet + 25–30 batteries | G35: Market benchmark | H35: HelloPower | I35: Untuk deployment lebih serius
A36: 35 | B36: VoltSwap | C36: City node station budget rupiah | D36: 270.585.000–541.170.000 | E36: Rp/station | F36: 15.000–30.000 × 18.039 | G36: Calculated | H36: HelloPower + BI | I36: Cocok skenario base case
A37: 36 | B37: VoltSwap | C37: Small two-cabinet hub budget | D37: 30.000–60.000 | E37: USD/hub | F37: 2 cabinet + 40–60 batteries | G37: Market benchmark | H37: HelloPower | I37: Untuk corridor/logistics hub
A38: 37 | B38: VoltSwap | C38: Small hub budget rupiah | D38: 541.170.000–1.082.340.000 | E38: Rp/hub | F38: 30.000–60.000 × 18.039 | G38: Calculated | H38: HelloPower + BI | I38: CAPEX skala tinggi
A39: 38 | B39: VoltSwap | C39: Local civil works & installation | D39: 10–25% | E39: % hardware cost | F39: Hardware × 10–25% | G39: Supplier quotation needed | H39: RFQ kontraktor listrik/site | I39: Tidak valid kalau cuma pakai internet
A40: 39 | B40: VoltSwap | C40: Charging efficiency | D40: 0.9 | E40: % | F40: energy output / grid input | G40: Assumption | H40: Pilot-required | I40: Perlu uji charger aktual
A41: 40 | B41: VoltSwap | C41: Grid energy per full charge | D41: =D11/D40 -> 1.6 | E41: kWh/charge | F41: 1,44 / 90% | G41: Calculated | H41: Internal formula | I41: Gunakan untuk electricity cost per swap
A42: 41 | B42: VoltSwap | C42: Electricity cost per full charge B-2 | D42: =D41*D5 -> 2311.52 | E42: Rp/charge | F42: 1,6 × 1.444,70 | G42: Calculated | H42: SUN Energy tarif listrik | I42: Belum termasuk idle load/cooling
A43: 42 | B43: VoltSwap | C43: Established station daily swaps | D43: 30–60 | E43: swaps/day | F43: Vendor operating benchmark | G43: Market benchmark | H43: HelloPower | I43: Jangan klaim untuk AXION sebelum pilot
A44: 43 | B44: VoltSwap | C44: Payback station benchmark | D44: 18–30 | E44: bulan | F44: Vendor operating benchmark | G44: Market benchmark | H44: HelloPower | I44: Hanya benchmark vendor, bukan bukti AXION
A45: 44 | B45: VoltSwap | C45: Maintenance station | D45: 2–5% | E45: % CAPEX/year | F45: CAPEX × 2–5% | G45: Assumption | H45: Pilot/RFQ O&M needed | I45: Perlu data vendor dan kondisi lokasi
A46: 45 | B46: VoltSwap | C46: Site rent station | D46: Placeholder | E46: Rp/bulan | F46: — | G46: Supplier quotation needed | H46: Survei lokasi/LOI partner | I46: Wajib cari per lokasi: Alfamart/SPBU/kampus/gudang
A47: 46 | B47: VoltOS | C47: EC2 t3.medium benchmark | D47: 0.0416 | E47: USD/hour | F47: — | G47: Market benchmark | H47: Vantage AWS pricing | I47: Untuk server app/dashboard awal
A48: 47 | B48: VoltOS | C48: EC2 t3.medium monthly | D48: =D47*24*30*$D$2 -> 540304.13 | E48: Rp/month | F48: 0,0416 × 24 × 30 × 18.039 | G48: Calculated | H48: Vantage + BI | I48: Belum termasuk storage, bandwidth, backup
A49: 48 | B49: VoltOS | C49: RDS db.t3.micro benchmark | D49: 0.018 | E49: USD/hour | F49: — | G49: Market benchmark | H49: Vantage RDS pricing | I49: Untuk database kecil/pilot
A50: 49 | B50: VoltOS | C50: RDS db.t3.micro monthly | D50: =D49*24*30*$D$2 -> 233785.44 | E50: Rp/month | F50: 0,018 × 24 × 30 × 18.039 | G50: Calculated | H50: Vantage + BI | I50: Belum termasuk storage dan I/O
A51: 50 | B51: VoltOS | C51: IoT SIM Telkomsel testing bundle | D51: 4 SIM, 50MB/SIM/month, 3 bulan | E51: paket | F51: — | G51: Source-based | H51: Telkomsel M2M portal | I51: Bagus untuk pilot testing konektivitas
A52: 51 | B52: VoltOS | C52: IoT/M2M SIM retail benchmark | D52: 300000 | E52: Rp/SIM/6 bulan | F52: Rp50.000/bulan | G52: Market benchmark | H52: TrackSolid.id | I52: Benchmark retail, bukan enterprise quotation
A53: 52 | B53: VoltOS | C53: IoT SIM monthly input | D53: 30.000–75.000 | E53: Rp/SIM/month | F53: Range dari retail + buffer | G53: Assumption | H53: Enterprise quotation needed | I53: Harus minta harga Telkomsel/Indosat/XL enterprise
A54: 53 | B54: VoltOS | C54: Initial software development | D54: 150–500 juta | E54: Rp/project | F54: Estimasi build dashboard, API, analytics | G54: Assumption | H54: Vendor software quotation needed | I54: Perlu quotation dev house / estimasi internal team
A55: 54 | B55: VoltOS | C55: Cloud OPEX pilot | D55: 2–10 juta | E55: Rp/month | F55: Server + DB + monitoring + storage | G55: Assumption | H55: AWS calculator/manual architecture | I55: Hitung ulang setelah arsitektur VoltOS fix
A56: 55 | B56: VoltOS | C56: Software maintenance | D56: 10–25% | E56: % dev cost/year | F56: Dev cost × 10–25% | G56: Assumption | H56: Vendor software quotation needed | I56: Untuk bugfix, security, support
A57: 56 | B57: VoltOS | C57: SaaS revenue per station | D57: 150.000–500.000 | E57: Rp/station/month | F57: — | G57: Pilot-required | H57: WTP survey/B2B interview | I57: Tidak bisa valid hanya dari internet
A58: 57 | B58: VoltOS | C58: SaaS revenue per battery | D58: 10.000–30.000 | E58: Rp/battery/month | F58: — | G58: Pilot-required | H58: WTP survey/B2B interview | I58: Perlu validasi calon operator/fleet
A59: 58 | B59: VoltGrid | C59: Stationary storage pack 2025 | D59: 70 | E59: USD/kWh | F59: — | G59: Source-based | H59: BloombergNEF | I59: Benchmark pack stationary storage
A60: 59 | B60: VoltGrid | C60: Stationary storage pack rupiah | D60: =D59*$D$2 -> 1262730 | E60: Rp/kWh | F60: 70 × 18.039 | G60: Calculated | H60: BloombergNEF + BI | I60: Belum termasuk PCS, EMS, enclosure
A61: 60 | B61: VoltGrid | C61: Commercial BESS LIB 4-hour | D61: 199 | E61: USD/kWh | F61: — | G61: Source-based | H61: NREL/NLR ATB | I61: Benchmark BESS komersial
A62: 61 | B62: VoltGrid | C62: Commercial BESS LIB 4-hour rupiah | D62: =D61*$D$2 -> 3589761 | E62: Rp/kWh | F62: 199 × 18.039 | G62: Calculated | H62: NREL/NLR ATB + BI | I62: Lebih realistis untuk sistem installed awal
A63: 62 | B63: VoltGrid | C63: Battery central inverter price | D63: 97.5 | E63: USD/kW | F63: — | G63: Source-based | H63: NREL/NLR ATB | I63: Input PCS/inverter
A64: 63 | B64: VoltGrid | C64: Inverter price rupiah | D64: =D63*$D$2 -> 1758802.5 | E64: Rp/kW | F64: 97,5 × 18.039 | G64: Calculated | H64: NREL/NLR ATB + BI | I64: Untuk sizing kW VoltGrid
A65: 64 | B65: VoltGrid | C65: Round-trip efficiency BESS | D65: 0.85 | E65: % | F65: — | G65: Source-based | H65: NREL/NLR ATB technical data | I65: Untuk energy loss model
A66: 65 | B66: VoltGrid | C66: Fixed O&M BESS | D66: 0.025 | E66: % CAPEX/year | F66: CAPEX × 2,5% | G66: Source-based benchmark | H66: NREL/NLR ATB | I66: Bisa pakai untuk VoltGrid, bukan VoltSwap
A67: 66 | B67: VoltGrid | C67: Second-life remaining capacity | D67: 70–80% | E67: % original capacity | F67: — | G67: Source-based benchmark | H67: Second-life battery review (arXiv) | I67: Untuk grading second-life
A68: 67 | B68: VoltGrid | C68: Second-life module acquisition | D68: 0,5–1,5 juta | E68: Rp/kWh | F68: — | G68: Supplier quotation needed | H68: RFQ supplier battery bekas/recycler | I68: Tidak cukup dari internet
A69: 68 | B69: VoltGrid | C69: Repackaging + testing | D69: 0,3–1,5 juta | E69: Rp/kWh | F69: — | G69: Supplier quotation needed | H69: RFQ lab/pack integrator | I69: Harus ada biaya testing safety
A70: 69 | B70: VoltGrid | C70: EMS + protection + enclosure | D70: 20–40% | E70: % battery+PCS | F70: — | G70: Assumption | H70: Supplier quotation needed | I70: Harus divalidasi vendor ESS
A71: 70 | B71: VoltGrid | C71: Installed ESS cost target | D71: 3–7 juta | E71: Rp/kWh installed | F71: BESS benchmark + assembly inference | G71: Inference | H71: BNEF/NREL + RFQ needed | I71: Pakai sebagai range awal, bukan angka final
A72: 71 | B72: Revenue | C72: VoltBattery B2B selling price | D72: 9–15 juta | E72: Rp/pack | F72: COGS + margin | G72: Assumption | H72: Market/WTP validation needed | I72: Harus dibandingkan harga motor/battery market
A73: 72 | B73: Revenue | C73: Battery leasing | D73: 250.000–500.000 | E73: Rp/pack/month | F73: — | G73: Pilot-required | H73: WTP survey/fleet interview | I73: Perlu survei pelanggan
A74: 73 | B74: Revenue | C74: Swap subscription | D74: Placeholder | E74: Rp/user/month | F74: — | G74: Pilot-required | H74: Survey + competitor benchmarking | I74: Belum ada angka source publik kuat yang terverifikasi
A75: 74 | B75: Revenue | C75: Pay-per-swap fee | D75: Placeholder | E75: Rp/swap | F75: — | G75: Pilot-required | H75: Pilot + WTP survey | I75: Harus berdasarkan daya jelajah, biaya bensin, dan tarif kompetitor
A76: 75 | B76: Revenue | C76: VoltGrid maintenance contract | D76: 2–5% | E76: % CAPEX/year | F76: CAPEX × 2–5% | G76: Assumption | H76: RFQ O&M / contract benchmark | I76: Bisa jadi revenue recurring
A77: 76 | B77: Revenue | C77: VoltGrid installed system selling price | D77: 3–7 juta | E77: Rp/kWh installed | F77: Cost + margin | G77: Inference | H77: BNEF/NREL + supplier quote needed | I77: Harus dibandingkan vendor ESS lokal
A78: 77 | B78: Produksi | C78: Utilization rate produksi | D78: 60–85% | E78: % | F78: Actual output / capacity | G78: Assumption | H78: Pilot-required | I78: Harus dari trial production
... A86: 85 | B86: Operasional | C86: Insurance/safety cost | D86: Placeholder | E86: Rp/year | F86: — | G86: Supplier quotation needed | H86: Insurance quotation | I86: Penting jika ada asset pool besar

Sheet Master Component
A1: No | B1: Produk | C1: Subsystem | D1: Assembly / Modul | E1: Komponen Lebih Kecil | F1: Komponen Terkecil / Item Sourcing | G1: Fungsi | H1: Status Validitas | I1: Qty per Unit | J1: Unit Price (USD) | K1: Total Cost (USD) | L1: Supplier | M1: Source Link | N1: Validation Status
A2: 1 | B2: VoltBattery | C2: Battery core | D2: Cell module | E2: LFP cell | F2: Cell LFP cylindrical/prismatic/pouch, cell holder, cell spacer | G2: Menyimpan energi utama | H2: Document-based + [Perlu Validasi vendor] | I2: 24 cells | J2: 3.38 | K2: =LEFT(I2,FIND(" ",I2)-1)*J2 -> 81.12 | L2: CATL / EVE Energy / BYD | M2: Alibaba LFP cells | N2: Market benchmark
A3: 2 | B3: VoltBattery | C3: Battery core | D3: Cell module | E3: Cell grouping | F3: Konfigurasi seri-paralel, busbar cell, nickel strip/copper strip | G3: Membentuk tegangan dan kapasitas pack | H3: [Inference] | I3: 1 set | J3: 0 | K3: 0 | L3: Internal assembly | M3: — | N3: Internal labor
A4: 3 | B4: VoltBattery | C4: Battery core | D4: Cell interconnection | E4: Busbar system | F4: Copper busbar, nickel strip, weld point, insulating washer | G4: Mengalirkan arus antar-cell | H4: [Inference] | I4: 1 set | J4: 2.5 | K4: 2.5 | L4: China busbar supplier | M4: Alibaba busbar | N4: Market benchmark
A5: 4 | B5: VoltBattery | C5: Battery core | D5: Welding system | E5: Cell welding interface | F5: Spot weld/nickel strip, laser weld point, weld tab | G5: Koneksi elektrik antar-cell | H5: [Perlu Validasi] | I5: 1 set | J5: 0 | K5: 0 | L5: Internal assembly | M5: — | N5: Internal labor
A6: 5 | B6: VoltBattery | C6: Battery core | D6: Insulation layer | E6: Electrical insulation | F6: Fish paper, mica sheet, Kapton tape, PVC sleeve, separator pad | G6: Mencegah short circuit internal | H6: [Inference] | I6: 1 set | J6: 1.5 | K6: 1.5 | L6: 3M / generic | M6: Alibaba insulation | N6: Market benchmark
A7: 6 | B7: VoltBattery | C7: Battery core | D7: Thermal layer | E7: Thermal management | F7: Thermal pad, gap filler, heat spreader, thermal foam | G7: Mengurangi hotspot | H7: [Inference] | I7: 1 set | J7: 3 | K7: 3 | L7: Henkel / generic | M7: Alibaba thermal pad | N7: Market benchmark
A8: 7 | B8: VoltBattery | C8: Battery electronics | D8: Smart BMS | E8: BMS PCB | F8: PCB board, MCU, analog front end, ADC, EEPROM/flash | G8: Otak proteksi dan monitoring baterai | H8: Document-based | I8: 1 pcs | J8: 18 | K8: 18 | L8: JBD / Daly / JK BMS | M8: Alibaba 72V BMS | N8: Market benchmark
A9: 8 | B9: VoltBattery | C9: Battery electronics | D9: Smart BMS | E9: Voltage sensing | F9: Voltage sense wire, balance wire, connector harness | G9: Membaca tegangan tiap cell group | H9: Document-based + [Inference] | I9: 1 set | J9: 1.5 | K9: 1.5 | L9: Generic harness | M9: Alibaba wire harness | N9: [Inference]
A10: 9 | B10: VoltBattery | C10: Battery electronics | D10: Smart BMS | E10: Current sensing | F10: Shunt resistor / Hall-effect current sensor | G10: Membaca arus charge/discharge | H10: [Inference] | I10: 1 pcs | J10: 2 | K10: 2 | L10: Allegro / Melexis / generic | M10: Alibaba Hall sensor | N10: [Inference]
A11: 10 | B11: VoltBattery | C11: Battery electronics | D11: Smart BMS | E11: Temperature sensing | F11: NTC thermistor, temp probe, sensor wire | G11: Membaca suhu cell/pack | H11: Document-based | I11: 3 pcs | J11: 0.3 | K11: =LEFT(I11,FIND(" ",I11)-1)*J11 -> 0.9 | L11: Generic NTC | M11: LCSC NTC thermistor | N11: Market benchmark
A12: 11 | B12: VoltBattery | C12: Battery electronics | D12: Smart BMS | E12: Balancing circuit | F12: Passive balance resistor, MOSFET, balance IC | G12: Menyeimbangkan cell | H12: Document-based + [Inference] | I12: 1 set | J12: 0 | K12: 0 | L12: Included in BMS | M12: — | N12: Included in BMS
A13: 12 | B13: VoltBattery | C13: Battery electronics | D13: Protection circuit | E13: Overcurrent/short protection | F13: Fuse, breaker, MOSFET/contactor, pre-charge resistor | G13: Memutus arus saat fault | H13: Document-based + [Inference] | I13: 1 set | J13: 3 | K13: 3 | L13: Littelfuse / TE / generic | M13: Alibaba fuse/MOSFET | N13: Market benchmark
A14: 13 | B14: VoltBattery | C14: Battery electronics | D14: Communication | E14: CAN/RS485 module | F14: CAN transceiver, RS485 transceiver, terminal connector | G14: Komunikasi ke motor/station/gateway | H14: Document-based | I14: 1 pcs | J14: 2 | K14: 2 | L14: MCP / Kvaser / generic | M14: Alibaba CAN module | N14: Market benchmark
A15: 14 | B15: VoltBattery | C15: Battery electronics | D15: Battery ID | E15: Identity module | F15: QR code, RFID/NFC tag, unique serial number, secure ID chip | G15: Tracking aset baterai | H15: Document-based | I15: 1 set | J15: 1.5 | K15: 1.5 | L15: NFC tag + QR label | M15: Alibaba RFID/NFC | N15: Market benchmark
A16: 15 | B16: VoltBattery | C16: Battery interface | D16: Power connector | E16: High-current connector | F16: Male/female DC connector, copper pin, anti-spark terminal | G16: Koneksi daya ke motor/station | H16: Document-based | I16: 1 pcs | J16: 5 | K16: 5 | L16: Anderson / Amphenol | M16: Alibaba DC connector | N16: Market benchmark
A17: 16 | B17: VoltBattery | C17: Battery interface | D17: Charging connector | E17: Charge port | F17: DC charge connector, locking pin, dust cap | G17: Interface charging | H17: [Inference] | I17: 1 pcs | J17: 3 | K17: 3 | L17: XT60 / custom | M17: Alibaba charge port | N17: [Inference]
A18: 17 | B18: VoltBattery | C18: Battery interface | D18: Signal connector | E18: Low-voltage connector | F18: CAN/RS485 pin, signal pin, waterproof plug | G18: Data dan kontrol | H18: [Inference] | I18: 1 set | J18: 1.5 | K18: 1.5 | L18: Molex / JST / generic | M18: Alibaba signal conn | N18: [Inference]
A19: 18 | B19: VoltBattery | C19: Mechanical pack | D19: Outer enclosure | E19: Casing battery | F19: ABS/PC/metal casing, lid, base shell | G19: Proteksi mekanik baterai | H19: Document-based | I19: 1 set | J19: 12 | K19: 12 | L19: Custom mold / injection | M19: Alibaba ABS casing | N19: Market benchmark
A20: 19 | B20: VoltBattery | C20: Mechanical pack | D20: Sealing system | E20: Waterproofing | F20: Rubber gasket, silicone sealant, O-ring, vent plug | G20: Target IP65 / tahan air-debu | H20: Document-based + [Perlu Validasi] | I20: 1 set | J20: 2 | K20: 2 | L20: Generic gasket supplier | M20: Alibaba gasket/O-ring | N20: Market benchmark
A21: 20 | B21: VoltBattery | C21: Mechanical pack | D21: Handle system | E21: Carrying handle | F21: Handle grip, hinge, screw, reinforcement bracket | G21: Memudahkan swapping manual | H21: Document-based | I21: 1 pcs | J21: 1.5 | K21: 1.5 | L21: Custom / generic | M21: Alibaba handle | N21: [Inference]
A22: 21 | B22: VoltBattery | C22: Mechanical pack | D22: Locking mechanism | E22: Mechanical lock | F22: Latch, spring, lock pin, keying structure | G22: Mengunci baterai di motor/station | H22: Document-based | I22: 1 set | J22: 2 | K22: 2 | L22: Custom latch/spring | M22: Alibaba lock mech | N22: Market benchmark
A23: 22 | B23: VoltBattery | C23: Mechanical pack | D23: Fastener | E23: Assembly hardware | F23: Screw, bolt, nut, washer, insert brass | G23: Merakit casing dan modul internal | H23: [Inference] | I23: 1 set | J23: 1 | K23: 1 | L23: Generic hardware | M23: Alibaba fastener | N23: [Inference]
... A49: 73 | B49: VoltOS | C49: Reliability | D49: Offline mode | E49: Store-forward system | F49: Local cache, retry queue, conflict resolution | G49: Tetap aman saat internet mati | H49: Document-based | I49: 1 module | J49: 0 | K49: 0 | L49: Internal dev | M49: — | N49: Dev cost
A50: 74 | B50: VoltGrid | C50: Energy source | D50: PV input | E50: Solar PV array | F50: PV module, mounting rail, cable, MC4 connector | G50: Sumber energi terbarukan | H50: Document-based | I50: 4 pcs | J50: 85 | K50: =LEFT(I50,FIND(" ",I50)-1)*J50 -> 340 | L50: JA Solar / LONGi / Trina | M50: Alibaba solar panel | N50: Market benchmark
A51: 75 | B51: VoltGrid | C51: Energy source | D51: Optional generation | E51: Wind/hydro/genset | F51: Turbine/genset, rectifier/controller, AC/DC interface | G51: Sumber energi tambahan | H51: Document-based | I51: 1 set | J51: 500 | K51: 500 | L51: Honda / generic genset | M51: Alibaba genset | N51: Market benchmark
A52: 76 | B52: VoltGrid | C52: Power conditioning | D52: MPPT | E52: Solar charge controller | F52: MPPT controller, DC breaker, surge protection | G52: Optimasi charging dari PV | H52: Document-based | I52: 1 pcs | J52: 120 | K52: 120 | L52: Victron / EPEver / Renogy | M52: Renogy MPPT | N52: Market benchmark
A53: 77 | B53: VoltGrid | C53: Battery storage | D53: Second-life rack | E53: Grade B battery module | F53: Reused pack/module, rack tray, module connector | G53: Penyimpanan energi | H53: Document-based | I53: 10 kWh | J53: 70 | K53: =LEFT(I53,FIND(" ",I53)-1)*J53 -> 700 | L53: VOLTLOOP second-life | M53: BNEF stationary storage | N53: Source-based (BNEF)
A54: 78 | B54: VoltGrid | C54: Battery storage | D54: Rack structure | E54: Battery rack | F54: Steel rack, tray, rail, clamp, fastener | G54: Menahan modul baterai | H54: Document-based | I54: 1 set | J54: 80 | K54: 80 | L54: Generic steel/welding | M54: Alibaba battery rack | N54: Market benchmark
A55: 79 | B55: VoltGrid | C55: Battery storage | D55: Battery integration | E55: DC bus system | F55: DC busbar, fuse, breaker, contactor, cable lug | G55: Menghubungkan modul ke inverter | H55: [Inference] | I55: 1 set | J55: 50 | K55: 50 | L55: Generic busbar/fuse | M55: Alibaba DC busbar | N55: [Inference]
A56: 80 | B56: VoltGrid | C56: Battery management | D56: Rack BMS | E56: BMS/EMS interface | F56: BMS master, slave BMS, sensor harness | G56: Monitoring modul second-life | H56: Document-based + [Inference] | I56: 1 pcs | J56: 35 | K56: 35 | L56: Daly / JBD / Seplos | M56: Alibaba rack BMS | N56: Market benchmark
A57: 81 | B57: VoltGrid | C57: Power conversion | D57: Inverter/charger | E57: Hybrid inverter | F57: DC/AC inverter, charger, transfer switch | G57: Mengubah DC ke AC dan charging | H57: Document-based | I57: 1 pcs | J57: 350 | K57: 350 | L57: Growatt / Deye / Victron | M57: Alibaba hybrid inverter | N57: Market benchmark
A58: 82 | B58: VoltGrid | C58: Power conversion | D58: PCS | E58: Power conversion system | F58: Inverter module, DC link capacitor, IGBT/MOSFET stage | G58: Konversi daya utama | H58: [Inference] | I58: 1 pcs | J58: 97.5 | K58: 97.5 | L58: Per kW — NREL ATB | M58: NREL ATB 2024 | N58: Source-based (NREL)
A59: 83 | B59: VoltGrid | C59: Control | D59: EMS | E59: Energy management system | F59: Controller, load priority logic, dispatch algorithm | G59: Mengatur energi dan beban | H59: Document-based | I59: 1 pcs | J59: 200 | K59: 200 | L59: Custom / Schneider | M59: Alibaba EMS controller | N59: Market benchmark
A60: 84 | B60: VoltGrid | C60: Protection | D60: DC protection | E60: DC safety panel | F60: DC MCB/fuse, SPD, isolator, contactor | G60: Proteksi sisi DC | H60: Document-based | I60: 1 set | J60: 40 | K60: 40 | L60: Schneider / ABB | M60: Alibaba DC panel | N60: Market benchmark
A61: 85 | B61: VoltGrid | C61: Protection | D61: AC protection | E61: AC distribution panel | F61: MCB, MCCB, relay, ELCB, grounding bar | G61: Proteksi sisi AC | H61: Document-based | I61: 1 set | J61: 60 | K61: 60 | L61: Schneider / ABB / Chint | M61: Alibaba AC panel | N61: Market benchmark
A62: 86 | B62: VoltGrid | C62: Protection | D62: Relay coordination | E62: Protection relay | F62: Over/under voltage relay, frequency relay, islanding relay | G62: Proteksi grid/microgrid | H62: [Inference] | I62: 1 set | J62: 45 | K62: 45 | L62: ABB / Schneider relay | M62: Alibaba protection relay | N62: [Inference]
A63: 87 | B63: VoltGrid | C63: Monitoring | D63: Local monitoring | E63: HMI/display | F63: Meter, screen, local dashboard | G63: Monitoring lokal | H63: Document-based | I63: 1 set | J63: 30 | K63: 30 | L63: Generic meter/display | M63: Alibaba HMI display | N63: Market benchmark
A64: 88 | B64: VoltGrid | C64: Monitoring | D64: Remote monitoring | E64: IoT gateway | F64: Modem, SIM, antenna, edge gateway | G64: Monitoring jarak jauh | H64: Document-based | I64: 1 pcs | J64: 45 | K64: 45 | L64: Same as VoltOS gateway | M64: Alibaba IoT gateway | N64: Market benchmark
A65: 89 | B65: VoltGrid | C65: Load system | D65: Critical load | E65: Priority load panel | F65: Health center, communication, water pump connection | G65: Beban prioritas | H65: Document-based | I65: 1 panel | J65: 25 | K65: 25 | L65: Local electrician | M65: — | N65: Installation scope
... A77: 101 | B77: Recycling Loop | C77: Partner system | D77: Certified recycler | E77: External partner | F77: Recycler permit, MoU, treatment cost, recovery yield | G77: Eksekusi recycle legal | H77: [Unverified] | I77: per batch | J77: 0 | K77: 0 | L77: TBD recycler partner | M77: — | N77: [Unverified] — RFQ needed
H79: SUBTOTAL VoltBattery (per pack) | K79: =SUM(K2:K27) -> 155.52
H80: SUBTOTAL VoltOS (per station hardware) | K80: =SUM(K28:K49) -> 108
H81: SUBTOTAL VoltGrid (per 10kWh system) | K81: =SUM(K50:K69) -> 3132.5
H82: SUBTOTAL Recycling Loop (per facility) | K82: =SUM(K70:K77) -> 335
H84: GRAND TOTAL (all categories) | K84: =SUM(K79:K82) -> 3731.02 | L84: =K84*18000 -> 67158360

Sheet System_Architecture
A1: VOLTLOOP SYSTEM ARCHITECTURE (G21)
A2: Block-level power + data interfaces | DF-0.9 / TRL 3 | All specs [Assumption] pending prototype validation
A4: POWER FLOW ARCHITECTURE
A5: From | B5: To | C5: Type | D5: Voltage | E5: Current (max) | F5: Power | G5: Connector | H5: Notes
A6: Grid AC (PLN) | B6: VoltSwap PDU | C6: AC 1-ph / 3-ph | D6: 220V / 380V AC | E6: 32A per phase | F6: 7-22 kW | G6: MCB/RCBO + terminal block | H6: PUIL 2011 compliant. SPD Type 2 AC at inlet.
A7: VoltSwap Charger | B7: SBP (per slot) | C7: DC CC/CV | D7: 42-54.6V DC | E7: 16A (0.5C) | F7: ~870W per slot | G7: Docking connector (ICD) | H7: 13s CC/CV profile. 6 slots x 870W = 5.2kW total.
A8: SBP (charged) | B8: EV Motorcycle | C8: DC discharge | D8: 32.5-54.6V DC | E8: 60A cont (BMS limit) | F8: ~2.8kW peak | G8: Vehicle docking connector | H8: 13s6p NMC 21700. BMS 60A cutoff. See ICD_Connector.
A9: SBP (2nd life) | B9: VoltGrid Rack | C9: DC parallel bus | D9: 42-54.6V DC | E9: 20A per pack | F9: ~1kW per pack | G9: Anderson SB50/75 or equiv | H9: 2nd-life packs at 70-80% SOH. Parallel bus via DC fused combiner.
A10: VoltGrid PCS | B10: Local Load / Grid | C10: AC (bidirectional) | D10: 220V AC 1-ph | E10: 45A | F10: 10kW | G10: AC MCCB + CT metering | H10: 48V hybrid inverter (Deye/Growatt class). Grid-tied or off-grid mode.
A11: Grid AC (PLN) | B11: VoltGrid PCS | C11: AC (charge from grid) | D11: 220V AC | E11: 45A | F11: 10kW | G11: Same PCS bidirectional port | H11: Arbitrage / TOU charging. Anti-islanding required for grid-tied.
A13: COMMUNICATION ARCHITECTURE
A14: Link | B14: Protocol | C14: Physical Layer | D14: Data Rate | E14: Payload | F14: Direction | G14: Latency Req | H14: Notes
A15: SBP BMS - VoltSwap | B15: CAN 2.0B | C15: CAN-H/CAN-L (twisted pair) | D15: 250 kbps | E15: SOC, V, I, Temp, Cycle#, Fault | F15: Bidirectional | G15: <100ms | H15: Via docking connector signal pins. HVIL on same harness.
A16: SBP NFC/BLE - Rider App | B16: NFC (ISO 14443) + BLE 5.0 | C16: NFC antenna + BLE radio | D16: NFC: 424 kbps / BLE: 2 Mbps | E16: Battery ID, SOH, passport URL | F16: SBP to phone | G16: Tap (<1s) | H16: NFC for ID swap; BLE for richer SOH/passport display.
A17: VoltSwap Ctrl - VoltOS | B17: Modbus TCP / MQTT | C17: Ethernet (RJ45 or WiFi) | D17: 100 Mbps | E17: Slot status, charger state, swap events, kWh | F17: Bidirectional | G17: <500ms | H17: VoltOS polls or subscribes. Local Ethernet preferred; WiFi fallback.
A18: VoltGrid Ctrl - VoltOS | B18: Modbus TCP | C18: Ethernet (RJ45) | D18: 100 Mbps | E18: PCS state, SOC aggregate, kWh in/out, alarms | F18: Bidirectional | G18: <1s | H18: Standard Modbus register map. PCS native Modbus RTU bridged to TCP by VoltOS.
A19: VoltOS - Cloud (VoltOS SaaS) | B19: MQTT 3.1.1 / REST API | C19: 4G LTE / WiFi | D19: Variable | E19: Telemetry, commands, passport, alerts | F19: Bidirectional | G19: <5s (best effort) | H19: TLS encrypted. Store-and-forward if offline. MQTT for telemetry; REST for config.
A20: VoltOS - Energy Meter | B20: Modbus RTU | C20: RS485 (2-wire) | D20: 9600 baud | E20: kWh import/export, V, I, PF | F20: Meter to VoltOS | G20: <2s | H20: Class 1 accuracy meter (CT-based). For carbon accounting + billing.
A22: INTERFACE MATRIX (subsystem x subsystem)
A23: P = Power | D = Data | M = Mechanical | T = Thermal
B24: SBP | C24: VoltSwap | D24: VoltGrid | E24: VoltOS | F24: EV / Rider | G24: Grid (PLN) | H24: Cloud
A25: SBP | B25: -- | C25: P D M T | D25: P M | E25: -- | F25: P D M | G25: -- | H25: D (via NFC/BLE)
A26: VoltSwap | B26: P D M T | C26: -- | D26: -- | E26: D | F26: -- | G26: P | H26: D (via VoltOS)
A27: VoltGrid | B27: P M | C27: -- | D27: -- | E27: D | F27: -- | G27: P (bidi) | H27: D (via VoltOS)
A28: VoltOS | B28: -- | C28: D | D28: D | E28: -- | F28: -- | G28: -- | H28: D (MQTT/REST)
A30: SYSTEM BOUNDARY NOTE
A31: Site = 1 VoltSwap + 1 VoltGrid + 2 VoltOS + 18 SBP (reference config from RollUp). Grid connection is single-point AC. All DC is 48V nominal bus. No high-voltage (>60V DC) interfaces in the system.
A32: Safety: HVIL on all power connectors. DC contactor + pre-charge on VoltGrid bus. Vent valve on each SBP. SPD DC+AC at grid entry. Emergency stop at VoltSwap + VoltGrid.

Sheet Architecture_Trade_Study
A1: VOLTLOOP — BATTERY ARCHITECTURE TRADE STUDY
A2: Gap G01 closure | Design Freeze Decision: 48V (13s6p) vs 72V (20s~4p) | DF-0.9 TRL-3
A3: Author: [TBD] | B3: Date: [TBD] | C3: Decision status: PROVISIONAL — awaiting systems engineer sign-off
A5: 1. BACKGROUND
A6: The SBP BOM specifies '13s 60A BMS' and '13s6p NMC 21700 (48V 30Ah, 1.44 kWh)'. The Master Input Data sheet independently stated '72V × 20Ah / 1000 = 1.44 kWh', creating a voltage-architecture conflict. Both configurations achieve 1.44 kWh but require completely different BMS, charger, and PCS hardware. This trade study resolves the conflict and provides documented rationale for the design freeze decision.
A8: 2. CONFIGURATION COMPARISON
A10: Parameter | B10: 48V — 13s6p (RECOMMENDED) | C10: 72V — 20s~4p (ALTERNATIVE) | D10: Decision Basis
A11: Cell configuration | B11: 13 series × 6 parallel = 78 cells | C11: 20 series × ~4 parallel = ~80 cells | D11: [Calculated]
A12: Nominal voltage | B12: 13 × 3.63V = 47.2V nominal | C12: 20 × 3.63V = 72.6V nominal | D12: [Calculated from Samsung 50E datasheet]
A13: Max charge voltage | B13: 13 × 4.2V = 54.6V | C13: 20 × 4.2V = 84.0V | D13: [Calculated from Samsung 50E datasheet]
A14: Capacity | B14: 6p × 4.9Ah = 29.4Ah ≈ 30Ah | C14: 4p × 4.9Ah = 19.6Ah ≈ 20Ah | D14: [Calculated]
A15: Energy (nominal) | B15: 47.2V × 29.4Ah = 1.388 kWh ≈ 1.44 kWh | C15: 72.6V × 19.6Ah = 1.423 kWh ≈ 1.44 kWh | D15: [Calculated — both achieve target energy]
A16: Cell count total | B16: 78 cells (13 × 6) | C16: 80 cells (20 × 4) | D16: [Calculated]
A17: Pack continuous discharge current | B17: 6p × 9.8A = 58.8A cont. (1.44 kW @ 24.5V sag) | C17: 4p × 9.8A = 39.2A cont. (2.84 kW @ 72V) | D17: [Samsung SDI INR21700-50E datasheet, 9.8A cont.]
A18: Voltage class (safety) | B18: SELV/PELV region (<60V DC) — standard insulation | C18: Exceeds 60V DC threshold — extra insulation, contactors, arcing rules | D18: [IEC 60364-4-41 / IEC 62619 voltage tier rules]
A19: BMS availability (Indonesia/Asia) | B19: 13s BMS: very wide market — ANT, Daly, JKBMS, Overkill, custom [Assumption] | C19: 20s BMS: narrower market, higher cost [Assumption] | D19: [Market inference — no quotation obtained yet]
A20: Charger availability | B20: 54.6V CC/CV: wide market, Mean Well, Elcon, custom [Assumption] | C20: 84V CC/CV: narrower market [Assumption] | D20: [Market inference — no quotation obtained yet]
A21: PCS/Inverter for VoltGrid | B21: 48V: Standard ESS inverter voltage — Deye, Growatt, Victron, SMA, Luxpower all make 48V hybrid inverters [Inference] | C21: 72V: NO standard ESS inverter at 72V input. Would require DC-DC boost to 48V (efficiency loss ~3-5%) or incompatible — BLOCKING ISSUE [Inference] | D21: [CRITICAL: 72V fails PCS compatibility — see Note 1 below]
... A24: Certification path (IEC 62619) | B24: More precedents at 48V for stationary ESS [Inference] | C24: Fewer precedents; higher complexity due to >60V threshold [Inference] | D24: [IEC 62619:2022 — no formal cost estimate available]
A26: 3. SCORING MATRIX (1=worst, 5=best)
A27: Criterion | B27: Weight | C27: 48V Score | D27: 72V Score | E27: 48V Weighted | F27: 72V Weighted | G27: Rationale
A28: PCS/inverter ecosystem fit | B28: 0.25 | C28: 5 | D28: 1 | E28: =B28*C28 -> 1.25 | F28: =B28*D28 -> 0.25 | G28: 48V = standard ESS. 72V = no standard PCS. [Inference]
A29: BMS component availability | B29: 0.15 | C29: 5 | D29: 3 | E29: =B29*C29 -> 0.75 | F29: =B29*D29 -> 0.45 | G29: Wider market at 13s vs 20s [Assumption]
A30: Charger availability | B30: 0.1 | C30: 5 | D30: 3 | E30: =B30*C30 -> 0.5 | F30: =B30*D30 -> 0.3 | G30: 54.6V more common than 84V [Assumption]
A31: Safety insulation class | B31: 0.15 | C31: 5 | D31: 3 | E31: =B31*C31 -> 0.75 | F31: =B31*D31 -> 0.45 | G31: 48V <60V DC threshold — simpler design [IEC 60364]
A32: Vehicle fleet compatibility | B32: 0.15 | C32: 4 | D32: 3 | E32: =B32*C32 -> 0.6 | F32: =B32*D32 -> 0.45 | G32: Most Indonesian delivery bikes 48V [Assumption — needs fleet survey]
A33: BOM rework risk | B33: 0.1 | C33: 5 | D33: 1 | E33: =B33*C33 -> 0.5 | F33: =B33*D33 -> 0.1 | G33: 48V = current BOM. 72V = full BOM rewrite.
A34: Power delivery (courier use-case) | B34: 0.1 | C34: 3 | D34: 4 | E34: =B34*C34 -> 0.3 | F34: =B34*D34 -> 0.4 | G34: 72V slightly better for cargo hills; 48V adequate for urban [Inference]
A35: TOTAL WEIGHTED SCORE | B35: =SUM(B28:B34) -> 1 | C35: =SUMPRODUCT(B28:B34,C28:C34)/SUM(B28:B34) -> 4.65 | D35: =SUMPRODUCT(B28:B34,D28:D34)/SUM(B28:B34) -> 2.4 | E35: =SUM(E28:E34) -> 4.65 | F35: =SUM(F28:F34) -> 2.4
A37: 4. RECOMMENDATION
A38: ADOPT 48V (13s6p, 1.44 kWh, Samsung INR21700-50E or equivalent). Rationale: (1) BOM already specifies 13s configuration; (2) 48V is the only standard ESS inverter input voltage compatible with VoltGrid PCS — 72V would have NO compatible standard PCS product, requiring costly DC-DC converter; (3) 48V stays below 60V DC safe-voltage threshold, simplifying insulation, connector ratings, and safety certification; (4) wider BMS/charger supplier ecosystem in Indonesia/Asia.
A39: ACTION REQUIRED: (a) Update Master Input Data to remove '72V × 20Ah' — replace with '48V × 30Ah (13s6p)'. (b) Systems engineer to sign off on this document. (c) Lock battery voltage in Assumptions sheet. (d) Confirm target vehicle fleet voltage with deployment team.
A41: 5. OPEN QUESTIONS / RISKS
A42: Q1: Samsung 50E has only 9.8A continuous per cell → 58.8A pack. If delivery bikes need >2 kW sustained (hills), consider Samsung INR21700-50S (45A/cell) or Molicel P42A at ~20% cost premium. [TBD — confirm vehicle peak power requirement]
A43: Q2: Cell cost — 50E vs 50S: 50E optimises energy; 50S optimises power. Final selection requires target vehicle power curve. [TBD]
A44: Q3: Target vehicle fleet voltage confirmation — survey of Grab/Gojek fleet motorcycle specs needed before procurement. [TBD]
A46: 6. NOTES
A47: Note 1: PCS voltage compatibility — ESS hybrid inverters are designed for 24V, 48V, 96V, or HVDC (200V+) battery banks. A 72V pack at ~84V full charge does not match any standard inverter input. Deye, Growatt, SMA Sunny Island, Victron Multiplus, and Luxpower all specify 48V nominal. A 72V → 48V DC-DC converter would add ~$80–200, introduce 3–5% efficiency loss, and additional failure mode. Sources: Deye SUN-xK-SG04LP3 datasheet, Growatt SPF 5000 spec sheet [Inference — need to verify with actual PCS selected for VoltGrid].
A48: Note 2: All costs and supplier availability in this study are [Assumption/Indicative Market Price] pending formal RFQ. See Procurement_RFQ_List sheet.
A49: Note 3: Cell datasheet reference — Samsung SDI INR21700-50E Spec No. INR21700-50E V1.0 (2018). Nominal cap 4,900 mAh, nom. voltage 3.63V, max charge 4.2V, cont. discharge 9.8A, cycle life ≥80% after 500 cycles at 0.5C/0.2C. [Verified — public datasheet]

Sheet Tech Stack
B1: TECHNOLOGY & PRODUCT STACK
B3: Layer | C3: Layer Name | D3: Component | E3: Description | F3: Vendor/Tool | G3: TKDN %
B4: L1 | C4: Hardware | D4: Battery Swap Cabinet | E4: 6-12 slot modular, IP54, IoT | F4: In-house + OEM partner | G4: 0.4
B5: L1 | C5: Hardware | D5: Microgrid BESS Container | E5: 50-100 kWh 2nd-life + 30 kWp PV + hybrid inverter | F5: Mixed | G5: 0.35
B6: L2 | C6: BMS | D6: Multi-Chemistry BMS | E6: NMC + LFP; tropical thermal mgmt | F6: In-house + Sungrow | G6: 0.25
B7: L3 | C7: Grading | D7: Battery Grading Lab | E7: EIS + capacity + thermal stress | F7: In-house + Maccor/Arbin | G7: 0.2
B8: L4 | C8: AI/ML | D8: Tropical Degradation Model | E8: Trained on 100K+ swap cycles + climate | F8: In-house PyTorch/XGBoost | G8: 1
B9: L5 | C9: Cloud | D9: VoltLoop OS Platform | E9: AWS-hosted; LoRaWAN + 4G edge | F9: AWS (Singapore region) | G9: 0
B10: L6 | C10: Compliance | D10: EU 2023/1542 Passport | E10: UUID + QR + carbon footprint | F10: In-house | G10: 1
B11: L7 | C11: Data SaaS | D11: OEM Dashboard | E11: Battery health + residual value + MRV | F11: In-house Next.js | G11: 1
B14: R&D ROADMAP
B15: Year | C15: Milestone
B16: Y1 | C16: Grading lab MVP; 1 swap hub pilot; BMS prototype
B17: Y2 | C17: AI tropical degradation model v1 (10K+ cycles); 5 hubs + 2 microgrids
B18: Y3 | C18: Battery passport beta; predictive maintenance live
B19: Y4 | C19: Material recovery pilot (Ni/Co/Li resale)
B20: Y5 | C20: ASEAN-compliant battery passport platform; OEM API marketplace

Sheet Requirements_Matrix
A1: VOLTLOOP — SYSTEM REQUIREMENTS MATRIX
A2: Gap G03 closure | Level: System (L0) + Subsystem (L1) | Status: DRAFT — not reviewed | DF-0.9 TRL-3
A3: All requirements are [Assumption] unless marked [Verified]. Owner must review, assign test method, and mark [Baselined] before DF-1.0.
A5: REQ ID | B5: Level | C5: Subsystem | D5: Requirement | E5: Rationale | F5: Target Value / Limit | G5: Verification Method | H5: Test Ref | I5: Status
A6: SYS-001 | B6: L0 | C6: Ecosystem | D6: Battery swap completed in <5 min from arrival to departure | E6: User experience parity with fuelling | F6: <5 minutes total | G6: Time-and-motion study | H6: SYS-T01 | I6: [Assumption]
A7: SYS-002 | B7: L0 | C7: Ecosystem | D7: System shall operate in Indonesia tropical climate: 20–40°C, up to 90% RH, 0–1500m altitude | E7: Deployment environment | F7: MTBF >5000h; no degradation in 40°C/90%RH for 24h soak | G7: Climate chamber test | H7: SBP-T08 | I7: [Assumption]
A8: SYS-003 | B8: L0 | C8: Ecosystem | D8: VoltLoop system shall not pose thermal runaway propagation risk between adjacent battery packs in a swap station | E8: IEC 62619:2022 thermal runaway propagation test requirement | F8: Thermal event in one pack shall not propagate to adjacent pack within 30 minutes (minimum) | G8: Calorimeter / thermocouple array test (TRL 5+) | H8: TRL 5 | I8: [TBD — TRL 5 scope]
A9: SYS-004 | B9: L0 | C9: Ecosystem | D9: All battery products shall target IEC 62619:2022 compliance path for VoltGrid ESS application | E9: Market access, insurance, investor requirement | F9: IEC 62619:2022 certification plan in place before Series A | G9: Certification audit | H9: — | I9: [TBD]
A10: SBP-001 | B10: L1 | C10: Smart Battery Pack | D10: Battery pack nominal energy ≥1.4 kWh | E10: Delivery bike range requirement | F10: 1.44 kWh (13s6p × 4.9Ah × 3.63V) | G10: Capacity test | H10: SBP-T01 | I10: [Calculated — pending cell test]
A11: SBP-002 | B11: L1 | C11: Smart Battery Pack | D11: Battery voltage architecture: 48V nominal (13s NMC 21700) | E11: See Architecture_Trade_Study | F11: Nominal 47.2V; max 54.6V; cutoff 32.5V | G11: Architecture_Trade_Study sign-off | H11: — | I11: [Provisional — awaiting sign-off]
A12: SBP-003 | B12: L1 | C12: Smart Battery Pack | D12: Pack continuous discharge ≥30A @ nominal voltage | E12: Delivery bike 1.44kW motor + accessories | F12: ≥30A continuous; ≥60A peak 30s | G12: Discharge test at 30A for 30 min | H12: SBP-T03 | I12: [Assumption — needs vehicle motor spec]
A13: SBP-004 | B13: L1 | C13: Smart Battery Pack | D13: BMS shall protect against: OVP, UVP, OCP, OTP, short circuit | E13: Cell safety; IEC 62619 | F13: OVP: 4.25V/cell; UVP: 3.0V/cell; OCP: 78A (130% rated); OTP: 60°C cell surface | G13: BMS protection test | H13: SBP-T04 | I13: [Assumption — pending BMS selection]
A14: SBP-005 | B14: L1 | C14: Smart Battery Pack | D14: Pack IP rating: IP54 minimum | E14: Outdoor tropical environment; rain splash, dust | F14: IP54 (IEC 60529) | G14: IP ingress test or supplier cert | H14: — | I14: [TBD — enclosure design pending]
A15: SBP-006 | B15: L1 | C15: Smart Battery Pack | D15: Pack mass: ≤12 kg | E15: Manual handling by courier | F15: ≤12 kg (cells + BMS + enclosure + connector) | G15: Weighing at proto build | H15: — | I15: [Assumption — CAD mass not yet calculated]
A16: SBP-007 | B16: L1 | C16: Smart Battery Pack | D16: Vent valve or pressure relief required on enclosure | E16: Safety: gas venting during thermal event; IEC 62619 | F16: Vent valve rated for minimum 10 kPa over-pressure; must not block in humid conditions | G16: Pressure test; humidity exposure | H16: — | I16: [Missing — add to SBP_BOM immediately]
... A26: OS-002 | B26: L1 | C26: VoltOS Edge | D26: VoltOS shall display SoC to courier via terminal with ±5% accuracy | E26: User experience; swap decision | F26: SoC ±2% vs BMS coulomb count; display refresh <2s | G26: Software test | H26: OS-T01 | I26: [Assumption]
A28: REQUIREMENTS SUMMARY
A29: ="Total requirements: "&COUNTA(A6:A26) -> Total requirements: 21
A30: Baselined: 0
A31: TBD/Unverified: majority
A32: NOTE: This matrix is Level 0/1 only. Sub-assembly requirements (L2/L3) are [Missing] and must be developed for DF-1.0 and before any formal supplier qualification.

Sheet ICD_Connector
A1: VOLTLOOP — INTERFACE CONTROL DOCUMENT: SWAP CONNECTOR (ICD-SWP-001)
A2: Gap G03 closure | Interface: SBP ↔ VoltSwap docking | Rev: 0.1 DRAFT | DF-0.9
A3: All specs marked [Assumption] unless noted. Connector supplier TBD — must be RFQ'd. See Procurement_RFQ_List.
A5: 1. INTERFACE OVERVIEW
A6: This ICD defines the mechanical, electrical, and communication interface between the Smart Battery Pack (SBP) and the VoltSwap Station docking bay. The connector must support: (1) high-current power transfer, (2) BMS signal/CAN communication, (3) HVIL safety interlock, (4) physical guide and alignment, (5) environmental sealing, (6) 100–500 mating cycle life.
A7: Source references: Industry standard 100–500 maintenance cycles for internal pack hybrid connectors (renhotecev.com, 2026); HVIL signal-first disconnect industry practice (renhotecev.com, 2026).
A9: 2. CONNECTOR INTERFACE SPECIFICATION
A11: Parameter | B11: Requirement | C11: Rationale | D11: Status
A12: Voltage rating | B12: ≥60V DC (SELV limit for 48V system at max 54.6V) | C12: 48V system; IEC 60364 SELV threshold | D12: [Assumption]
A13: Continuous current rating (power pins) | B13: ≥120A continuous [as per BOM spec] | C13: Supports 2C charge (58.8A) + headroom; consistent with BOM | D13: [Assumption — BOM spec; verify vs actual charge rate]
A14: Peak current rating | B14: ≥200A for 30s | C14: Motor inrush; future higher-C charging | D14: [Assumption]
A15: Signal pins | B15: Minimum 4 pins: CAN-H, CAN-L, HVIL-A, HVIL-B | C15: BMS CAN communication + HVIL interlock | D15: [Assumption]
A16: HVIL interlock logic | B16: HVIL signal pins break BEFORE power pins on disconnect; make AFTER power pins on connect (signal-first design) | C16: Prevents arcing on hot-plug; industry standard practice [renhotecev.com 2026] | D16: [Assumption — to be validated in SBP-T06]
A17: Mating cycle life | B17: ≥300 mate/unmate cycles with <5% contact resistance increase | C17: Industry std 100–500 cycles [renhotecev.com 2026]; 300 = ~1 swap/day for 1 year | D17: [Assumption]
A18: IP rating (mated) | B18: IP54 minimum (mated condition) | C18: Tropical outdoor use; rain splash, dust | D18: [Assumption]
A19: IP rating (unmated / stowed) | B19: IP44 minimum (unmated, pack out of bay) | C19: Pack exposed during handling | D19: [Assumption]
